Workbook

Sheet Iluminacion y ventilacion
A1: PLANILLA DE ILUMINACION Y VENTILACION
A2: Local | B2: (a) Medidas | C2: (b) Medidas | D2: (Area) Medidas | E2: Iluminacion | H2: Ventilacion | K2: VERIFICACION | L2: OBSERVACIONES
E3: Coef. | F3: Area requerida | G3: Area proyectada | H3: Coef. | I3: Area requerida | J3: Area proyectada
A4: PB
A5: 01 - Cocina / comedor | B5: 7.63 | C5: 3.56 | D5: =B5*C5 -> 27.1628 | E5: 9 | F5: =D5/E5 -> 3.0180889 | G5: 16.95 | H5: i/3 | I5: =F5/3 -> 1.0060296 | J5: 8.48 | K5: =IF(OR(G5="COND",J5="COND"),"COND",IF(AND(G5>=F5,J5>=I5),"CUMPLE","NO CUMPLE")) -> CUMPLE
A6: 02 - Deposito | B6: 3.8 | C6: 3.1 | D6: =B6*C6 -> 11.78 | E6: - | F6: - | G6: - | H6: - | I6: - | J6: - | K6: NO EXIGIBLE | L6: Local no habitable: el codigo no le exige iluminacion ni ventilacion natural. Si se lo considera habitable, hay que preverle conducto.
A7: 03 - Lavadero | B7: 3.5 | C7: 1.7 | D7: =B7*C7 -> 5.95 | E7: 9 | F7: =D7/E7 -> 0.66111111 | G7: 10.5 | H7: i/3 | I7: =F7/3 -> 0.22037037 | J7: 1.6 | K7: =IF(OR(G7="COND",J7="COND"),"COND",IF(AND(G7>=F7,J7>=I7),"CUMPLE","NO CUMPLE")) -> CUMPLE
A8: 06 - Living / comedor | B8: 8.66 | C8: 4.06 | D8: =B8*C8 -> 35.1596 | E8: 9 | F8: =D8/E8 -> 3.9066222 | G8: 34.05 | H8: i/3 | I8: =F8/3 -> 1.3022074 | J8: 15 | K8: =IF(OR(G8="COND",J8="COND"),"COND",IF(AND(G8>=F8,J8>=I8),"CUMPLE","NO CUMPLE")) -> CUMPLE
A9: 07 - Hall / ingreso | B9: 4 | C9: 2.15 | D9: =B9*C9 -> 8.6 | E9: 9 | F9: =D9/E9 -> 0.95555556 | G9: 10.5 | H9: i/3 | I9: =F9/3 -> 0.31851852 | J9: 1.6 | K9: =IF(OR(G9="COND",J9="COND"),"COND",IF(AND(G9>=F9,J9>=I9),"CUMPLE","NO CUMPLE")) -> CUMPLE | L9: CORREGIDO: la planilla original repetia los valores del local 03 (0,66 y 0,22). Con 4,00 x 2,15 = 8,60 m2 corresponden 0,96 y 0,32. Cumple igual.
A10: 09 - Dormitorio suite | B10: 3.5 | C10: 3.5 | D10: =B10*C10 -> 12.25 | E10: 9 | F10: =D10/E10 -> 1.3611111 | G10: 6 | H10: i/3 | I10: =F10/3 -> 0.4537037 | J10: 3 | K10: =IF(OR(G10="COND",J10="COND"),"COND",IF(AND(G10>=F10,J10>=I10),"CUMPLE","NO CUMPLE")) -> CUMPLE
A11: 10 - Bano suite | B11: 3.38 | C11: 1.72 | D11: =B11*C11 -> 5.8136 | E11: 9 | F11: =D11/E11 -> 0.64595556 | G11: COND | H11: i/3 | I11: =F11/3 -> 0.21531852 | J11: COND | K11: =IF(OR(G11="COND",J11="COND"),"COND",IF(AND(G11>=F11,J11>=I11),"CUMPLE","NO CUMPLE")) -> COND | L11: Sin ventana al exterior: se ventila por conducto o extraccion mecanica.
A12: 11 - Bano visita | B12: 2.4 | C12: 1.3 | D12: =B12*C12 -> 3.12 | E12: 9 | F12: =D12/E12 -> 0.34666667 | G12: COND | H12: i/3 | I12: =F12/3 -> 0.11555556 | J12: COND | K12: =IF(OR(G12="COND",J12="COND"),"COND",IF(AND(G12>=F12,J12>=I12),"CUMPLE","NO CUMPLE")) -> COND | L12: Sin ventana al exterior: se ventila por conducto o extraccion mecanica.
A13: 12 - Bano exterior | B13: 1.9 | C13: 0.95 | D13: =B13*C13 -> 1.805 | E13: 9 | F13: =D13/E13 -> 0.20055556 | G13: COND | H13: i/3 | I13: =F13/3 -> 0.066851852 | J13: COND | K13: =IF(OR(G13="COND",J13="COND"),"COND",IF(AND(G13>=F13,J13>=I13),"CUMPLE","NO CUMPLE")) -> COND | L13: Sin ventana al exterior: se ventila por conducto o extraccion mecanica.
A14: PA
A15: 13 - Dormitorio 1 | B15: 4.25 | C15: 4 | D15: =B15*C15 -> 17 | E15: 9 | F15: =D15/E15 -> 1.8888889 | G15: 8.75 | H15: i/3 | I15: =F15/3 -> 0.62962963 | J15: 4.38 | K15: =IF(OR(G15="COND",J15="COND"),"COND",IF(AND(G15>=F15,J15>=I15),"CUMPLE","NO CUMPLE")) -> CUMPLE
A16: 14 - Estar / Playroom | B16: 4.13 | C16: 4.08 | D16: =B16*C16 -> 16.8504 | E16: 9 | F16: =D16/E16 -> 1.8722667 | G16: 5 | H16: i/3 | I16: =F16/3 -> 0.62408889 | J16: 5 | K16: =IF(OR(G16="COND",J16="COND"),"COND",IF(AND(G16>=F16,J16>=I16),"CUMPLE","NO CUMPLE")) -> CUMPLE | L16: La superficie abrible declarada iguala a la vidriada: supondria una carpinteria 100% abrible. En el resto de los locales la relacion es del 50%. Verificar.
A17: 15 - Dormitorio 2 | B17: 3.5 | C17: 4.05 | D17: =B17*C17 -> 14.175 | E17: 9 | F17: =D17/E17 -> 1.575 | G17: 3.75 | H17: i/3 | I17: =F17/3 -> 0.525 | J17: 1.88 | K17: =IF(OR(G17="COND",J17="COND"),"COND",IF(AND(G17>=F17,J17>=I17),"CUMPLE","NO CUMPLE")) -> CUMPLE
A18: 17 - Bano | B18: 2.2 | C18: 1.6 | D18: =B18*C18 -> 3.52 | E18: 9 | F18: =D18/E18 -> 0.39111111 | G18: 1.875 | H18: i/3 | I18: =F18/3 -> 0.13037037 | J18: 0.94 | K18: =IF(OR(G18="COND",J18="COND"),"COND",IF(AND(G18>=F18,J18>=I18),"CUMPLE","NO CUMPLE")) -> CUMPLE
A20: En amarillo, las medidas corregidas al relevar los locales para el balance termico.

Sheet Planilla 3 higrotermica
B1: Municipalidad de Rosario | M1: ORDENANZA N 8757/11
B2: Secretaria de Planeamiento - Programa de Construcciones Sustentables y Eficiencia Energetica
B3: Solicitud del Certificado de Aspectos Higrotermicos y Eficiencia Energetica de las Construcciones
A4: PLANILLA 3: Verificacion de transmitancia termica y factor de exposicion solar de cerramientos transparentes.
A5: Descripcion | B5: Altura del vano | C5: Ancho del vano | D5: Area del vano | E5: Area total vanos (m2) | F5: Porcentaje sup. de vanos | G5: Transmit. Max. [W/m2K] | H5: Tipo de vidrio | I5: Tipo de proteccion | J5: Transmit. [W/m2K] | K5: Orientacion | L5: Factor de Expos. Solar | M5: VERIFICACION
A6: Plano: Fachada Noreste
A7: PA02 | B7: 3 | C7: 0.75 | D7: =IF(COUNT(B7,C7)<2,"",B7*C7) -> 2.25 | E7: =SUM(D7:D13) -> 12.9225 | F7: =IF(OR(D7="",$E$7=""),"",D7/$E$7) -> 0.17411492 | G7: =IF(A7="","",Datos_higro!$B$4) -> 2.9 | H7: DVH 6+9+3+3 (aluminio linea A30) | I7: Sin Proteccion | J7: 2.8 | K7: Noreste | L7: =IF(I7="","",IFERROR(VLOOKUP(I7,Datos_higro!$A$21:$B$28,2,0),"")) -> 0.88 | M7: =IF(OR(D7="",J7=""),"",IF(J7<=G7,"CUMPLE","NO CUMPLE")) -> CUMPLE
A8: VA02 | B8: 2.15 | C8: 0.75 | D8: =IF(COUNT(B8,C8)<2,"",B8*C8) -> 1.6125 | F8: =IF(OR(D8="",$E$7=""),"",D8/$E$7) -> 0.12478236 | G8: =IF(A8="","",Datos_higro!$B$4) -> 2.9 | H8: DVH 6+9+3+3 (aluminio linea A30) | I8: Sin Proteccion | J8: 2.8 | K8: Noreste | L8: =IF(I8="","",IFERROR(VLOOKUP(I8,Datos_higro!$A$21:$B$28,2,0),"")) -> 0.88 | M8: =IF(OR(D8="",J8=""),"",IF(J8<=G8,"CUMPLE","NO CUMPLE")) -> CUMPLE
A9: PV03 | B9: 3 | C9: 1.76 | D9: =IF(COUNT(B9,C9)<2,"",B9*C9) -> 5.28 | F9: =IF(OR(D9="",$E$7=""),"",D9/$E$7) -> 0.40858967 | G9: =IF(A9="","",Datos_higro!$B$4) -> 2.9 | H9: DVH 6+9+3+3 (aluminio linea A30) | I9: Sin Proteccion | J9: 2.8 | K9: Noreste | L9: =IF(I9="","",IFERROR(VLOOKUP(I9,Datos_higro!$A$21:$B$28,2,0),"")) -> 0.88 | M9: =IF(OR(D9="",J9=""),"",IF(J9<=G9,"CUMPLE","NO CUMPLE")) -> CUMPLE
A10: VA03 | B10: 2.52 | C10: 0.75 | D10: =IF(COUNT(B10,C10)<2,"",B10*C10) -> 1.89 | F10: =IF(OR(D10="",$E$7=""),"",D10/$E$7) -> 0.14625653 | G10: =IF(A10="","",Datos_higro!$B$4) -> 2.9 | H10: DVH 6+9+3+3 (aluminio linea A30) | I10: Sin Proteccion | J10: 2.8 | K10: Noreste | L10: =IF(I10="","",IFERROR(VLOOKUP(I10,Datos_higro!$A$21:$B$28,2,0),"")) -> 0.88 | M10: =IF(OR(D10="",J10=""),"",IF(J10<=G10,"CUMPLE","NO CUMPLE")) -> CUMPLE
A11: PF05 | B11: 2.52 | C11: 0.75 | D11: =IF(COUNT(B11,C11)<2,"",B11*C11) -> 1.89 | F11: =IF(OR(D11="",$E$7=""),"",D11/$E$7) -> 0.14625653 | G11: =IF(A11="","",Datos_higro!$B$4) -> 2.9 | H11: DVH 6+9+3+3 (aluminio linea A30) | I11: Sin Proteccion | J11: 2.8 | K11: Noreste | L11: =IF(I11="","",IFERROR(VLOOKUP(I11,Datos_higro!$A$21:$B$28,2,0),"")) -> 0.88 | M11: =IF(OR(D11="",J11=""),"",IF(J11<=G11,"CUMPLE","NO CUMPLE")) -> CUMPLE
D12: =IF(COUNT(B12,C12)<2,"",B12*C12) | F12: =IF(OR(D12="",$E$7=""),"",D12/$E$7) | G12: =IF(A12="","",Datos_higro!$B$4) | L12: =IF(I12="","",IFERROR(VLOOKUP(I12,Datos_higro!$A$21:$B$28,2,0),"")) | M12: =IF(OR(D12="",J12=""),"",IF(J12<=G12,"CUMPLE","NO CUMPLE"))
D13: =IF(COUNT(B13,C13)<2,"",B13*C13) | F13: =IF(OR(D13="",$E$7=""),"",D13/$E$7) | G13: =IF(A13="","",Datos_higro!$B$4) | L13: =IF(I13="","",IFERROR(VLOOKUP(I13,Datos_higro!$A$21:$B$28,2,0),"")) | M13: =IF(OR(D13="",J13=""),"",IF(J13<=G13,"CUMPLE","NO CUMPLE"))
A14: Plano: Fachada Sudoeste
A15: PA01 | B15: 3 | C15: 1 | D15: =IF(COUNT(B15,C15)<2,"",B15*C15) -> 3 | E15: =SUM(D15:D21) -> 19.77 | F15: =IF(OR(D15="",$E$15=""),"",D15/$E$15) -> 0.15174507 | G15: =IF(A15="","",Datos_higro!$B$4) -> 2.9 | H15: DVH 6+9+3+3 (aluminio linea A30) | I15: Sin Proteccion | J15: 2.8 | K15: Sudoeste | L15: =IF(I15="","",IFERROR(VLOOKUP(I15,Datos_higro!$A$21:$B$28,2,0),"")) -> 0.88 | M15: =IF(OR(D15="",J15=""),"",IF(J15<=G15,"CUMPLE","NO CUMPLE")) -> CUMPLE
A16: PF01 | B16: 3 | C16: 3.55 | D16: =IF(COUNT(B16,C16)<2,"",B16*C16) -> 10.65 | F16: =IF(OR(D16="",$E$15=""),"",D16/$E$15) -> 0.53869499 | G16: =IF(A16="","",Datos_higro!$B$4) -> 2.9 | H16: DVH 6+9+3+3 (aluminio linea A30) | I16: Sin Proteccion | J16: 2.8 | K16: Sudoeste | L16: =IF(I16="","",IFERROR(VLOOKUP(I16,Datos_higro!$A$21:$B$28,2,0),"")) -> 0.88 | M16: =IF(OR(D16="",J16=""),"",IF(J16<=G16,"CUMPLE","NO CUMPLE")) -> CUMPLE
A17: PF04 | B17: 0.6 | C17: 2.7 | D17: =IF(COUNT(B17,C17)<2,"",B17*C17) -> 1.62 | F17: =IF(OR(D17="",$E$15=""),"",D17/$E$15) -> 0.081942337 | G17: =IF(A17="","",Datos_higro!$B$4) -> 2.9 | H17: DVH 6+9+3+3 (aluminio linea A30) | I17: Sin Proteccion | J17: 2.8 | K17: Sudoeste | L17: =IF(I17="","",IFERROR(VLOOKUP(I17,Datos_higro!$A$21:$B$28,2,0),"")) -> 0.88 | M17: =IF(OR(D17="",J17=""),"",IF(J17<=G17,"CUMPLE","NO CUMPLE")) -> CUMPLE
A18: VA01 | B18: 3 | C18: 0.75 | D18: =IF(COUNT(B18,C18)<2,"",B18*C18) -> 2.25 | F18: =IF(OR(D18="",$E$15=""),"",D18/$E$15) -> 0.1138088 | G18: =IF(A18="","",Datos_higro!$B$4) -> 2.9 | H18: DVH 6+9+3+3 (aluminio linea A30) | I18: Sin Proteccion | J18: 2.8 | K18: Sudoeste | L18: =IF(I18="","",IFERROR(VLOOKUP(I18,Datos_higro!$A$21:$B$28,2,0),"")) -> 0.88 | M18: =IF(OR(D18="",J18=""),"",IF(J18<=G18,"CUMPLE","NO CUMPLE")) -> CUMPLE
A19: VA01 | B19: 3 | C19: 0.75 | D19: =IF(COUNT(B19,C19)<2,"",B19*C19) -> 2.25 | F19: =IF(OR(D19="",$E$15=""),"",D19/$E$15) -> 0.1138088 | G19: =IF(A19="","",Datos_higro!$B$4) -> 2.9 | H19: DVH 6+9+3+3 (aluminio linea A30) | I19: Sin Proteccion | J19: 2.8 | K19: Sudoeste | L19: =IF(I19="","",IFERROR(VLOOKUP(I19,Datos_higro!$A$21:$B$28,2,0),"")) -> 0.88 | M19: =IF(OR(D19="",J19=""),"",IF(J19<=G19,"CUMPLE","NO CUMPLE")) -> CUMPLE
D20: =IF(COUNT(B20,C20)<2,"",B20*C20) | F20: =IF(OR(D20="",$E$15=""),"",D20/$E$15) | G20: =IF(A20="","",Datos_higro!$B$4) | L20: =IF(I20="","",IFERROR(VLOOKUP(I20,Datos_higro!$A$21:$B$28,2,0),"")) | M20: =IF(OR(D20="",J20=""),"",IF(J20<=G20,"CUMPLE","NO CUMPLE"))
D21: =IF(COUNT(B21,C21)<2,"",B21*C21) | F21: =IF(OR(D21="",$E$15=""),"",D21/$E$15) | G21: =IF(A21="","",Datos_higro!$B$4) | L21: =IF(I21="","",IFERROR(VLOOKUP(I21,Datos_higro!$A$21:$B$28,2,0),"")) | M21: =IF(OR(D21="",J21=""),"",IF(J21<=G21,"CUMPLE","NO CUMPLE"))
A22: Plano: Fachada Sudeste
A23: PF02 | B23: 3 | C23: 3.75 | D23: =IF(COUNT(B23,C23)<2,"",B23*C23) -> 11.25 | E23: =SUM(D23:D27) -> 20.958 | F23: =IF(OR(D23="",$E$23=""),"",D23/$E$23) -> 0.53678786 | G23: =IF(A23="","",Datos_higro!$B$4) -> 2.9 | H23: DVH 6+9+3+3 (aluminio linea A30) | I23: Sin Proteccion | J23: 2.8 | K23: Sudeste | L23: =IF(I23="","",IFERROR(VLOOKUP(I23,Datos_higro!$A$21:$B$28,2,0),"")) -> 0.88 | M23: =IF(OR(D23="",J23=""),"",IF(J23<=G23,"CUMPLE","NO CUMPLE")) -> CUMPLE
A24: PV04 | B24: 3 | C24: 2.06 | D24: =IF(COUNT(B24,C24)<2,"",B24*C24) -> 6.18 | F24: =IF(OR(D24="",$E$23=""),"",D24/$E$23) -> 0.29487547 | G24: =IF(A24="","",Datos_higro!$B$4) -> 2.9 | H24: DVH 6+9+3+3 (aluminio linea A30) | I24: Sin Proteccion | J24: 2.8 | K24: Sudeste | L24: =IF(I24="","",IFERROR(VLOOKUP(I24,Datos_higro!$A$21:$B$28,2,0),"")) -> 0.88 | M24: =IF(OR(D24="",J24=""),"",IF(J24<=G24,"CUMPLE","NO CUMPLE")) -> CUMPLE
A25: VA05 | B25: 2.52 | C25: 1.4 | D25: =IF(COUNT(B25,C25)<2,"",B25*C25) -> 3.528 | F25: =IF(OR(D25="",$E$23=""),"",D25/$E$23) -> 0.16833667 | G25: =IF(A25="","",Datos_higro!$B$4) -> 2.9 | H25: DVH 6+9+3+3 (aluminio linea A30) | I25: Sin Proteccion | J25: 2.8 | K25: Sudeste | L25: =IF(I25="","",IFERROR(VLOOKUP(I25,Datos_higro!$A$21:$B$28,2,0),"")) -> 0.88 | M25: =IF(OR(D25="",J25=""),"",IF(J25<=G25,"CUMPLE","NO CUMPLE")) -> CUMPLE
D26: =IF(COUNT(B26,C26)<2,"",B26*C26) | F26: =IF(OR(D26="",$E$23=""),"",D26/$E$23) | G26: =IF(A26="","",Datos_higro!$B$4) | L26: =IF(I26="","",IFERROR(VLOOKUP(I26,Datos_higro!$A$21:$B$28,2,0),"")) | M26: =IF(OR(D26="",J26=""),"",IF(J26<=G26,"CUMPLE","NO CUMPLE"))
D27: =IF(COUNT(B27,C27)<2,"",B27*C27) | F27: =IF(OR(D27="",$E$23=""),"",D27/$E$23) | G27: =IF(A27="","",Datos_higro!$B$4) | L27: =IF(I27="","",IFERROR(VLOOKUP(I27,Datos_higro!$A$21:$B$28,2,0),"")) | M27: =IF(OR(D27="",J27=""),"",IF(J27<=G27,"CUMPLE","NO CUMPLE"))
A28: Plano: Fachada Noroeste
A29: PF03 | B29: 3 | C29: 2.88 | D29: =IF(COUNT(B29,C29)<2,"",B29*C29) -> 8.64 | E29: =SUM(D29:D36) -> 59.91 | F29: =IF(OR(D29="",$E$29=""),"",D29/$E$29) -> 0.14421632 | G29: =IF(A29="","",Datos_higro!$B$4) -> 2.9 | H29: DVH 6+9+3+3 (aluminio linea A30) | I29: Sin Proteccion | J29: 2.8 | K29: Noroeste | L29: =IF(I29="","",IFERROR(VLOOKUP(I29,Datos_higro!$A$21:$B$28,2,0),"")) -> 0.88 | M29: =IF(OR(D29="",J29=""),"",IF(J29<=G29,"CUMPLE","NO CUMPLE")) -> CUMPLE
A30: PF01 | B30: 3 | C30: 3.55 | D30: =IF(COUNT(B30,C30)<2,"",B30*C30) -> 10.65 | F30: =IF(OR(D30="",$E$29=""),"",D30/$E$29) -> 0.17776665 | G30: =IF(A30="","",Datos_higro!$B$4) -> 2.9 | H30: DVH 6+9+3+3 (aluminio linea A30) | I30: Sin Proteccion | J30: 2.8 | K30: Noroeste | L30: =IF(I30="","",IFERROR(VLOOKUP(I30,Datos_higro!$A$21:$B$28,2,0),"")) -> 0.88 | M30: =IF(OR(D30="",J30=""),"",IF(J30<=G30,"CUMPLE","NO CUMPLE")) -> CUMPLE
A31: PV01 | B31: 3 | C31: 7.7 | D31: =IF(COUNT(B31,C31)<2,"",B31*C31) -> 23.1 | F31: =IF(OR(D31="",$E$29=""),"",D31/$E$29) -> 0.38557837 | G31: =IF(A31="","",Datos_higro!$B$4) -> 2.9 | H31: DVH 6+9+3+3 (aluminio linea A30) | I31: Sin Proteccion | J31: 2.8 | K31: Noroeste | L31: =IF(I31="","",IFERROR(VLOOKUP(I31,Datos_higro!$A$21:$B$28,2,0),"")) -> 0.88 | M31: =IF(OR(D31="",J31=""),"",IF(J31<=G31,"CUMPLE","NO CUMPLE")) -> CUMPLE
A32: PV02 | B32: 3 | C32: 2.48 | D32: =IF(COUNT(B32,C32)<2,"",B32*C32) -> 7.44 | F32: =IF(OR(D32="",$E$29=""),"",D32/$E$29) -> 0.12418628 | G32: =IF(A32="","",Datos_higro!$B$4) -> 2.9 | H32: DVH 6+9+3+3 (aluminio linea A30) | I32: Sin Proteccion | J32: 2.8 | K32: Noroeste | L32: =IF(I32="","",IFERROR(VLOOKUP(I32,Datos_higro!$A$21:$B$28,2,0),"")) -> 0.88 | M32: =IF(OR(D32="",J32=""),"",IF(J32<=G32,"CUMPLE","NO CUMPLE")) -> CUMPLE
A33: VA04 | B33: 2.52 | C33: 2 | D33: =IF(COUNT(B33,C33)<2,"",B33*C33) -> 5.04 | F33: =IF(OR(D33="",$E$29=""),"",D33/$E$29) -> 0.084126189 | G33: =IF(A33="","",Datos_higro!$B$4) -> 2.9 | H33: DVH 6+9+3+3 (aluminio linea A30) | I33: Sin Proteccion | J33: 2.8 | K33: Noroeste | L33: =IF(I33="","",IFERROR(VLOOKUP(I33,Datos_higro!$A$21:$B$28,2,0),"")) -> 0.88 | M33: =IF(OR(D33="",J33=""),"",IF(J33<=G33,"CUMPLE","NO CUMPLE")) -> CUMPLE
A34: VA04 | B34: 2.52 | C34: 2 | D34: =IF(COUNT(B34,C34)<2,"",B34*C34) -> 5.04 | F34: =IF(OR(D34="",$E$29=""),"",D34/$E$29) -> 0.084126189 | G34: =IF(A34="","",Datos_higro!$B$4) -> 2.9 | H34: DVH 6+9+3+3 (aluminio linea A30) | I34: Sin Proteccion | J34: 2.8 | K34: Noroeste | L34: =IF(I34="","",IFERROR(VLOOKUP(I34,Datos_higro!$A$21:$B$28,2,0),"")) -> 0.88 | M34: =IF(OR(D34="",J34=""),"",IF(J34<=G34,"CUMPLE","NO CUMPLE")) -> CUMPLE
D35: =IF(COUNT(B35,C35)<2,"",B35*C35) | F35: =IF(OR(D35="",$E$29=""),"",D35/$E$29) | G35: =IF(A35="","",Datos_higro!$B$4) | L35: =IF(I35="","",IFERROR(VLOOKUP(I35,Datos_higro!$A$21:$B$28,2,0),"")) | M35: =IF(OR(D35="",J35=""),"",IF(J35<=G35,"CUMPLE","NO CUMPLE"))
D36: =IF(COUNT(B36,C36)<2,"",B36*C36) | F36: =IF(OR(D36="",$E$29=""),"",D36/$E$29) | G36: =IF(A36="","",Datos_higro!$B$4) | L36: =IF(I36="","",IFERROR(VLOOKUP(I36,Datos_higro!$A$21:$B$28,2,0),"")) | M36: =IF(OR(D36="",J36=""),"",IF(J36<=G36,"CUMPLE","NO CUMPLE"))
A37: HOJA REHECHA: las orientaciones se tomaron del plano de fachadas y cambiaron casi todas. Hay que reemplazar la planilla entera, no alcanza con retocar celdas.
A38: COMO SE COMPLETA
A39: Descripcion, altura y ancho del vano: de la planilla de carpinterias.
A40: Area del vano, area total por plano y porcentaje: se calculan solos.
A41: Tipo de vidrio y tipo de proteccion: desplegables; sus valores estan en la hoja Datos_higro.
A42: Transmitancia del cerramiento: cargarla segun el vidrio y el marco adoptados.
A43: PROTECCION: la obra tiene cortinas blackout INTERIORES, y los panos fijos PF no tienen nada.
A44: Una cortina interior NO computa como proteccion solar: la radiacion ya atraveso el vidrio
A45: cuando llega a la cortina. La ordenanza acredita protecciones exteriores (aleros, parasoles,
A46: cortinas de enrollar exteriores, toldos). Por eso las veinte aberturas van Sin Proteccion.
A48: CONSECUENCIA: el factor de exposicion solar da 0,88 esta muy por encima del maximo de 0,30 que la ordenanza admite para
A49: el cuadrante Este/Oeste, donde caen las cuatro fachadas de esta casa por estar girada 45
... A91: dar el total de vanos de los cuatro planos. Sirve para controlar que no falte ninguno.

Sheet Planilla vigas
A1: VIGAS H°A° H-21 ACERO 42/50
A2: NIVEL | B2: POSICION | C2: LUZ (m) | D2: CARGAS (kg/m) | F2: REACCIONES | H2: MOMENTO TRAMO (kgm) | I2: MOMENTO APOYO (kgm) | J2: DIMENSIONES | M2: ARMADURA TRAMO | P2: ARMADURA APOYO | S2: T (kg/cm2) | V2: ESTRIBOS | W2: VERIFICACION | X2: OBSERVACIONES | Y2: DATOS AUXILIARES
D3: p | E3: diagrama | F3: RA | G3: RB | J3: b | K3: h | L3: d | M3: cm2 | N3: n | O3: o | P3: cm2 | Q3: n | R3: o | S3: A | T3: B | U3: o | V3: SEPAR | Y3: esquema | Z3: tipo | AA3: hf losa | AB3: b ef tramo | AC3: b ef apoyo | AD3: P punt. (kg) | AE3: a (m) | AF3: B trib. | AG3: h muro | AH3: rec.
A4: PA | B4: VI 01a | C4: 9.9 | D4: =(Datos_vigas!$B$10*(VLOOKUP($A$4,Datos_vigas!$A$14:$E$15,2,0)*AF4+Datos_vigas!$B$7*J4*L4/10000+Datos_vigas!$B$16*AG4)+Datos_vigas!$B$11*VLOOKUP($A$4,Datos_vigas!$A$14:$E$15,3,0)*AF4) -> 1082.4 | F4: =VLOOKUP(Y4,Datos_vigas!$A$19:$E$23,4,0)*D4*C4+IF(OR(AD4="",AE4=""),0,AD4*MAX(AE4,C4-AE4)/C4) -> 6161.562 | G4: =F4 -> 6161.562 | H4: =VLOOKUP(Y4,Datos_vigas!$A$19:$E$23,2,0)*D4*C4^2+0.75*1000*IF(OR(AD4="",AE4=""),0,AD4*AE4*(C4-AE4)/C4/1000) -> 7577.7247 | I4: =IF(VLOOKUP(Y4,Datos_vigas!$A$19:$E$23,3,0)=0,"---",VLOOKUP(Y4,Datos_vigas!$A$19:$E$23,3,0)*D4*C4^2+0.5*1000*IF(OR(AD4="",AE4=""),0,AD4*AE4*(C4-AE4)/C4/1000)) -> 10608.602 | J4: 15 | K4: =L4-AH4 -> 67 | L4: 70 | M4: =IF(NOT(ISNUMBER(H4)),"---",IF(H4<=0,"---",IF(H4*100/(Datos_vigas!$B$8*AB4*K4^2*Datos_vigas!$B$5)>=0.5,"REVISAR",MAX((1-SQRT(1-2*H4*100/(Datos_vigas!$B$8*AB4*K4^2*Datos_vigas!$B$5)))*AB4*K4*Datos_vigas!$B$5/Datos_vigas!$B$6,0.0033*J4*K4)))) -> 3.3165 | N4: 3 | O4: 12 | P4: =IF(NOT(ISNUMBER(I4)),"---",IF(I4<=0,"---",IF(I4*100/(Datos_vigas!$B$8*AC4*K4^2*Datos_vigas!$B$5)>=0.5,"REVISAR",MAX((1-SQRT(1-2*I4*100/(Datos_vigas!$B$8*AC4*K4^2*Datos_vigas!$B$5)))*AC4*K4*Datos_vigas!$B$5/Datos_vigas!$B$6,0.0033*J4*K4)))) -> 4.2015471 | Q4: 2 | R4: 20 | S4: =F4/(J4*0.85*K4) -> 7.2128323 | T4: =G4/(J4*0.85*K4) -> 7.2128323 | U4: 6 | V4: 30 | W4: =IF(OR(M4="REVISAR",P4="REVISAR"),"SECCION INSUF.",IF(NOT(AND(M4<>"REVISAR",P4<>"REVISAR",IF(ISNUMBER(M4),N4*PI()*(O4/10)^2/4>=M4,TRUE()),IF(ISNUMBER(P4),Q4*PI()*(R4/10)^2/4>=P4,TRUE()),IF(ISNUMBER(M4),M4<=0.0163*AB4*K4,TRUE()),IF(ISNUMBER(P4),P4<=0.0163*AC4*K4,TRUE()))),"NO VERIFICA FLEX.",IF(NOT(F4<=Datos_vigas!$B$9*(0.53*SQRT(Datos_vigas!$B$5)*J4*K4+2*PI()*(U4/10)^2/4*Datos_vigas!$B$6*K4/V4)),"NO VERIF. CORTE",IF(NOT(L4>=C4*100/VLOOKUP(Y4,Datos_vigas!$A$19:$E$23,5,0)),"VERIFICAR FLECHA","VERIFICA")))) -> VERIFICA | X4: Viga de borde sobre la medianera: NO recibe losa. Solo peso propio y mamposteria. Apoya en el tabique T01a y en la columna COL 01 de 10x10. Viga de borde: recibe la reaccion de la losa excentrica y queda sometida a TORSION, no verificada en esta planilla. | Y4: Continua | Z4: Invertida | AA4: 12 | AB4: =IF(Z4="Colgante",MIN(C4*100/4,J4+16*AA4),J4) -> 15 | AC4: =IF(Z4="Invertida",MIN(C4*100/4,J4+16*AA4),J4) -> 207 | AF4: 0 | AG4: 2.6 | AH4: 3
B5: VI 01b | C5: 3.95 | D5: =(Datos_vigas!$B$10*(VLOOKUP($A$4,Datos_vigas!$A$14:$E$15,2,0)*AF5+Datos_vigas!$B$7*J5*L5/10000+Datos_vigas!$B$16*AG5)+Datos_vigas!$B$11*VLOOKUP($A$4,Datos_vigas!$A$14:$E$15,3,0)*AF5) -> 1082.4 | F5: =VLOOKUP(Y5,Datos_vigas!$A$19:$E$23,4,0)*D5*C5+IF(OR(AD5="",AE5=""),0,AD5*MAX(AE5,C5-AE5)/C5) -> 2458.401 | G5: =F5 -> 2458.401 | H5: =VLOOKUP(Y5,Datos_vigas!$A$19:$E$23,2,0)*D5*C5^2+0.75*1000*IF(OR(AD5="",AE5=""),0,AD5*AE5*(C5-AE5)/C5/1000) -> 1206.3203 | I5: =IF(VLOOKUP(Y5,Datos_vigas!$A$19:$E$23,3,0)=0,"---",VLOOKUP(Y5,Datos_vigas!$A$19:$E$23,3,0)*D5*C5^2+0.5*1000*IF(OR(AD5="",AE5=""),0,AD5*AE5*(C5-AE5)/C5/1000)) -> 1688.8146 | J5: 15 | K5: =L5-AH5 -> 67 | L5: 70 | M5: =IF(NOT(ISNUMBER(H5)),"---",IF(H5<=0,"---",IF(H5*100/(Datos_vigas!$B$8*AB5*K5^2*Datos_vigas!$B$5)>=0.5,"REVISAR",MAX((1-SQRT(1-2*H5*100/(Datos_vigas!$B$8*AB5*K5^2*Datos_vigas!$B$5)))*AB5*K5*Datos_vigas!$B$5/Datos_vigas!$B$6,0.0033*J5*K5)))) -> 3.3165 | N5: 3 | O5: 12 | P5: =IF(NOT(ISNUMBER(I5)),"---",IF(I5<=0,"---",IF(I5*100/(Datos_vigas!$B$8*AC5*K5^2*Datos_vigas!$B$5)>=0.5,"REVISAR",MAX((1-SQRT(1-2*I5*100/(Datos_vigas!$B$8*AC5*K5^2*Datos_vigas!$B$5)))*AC5*K5*Datos_vigas!$B$5/Datos_vigas!$B$6,0.0033*J5*K5)))) -> 3.3165 | Q5: 3 | R5: 12 | S5: =F5/(J5*0.85*K5) -> 2.8778472 | T5: =G5/(J5*0.85*K5) -> 2.8778472 | U5: 6 | V5: 30 | W5: =IF(OR(M5="REVISAR",P5="REVISAR"),"SECCION INSUF.",IF(NOT(AND(M5<>"REVISAR",P5<>"REVISAR",IF(ISNUMBER(M5),N5*PI()*(O5/10)^2/4>=M5,TRUE()),IF(ISNUMBER(P5),Q5*PI()*(R5/10)^2/4>=P5,TRUE()),IF(ISNUMBER(M5),M5<=0.0163*AB5*K5,TRUE()),IF(ISNUMBER(P5),P5<=0.0163*AC5*K5,TRUE()))),"NO VERIFICA FLEX.",IF(NOT(F5<=Datos_vigas!$B$9*(0.53*SQRT(Datos_vigas!$B$5)*J5*K5+2*PI()*(U5/10)^2/4*Datos_vigas!$B$6*K5/V5)),"NO VERIF. CORTE",IF(NOT(L5>=C5*100/VLOOKUP(Y5,Datos_vigas!$A$19:$E$23,5,0)),"VERIFICAR FLECHA","VERIFICA")))) -> VERIFICA | X5: Viga de borde: recibe la reaccion de la losa excentrica y queda sometida a TORSION, no verificada en esta planilla. | Y5: Continua | Z5: Invertida | AA5: 12 | AB5: =IF(Z5="Colgante",MIN(C5*100/4,J5+16*AA5),J5) -> 15 | AC5: =IF(Z5="Invertida",MIN(C5*100/4,J5+16*AA5),J5) -> 98.75 | AF5: 0 | AG5: 2.6 | AH5: 3
B6: VI 02 | C6: 9.88 | D6: =(Datos_vigas!$B$10*(VLOOKUP($A$4,Datos_vigas!$A$14:$E$15,2,0)*AF6+Datos_vigas!$B$7*J6*L6/10000+Datos_vigas!$B$16*AG6)+Datos_vigas!$B$11*VLOOKUP($A$4,Datos_vigas!$A$14:$E$15,3,0)*AF6) -> 3717.62 | F6: =VLOOKUP(Y6,Datos_vigas!$A$19:$E$23,4,0)*D6*C6+IF(OR(AD6="",AE6=""),0,AD6*MAX(AE6,C6-AE6)/C6) -> 21119.799 | G6: =F6 -> 21119.799 | H6: =VLOOKUP(Y6,Datos_vigas!$A$19:$E$23,2,0)*D6*C6^2+0.75*1000*IF(OR(AD6="",AE6=""),0,AD6*AE6*(C6-AE6)/C6/1000) -> 25921.465 | I6: =IF(VLOOKUP(Y6,Datos_vigas!$A$19:$E$23,3,0)=0,"---",VLOOKUP(Y6,Datos_vigas!$A$19:$E$23,3,0)*D6*C6^2+0.5*1000*IF(OR(AD6="",AE6=""),0,AD6*AE6*(C6-AE6)/C6/1000)) -> 36289.325 | J6: 15 | K6: =L6-AH6 -> 64 | L6: 70 | M6: =IF(NOT(ISNUMBER(H6)),"---",IF(H6<=0,"---",IF(H6*100/(Datos_vigas!$B$8*AB6*K6^2*Datos_vigas!$B$5)>=0.5,"REVISAR",MAX((1-SQRT(1-2*H6*100/(Datos_vigas!$B$8*AB6*K6^2*Datos_vigas!$B$5)))*AB6*K6*Datos_vigas!$B$5/Datos_vigas!$B$6,0.0033*J6*K6)))) -> 12.287671 | N6: 4 | O6: 20 | P6: =IF(NOT(ISNUMBER(I6)),"---",IF(I6<=0,"---",IF(I6*100/(Datos_vigas!$B$8*AC6*K6^2*Datos_vigas!$B$5)>=0.5,"REVISAR",MAX((1-SQRT(1-2*I6*100/(Datos_vigas!$B$8*AC6*K6^2*Datos_vigas!$B$5)))*AC6*K6*Datos_vigas!$B$5/Datos_vigas!$B$6,0.0033*J6*K6)))) -> 15.174356 | Q6: 4 | R6: 25 | S6: =F6/(J6*0.85*K6) -> 25.882107 | T6: =G6/(J6*0.85*K6) -> 25.882107 | U6: 8 | V6: 10 | W6: =IF(OR(M6="REVISAR",P6="REVISAR"),"SECCION INSUF.",IF(NOT(AND(M6<>"REVISAR",P6<>"REVISAR",IF(ISNUMBER(M6),N6*PI()*(O6/10)^2/4>=M6,TRUE()),IF(ISNUMBER(P6),Q6*PI()*(R6/10)^2/4>=P6,TRUE()),IF(ISNUMBER(M6),M6<=0.0163*AB6*K6,TRUE()),IF(ISNUMBER(P6),P6<=0.0163*AC6*K6,TRUE()))),"NO VERIFICA FLEX.",IF(NOT(F6<=Datos_vigas!$B$9*(0.53*SQRT(Datos_vigas!$B$5)*J6*K6+2*PI()*(U6/10)^2/4*Datos_vigas!$B$6*K6/V6)),"NO VERIF. CORTE",IF(NOT(L6>=C6*100/VLOOKUP(Y6,Datos_vigas!$A$19:$E$23,5,0)),"VERIFICAR FLECHA","VERIFICA")))) -> VERIFICA | X6: Armadura en 2 capas (rec. 6 cm). NO USAR TEXTO VIEJO. Recibe L03 (2,08 m) y el alero L02, computado como 0,59 m equivalentes por tener menor carga que un entrepiso. Con 9,88 m de luz y 15x60 la armadura de apoyo necesaria (25,5 cm2) supera la cuantia maxima (13,2). Apoyos confirmados en obra: tabique T07 perpendicular en el extremo superior y COL 02 en el inferior, sin apoyo intermedio. Para esta carga harian falta 15x75 (As 16,2 cm2). Verificar la seccion real construida. | Y6: Continua | Z6: Invertida | AA6: 12 | AB6: =IF(Z6="Colgante",MIN(C6*100/4,J6+16*AA6),J6) -> 15 | AC6: =IF(Z6="Invertida",MIN(C6*100/4,J6+16*AA6),J6) -> 207 | AF6: 2.689 | AG6: 2.6 | AH6: 6
B7: VI 03c | C7: 3.75 | D7: =(Datos_vigas!$B$10*(VLOOKUP($A$4,Datos_vigas!$A$14:$E$15,2,0)*AF7+Datos_vigas!$B$7*J7*L7/10000+Datos_vigas!$B$16*AG7)+Datos_vigas!$B$11*VLOOKUP($A$4,Datos_vigas!$A$14:$E$15,3,0)*AF7) -> 3140.4 | F7: =VLOOKUP(Y7,Datos_vigas!$A$19:$E$23,4,0)*D7*C7+IF(OR(AD7="",AE7=""),0,AD7*MAX(AE7,C7-AE7)/C7) -> 6771.4875 | G7: =F7 -> 6771.4875 | H7: =VLOOKUP(Y7,Datos_vigas!$A$19:$E$23,2,0)*D7*C7^2+0.75*1000*IF(OR(AD7="",AE7=""),0,AD7*AE7*(C7-AE7)/C7/1000) -> 3154.4827 | I7: =IF(VLOOKUP(Y7,Datos_vigas!$A$19:$E$23,3,0)=0,"---",VLOOKUP(Y7,Datos_vigas!$A$19:$E$23,3,0)*D7*C7^2+0.5*1000*IF(OR(AD7="",AE7=""),0,AD7*AE7*(C7-AE7)/C7/1000)) -> 4416.1875 | J7: 15 | K7: =L7-AH7 -> 67 | L7: 70 | M7: =IF(NOT(ISNUMBER(H7)),"---",IF(H7<=0,"---",IF(H7*100/(Datos_vigas!$B$8*AB7*K7^2*Datos_vigas!$B$5)>=0.5,"REVISAR",MAX((1-SQRT(1-2*H7*100/(Datos_vigas!$B$8*AB7*K7^2*Datos_vigas!$B$5)))*AB7*K7*Datos_vigas!$B$5/Datos_vigas!$B$6,0.0033*J7*K7)))) -> 3.3165 | N7: 3 | O7: 12 | P7: =IF(NOT(ISNUMBER(I7)),"---",IF(I7<=0,"---",IF(I7*100/(Datos_vigas!$B$8*AC7*K7^2*Datos_vigas!$B$5)>=0.5,"REVISAR",MAX((1-SQRT(1-2*I7*100/(Datos_vigas!$B$8*AC7*K7^2*Datos_vigas!$B$5)))*AC7*K7*Datos_vigas!$B$5/Datos_vigas!$B$6,0.0033*J7*K7)))) -> 3.3165 | Q7: 3 | R7: 12 | S7: =F7/(J7*0.85*K7) -> 7.9268218 | T7: =G7/(J7*0.85*K7) -> 7.9268218 | U7: 6 | V7: 30 | W7: =IF(OR(M7="REVISAR",P7="REVISAR"),"SECCION INSUF.",IF(NOT(AND(M7<>"REVISAR",P7<>"REVISAR",IF(ISNUMBER(M7),N7*PI()*(O7/10)^2/4>=M7,TRUE()),IF(ISNUMBER(P7),Q7*PI()*(R7/10)^2/4>=P7,TRUE()),IF(ISNUMBER(M7),M7<=0.0163*AB7*K7,TRUE()),IF(ISNUMBER(P7),P7<=0.0163*AC7*K7,TRUE()))),"NO VERIFICA FLEX.",IF(NOT(F7<=Datos_vigas!$B$9*(0.53*SQRT(Datos_vigas!$B$5)*J7*K7+2*PI()*(U7/10)^2/4*Datos_vigas!$B$6*K7/V7)),"NO VERIF. CORTE",IF(NOT(L7>=C7*100/VLOOKUP(Y7,Datos_vigas!$A$19:$E$23,5,0)),"VERIFICAR FLECHA","VERIFICA")))) -> VERIFICA | Y7: Continua | Z7: Invertida | AA7: 12 | AB7: =IF(Z7="Colgante",MIN(C7*100/4,J7+16*AA7),J7) -> 15 | AC7: =IF(Z7="Invertida",MIN(C7*100/4,J7+16*AA7),J7) -> 93.75 | AF7: 2.1 | AG7: 2.6 | AH7: 3
B8: VI 04a | C8: 3.75 | D8: =(Datos_vigas!$B$10*(VLOOKUP($A$4,Datos_vigas!$A$14:$E$15,2,0)*AF8+Datos_vigas!$B$7*J8*L8/10000+Datos_vigas!$B$16*AG8)+Datos_vigas!$B$11*VLOOKUP($A$4,Datos_vigas!$A$14:$E$15,3,0)*AF8) -> 1082.4 | F8: =VLOOKUP(Y8,Datos_vigas!$A$19:$E$23,4,0)*D8*C8+IF(OR(AD8="",AE8=""),0,AD8*MAX(AE8,C8-AE8)/C8) -> 5626.565 | G8: =F8 -> 5626.565 | H8: =VLOOKUP(Y8,Datos_vigas!$A$19:$E$23,2,0)*D8*C8^2+0.75*1000*IF(OR(AD8="",AE8=""),0,AD8*AE8*(C8-AE8)/C8/1000) -> 5532.3179 | I8: =IF(VLOOKUP(Y8,Datos_vigas!$A$19:$E$23,3,0)=0,"---",VLOOKUP(Y8,Datos_vigas!$A$19:$E$23,3,0)*D8*C8^2+0.5*1000*IF(OR(AD8="",AE8=""),0,AD8*AE8*(C8-AE8)/C8/1000)) -> 4485.501 | J8: 15 | K8: =L8-AH8 -> 67 | L8: 70 | M8: =IF(NOT(ISNUMBER(H8)),"---",IF(H8<=0,"---",IF(H8*100/(Datos_vigas!$B$8*AB8*K8^2*Datos_vigas!$B$5)>=0.5,"REVISAR",MAX((1-SQRT(1-2*H8*100/(Datos_vigas!$B$8*AB8*K8^2*Datos_vigas!$B$5)))*AB8*K8*Datos_vigas!$B$5/Datos_vigas!$B$6,0.0033*J8*K8)))) -> 3.3165 | N8: 3 | O8: 12 | P8: =IF(NOT(ISNUMBER(I8)),"---",IF(I8<=0,"---",IF(I8*100/(Datos_vigas!$B$8*AC8*K8^2*Datos_vigas!$B$5)>=0.5,"REVISAR",MAX((1-SQRT(1-2*I8*100/(Datos_vigas!$B$8*AC8*K8^2*Datos_vigas!$B$5)))*AC8*K8*Datos_vigas!$B$5/Datos_vigas!$B$6,0.0033*J8*K8)))) -> 3.3165 | Q8: 3 | R8: 12 | S8: =F8/(J8*0.85*K8) -> 6.5865555 | T8: =G8/(J8*0.85*K8) -> 6.5865555 | U8: 6 | V8: 30 | W8: =IF(OR(M8="REVISAR",P8="REVISAR"),"SECCION INSUF.",IF(NOT(AND(M8<>"REVISAR",P8<>"REVISAR",IF(ISNUMBER(M8),N8*PI()*(O8/10)^2/4>=M8,TRUE()),IF(ISNUMBER(P8),Q8*PI()*(R8/10)^2/4>=P8,TRUE()),IF(ISNUMBER(M8),M8<=0.0163*AB8*K8,TRUE()),IF(ISNUMBER(P8),P8<=0.0163*AC8*K8,TRUE()))),"NO VERIFICA FLEX.",IF(NOT(F8<=Datos_vigas!$B$9*(0.53*SQRT(Datos_vigas!$B$5)*J8*K8+2*PI()*(U8/10)^2/4*Datos_vigas!$B$6*K8/V8)),"NO VERIF. CORTE",IF(NOT(L8>=C8*100/VLOOKUP(Y8,Datos_vigas!$A$19:$E$23,5,0)),"VERIFICAR FLECHA","VERIFICA")))) -> VERIFICA | X8: VI 09 le descarga 6.332 kg a 1,80 m del apoyo, practicamente al medio de sus 3,75 m. Esta viga no recibe losa, de modo que la puntual es casi toda su carga. Se superpone el momento isostatico P a b / L repartido 0,75 al tramo y 0,50 al apoyo, y la reaccion isostatica al corte. | Y8: Continua | Z8: Invertida | AA8: 12 | AB8: =IF(Z8="Colgante",MIN(C8*100/4,J8+16*AA8),J8) -> 15 | AC8: =IF(Z8="Invertida",MIN(C8*100/4,J8+16*AA8),J8) -> 93.75 | AD8: 6332 | AE8: 1.8 | AF8: 0 | AG8: 2.6 | AH8: 3
B9: VI 04b | C9: 3.8 | D9: =(Datos_vigas!$B$10*(VLOOKUP($A$4,Datos_vigas!$A$14:$E$15,2,0)*AF9+Datos_vigas!$B$7*J9*L9/10000+Datos_vigas!$B$16*AG9)+Datos_vigas!$B$11*VLOOKUP($A$4,Datos_vigas!$A$14:$E$15,3,0)*AF9) -> 2600.42 | F9: =VLOOKUP(Y9,Datos_vigas!$A$19:$E$23,4,0)*D9*C9+IF(OR(AD9="",AE9=""),0,AD9*MAX(AE9,C9-AE9)/C9) -> 5681.9177 | G9: =F9 -> 5681.9177 | H9: =VLOOKUP(Y9,Datos_vigas!$A$19:$E$23,2,0)*D9*C9^2+0.75*1000*IF(OR(AD9="",AE9=""),0,AD9*AE9*(C9-AE9)/C9/1000) -> 2682.2011 | I9: =IF(VLOOKUP(Y9,Datos_vigas!$A$19:$E$23,3,0)=0,"---",VLOOKUP(Y9,Datos_vigas!$A$19:$E$23,3,0)*D9*C9^2+0.5*1000*IF(OR(AD9="",AE9=""),0,AD9*AE9*(C9-AE9)/C9/1000)) -> 3755.0065 | J9: 15 | K9: =L9-AH9 -> 67 | L9: 70 | M9: =IF(NOT(ISNUMBER(H9)),"---",IF(H9<=0,"---",IF(H9*100/(Datos_vigas!$B$8*AB9*K9^2*Datos_vigas!$B$5)>=0.5,"REVISAR",MAX((1-SQRT(1-2*H9*100/(Datos_vigas!$B$8*AB9*K9^2*Datos_vigas!$B$5)))*AB9*K9*Datos_vigas!$B$5/Datos_vigas!$B$6,0.0033*J9*K9)))) -> 3.3165 | N9: 3 | O9: 12 | P9: =IF(NOT(ISNUMBER(I9)),"---",IF(I9<=0,"---",IF(I9*100/(Datos_vigas!$B$8*AC9*K9^2*Datos_vigas!$B$5)>=0.5,"REVISAR",MAX((1-SQRT(1-2*I9*100/(Datos_vigas!$B$8*AC9*K9^2*Datos_vigas!$B$5)))*AC9*K9*Datos_vigas!$B$5/Datos_vigas!$B$6,0.0033*J9*K9)))) -> 3.3165 | Q9: 3 | R9: 12 | S9: =F9/(J9*0.85*K9) -> 6.6513523 | T9: =G9/(J9*0.85*K9) -> 6.6513523 | U9: 6 | V9: 30 | W9: =IF(OR(M9="REVISAR",P9="REVISAR"),"SECCION INSUF.",IF(NOT(AND(M9<>"REVISAR",P9<>"REVISAR",IF(ISNUMBER(M9),N9*PI()*(O9/10)^2/4>=M9,TRUE()),IF(ISNUMBER(P9),Q9*PI()*(R9/10)^2/4>=P9,TRUE()),IF(ISNUMBER(M9),M9<=0.0163*AB9*K9,TRUE()),IF(ISNUMBER(P9),P9<=0.0163*AC9*K9,TRUE()))),"NO VERIFICA FLEX.",IF(NOT(F9<=Datos_vigas!$B$9*(0.53*SQRT(Datos_vigas!$B$5)*J9*K9+2*PI()*(U9/10)^2/4*Datos_vigas!$B$6*K9/V9)),"NO VERIF. CORTE",IF(NOT(L9>=C9*100/VLOOKUP(Y9,Datos_vigas!$A$19:$E$23,5,0)),"VERIFICAR FLECHA","VERIFICA")))) -> VERIFICA | Y9: Continua | Z9: Invertida | AA9: 12 | AB9: =IF(Z9="Colgante",MIN(C9*100/4,J9+16*AA9),J9) -> 15 | AC9: =IF(Z9="Invertida",MIN(C9*100/4,J9+16*AA9),J9) -> 95 | AF9: 1.549 | AG9: 2.6 | AH9: 3
B10: VI 06 | C10: 6.53 | D10: =(Datos_vigas!$B$10*(VLOOKUP($A$4,Datos_vigas!$A$14:$E$15,2,0)*AF10+Datos_vigas!$B$7*J10*L10/10000+Datos_vigas!$B$16*AG10)+Datos_vigas!$B$11*VLOOKUP($A$4,Datos_vigas!$A$14:$E$15,3,0)*AF10) -> 2600.42 | F10: =VLOOKUP(Y10,Datos_vigas!$A$19:$E$23,4,0)*D10*C10+IF(OR(AD10="",AE10=""),0,AD10*MAX(AE10,C10-AE10)/C10) -> 15234.677 | G10: =F10 -> 15234.677 | H10: =VLOOKUP(Y10,Datos_vigas!$A$19:$E$23,2,0)*D10*C10^2+0.75*1000*IF(OR(AD10="",AE10=""),0,AD10*AE10*(C10-AE10)/C10/1000) -> 10095.085 | I10: =IF(VLOOKUP(Y10,Datos_vigas!$A$19:$E$23,3,0)=0,"---",VLOOKUP(Y10,Datos_vigas!$A$19:$E$23,3,0)*D10*C10^2+0.5*1000*IF(OR(AD10="",AE10=""),0,AD10*AE10*(C10-AE10)/C10/1000)) -> 12538.174 | J10: 15 | K10: =L10-AH10 -> 67 | L10: 70 | M10: =IF(NOT(ISNUMBER(H10)),"---",IF(H10<=0,"---",IF(H10*100/(Datos_vigas!$B$8*AB10*K10^2*Datos_vigas!$B$5)>=0.5,"REVISAR",MAX((1-SQRT(1-2*H10*100/(Datos_vigas!$B$8*AB10*K10^2*Datos_vigas!$B$5)))*AB10*K10*Datos_vigas!$B$5/Datos_vigas!$B$6,0.0033*J10*K10)))) -> 4.1580931 | N10: 2 | O10: 20 | P10: =IF(NOT(ISNUMBER(I10)),"---",IF(I10<=0,"---",IF(I10*100/(Datos_vigas!$B$8*AC10*K10^2*Datos_vigas!$B$5)>=0.5,"REVISAR",MAX((1-SQRT(1-2*I10*100/(Datos_vigas!$B$8*AC10*K10^2*Datos_vigas!$B$5)))*AC10*K10*Datos_vigas!$B$5/Datos_vigas!$B$6,0.0033*J10*K10)))) -> 4.9733256 | Q10: 2 | R10: 20 | S10: =F10/(J10*0.85*K10) -> 17.83398 | T10: =G10/(J10*0.85*K10) -> 17.83398 | U10: 6 | V10: 10 | W10: =IF(OR(M10="REVISAR",P10="REVISAR"),"SECCION INSUF.",IF(NOT(AND(M10<>"REVISAR",P10<>"REVISAR",IF(ISNUMBER(M10),N10*PI()*(O10/10)^2/4>=M10,TRUE()),IF(ISNUMBER(P10),Q10*PI()*(R10/10)^2/4>=P10,TRUE()),IF(ISNUMBER(M10),M10<=0.0163*AB10*K10,TRUE()),IF(ISNUMBER(P10),P10<=0.0163*AC10*K10,TRUE()))),"NO VERIFICA FLEX.",IF(NOT(F10<=Datos_vigas!$B$9*(0.53*SQRT(Datos_vigas!$B$5)*J10*K10+2*PI()*(U10/10)^2/4*Datos_vigas!$B$6*K10/V10)),"NO VERIF. CORTE",IF(NOT(L10>=C10*100/VLOOKUP(Y10,Datos_vigas!$A$19:$E$23,5,0)),"VERIFICAR FLECHA","VERIFICA")))) -> VERIFICA | X10: Longitud total 14,00 m. Sobre su eje hay cuatro columnas: trabaja como viga continua de tres tramos de 4,10, 4,32 y 6,53 m. Se calcula con el mayor. Es el cuarto borde de la losa cruzada L07. Longitud total 14,00 m. Sobre su eje hay cuatro columnas: trabaja como viga continua de tres tramos de 4,10, 4,32 y 6,53 m. Se calcula con el mayor. Es el cuarto borde de la losa cruzada L07. VI 08b le descarga 5.954 kg a 6,00 m del extremo inferior, dentro del tramo de 6,53 m y a solo 53 cm del apoyo siguiente: aporta poco momento y mucho corte, por eso la reaccion sube de 9.764 a 15.235 kg. Se superpone el momento isostatico P a b / L repartido 0,75 al tramo y 0,50 al apoyo, y la reaccion isostatica al corte. Viga principal: recibe a VI 08b y a VI 09. VI 09 apoya a 7,95 m del extremo inferior, o sea en el tramo del medio de 4,32 m, que con esa puntual llega a 7.993 kgm y no gobierna. El tramo que gobierna es el de 6,53 m con la puntual de VI 08b. | Y10: Continua | Z10: Invertida | AA10: 12 | AB10: =IF(Z10="Colgante",MIN(C10*100/4,J10+16*AA10),J10) -> 15 | AC10: =IF(Z10="Invertida",MIN(C10*100/4,J10+16*AA10),J10) -> 163.25 | AD10: 5954 | AE10: 6 | AF10: 1.549 | AG10: 2.6 | AH10: 3
B11: VI 07a | C11: 3.37 | D11: =(Datos_vigas!$B$10*(VLOOKUP($A$4,Datos_vigas!$A$14:$E$15,2,0)*AF11+Datos_vigas!$B$7*J11*L11/10000+Datos_vigas!$B$16*AG11)+Datos_vigas!$B$11*VLOOKUP($A$4,Datos_vigas!$A$14:$E$15,3,0)*AF11) -> 1846.8 | F11: =VLOOKUP(Y11,Datos_vigas!$A$19:$E$23,4,0)*D11*C11+IF(OR(AD11="",AE11=""),0,AD11*MAX(AE11,C11-AE11)/C11) -> 3578.6367 | G11: =F11 -> 3578.6367 | H11: =VLOOKUP(Y11,Datos_vigas!$A$19:$E$23,2,0)*D11*C11^2+0.75*1000*IF(OR(AD11="",AE11=""),0,AD11*AE11*(C11-AE11)/C11/1000) -> 1498.1673 | I11: =IF(VLOOKUP(Y11,Datos_vigas!$A$19:$E$23,3,0)=0,"---",VLOOKUP(Y11,Datos_vigas!$A$19:$E$23,3,0)*D11*C11^2+0.5*1000*IF(OR(AD11="",AE11=""),0,AD11*AE11*(C11-AE11)/C11/1000)) -> 2097.3923 | J11: 15 | K11: =L11-AH11 -> 67 | L11: 70 | M11: =IF(NOT(ISNUMBER(H11)),"---",IF(H11<=0,"---",IF(H11*100/(Datos_vigas!$B$8*AB11*K11^2*Datos_vigas!$B$5)>=0.5,"REVISAR",MAX((1-SQRT(1-2*H11*100/(Datos_vigas!$B$8*AB11*K11^2*Datos_vigas!$B$5)))*AB11*K11*Datos_vigas!$B$5/Datos_vigas!$B$6,0.0033*J11*K11)))) -> 3.3165 | N11: 3 | O11: 12 | P11: =IF(NOT(ISNUMBER(I11)),"---",IF(I11<=0,"---",IF(I11*100/(Datos_vigas!$B$8*AC11*K11^2*Datos_vigas!$B$5)>=0.5,"REVISAR",MAX((1-SQRT(1-2*I11*100/(Datos_vigas!$B$8*AC11*K11^2*Datos_vigas!$B$5)))*AC11*K11*Datos_vigas!$B$5/Datos_vigas!$B$6,0.0033*J11*K11)))) -> 3.3165 | Q11: 3 | R11: 12 | S11: =F11/(J11*0.85*K11) -> 4.1892147 | T11: =G11/(J11*0.85*K11) -> 4.1892147 | U11: 6 | V11: 30 | W11: =IF(OR(M11="REVISAR",P11="REVISAR"),"SECCION INSUF.",IF(NOT(AND(M11<>"REVISAR",P11<>"REVISAR",IF(ISNUMBER(M11),N11*PI()*(O11/10)^2/4>=M11,TRUE()),IF(ISNUMBER(P11),Q11*PI()*(R11/10)^2/4>=P11,TRUE()),IF(ISNUMBER(M11),M11<=0.0163*AB11*K11,TRUE()),IF(ISNUMBER(P11),P11<=0.0163*AC11*K11,TRUE()))),"NO VERIFICA FLEX.",IF(NOT(F11<=Datos_vigas!$B$9*(0.53*SQRT(Datos_vigas!$B$5)*J11*K11+2*PI()*(U11/10)^2/4*Datos_vigas!$B$6*K11/V11)),"NO VERIF. CORTE",IF(NOT(L11>=C11*100/VLOOKUP(Y11,Datos_vigas!$A$19:$E$23,5,0)),"VERIFICAR FLECHA","VERIFICA")))) -> VERIFICA | X11: Viga de borde: recibe la reaccion de la losa excentrica y queda sometida a TORSION, no verificada en esta planilla. | Y11: Continua | Z11: Invertida | AA11: 12 | AB11: =IF(Z11="Colgante",MIN(C11*100/4,J11+16*AA11),J11) -> 15 | AC11: =IF(Z11="Invertida",MIN(C11*100/4,J11+16*AA11),J11) -> 84.25 | AF11: 0.78 | AG11: 2.6 | AH11: 3
B12: VI 07b | C12: 4.03 | D12: =(Datos_vigas!$B$10*(VLOOKUP($A$4,Datos_vigas!$A$14:$E$15,2,0)*AF12+Datos_vigas!$B$7*J12*L12/10000+Datos_vigas!$B$16*AG12)+Datos_vigas!$B$11*VLOOKUP($A$4,Datos_vigas!$A$14:$E$15,3,0)*AF12) -> 1082.4 | F12: =VLOOKUP(Y12,Datos_vigas!$A$19:$E$23,4,0)*D12*C12+IF(OR(AD12="",AE12=""),0,AD12*MAX(AE12,C12-AE12)/C12) -> 2508.1914 | G12: =F12 -> 2508.1914 | H12: =VLOOKUP(Y12,Datos_vigas!$A$19:$E$23,2,0)*D12*C12^2+0.75*1000*IF(OR(AD12="",AE12=""),0,AD12*AE12*(C12-AE12)/C12/1000) -> 1255.6787 | I12: =IF(VLOOKUP(Y12,Datos_vigas!$A$19:$E$23,3,0)=0,"---",VLOOKUP(Y12,Datos_vigas!$A$19:$E$23,3,0)*D12*C12^2+0.5*1000*IF(OR(AD12="",AE12=""),0,AD12*AE12*(C12-AE12)/C12/1000)) -> 1757.915 | J12: 15 | K12: =L12-AH12 -> 67 | L12: 70 | M12: =IF(NOT(ISNUMBER(H12)),"---",IF(H12<=0,"---",IF(H12*100/(Datos_vigas!$B$8*AB12*K12^2*Datos_vigas!$B$5)>=0.5,"REVISAR",MAX((1-SQRT(1-2*H12*100/(Datos_vigas!$B$8*AB12*K12^2*Datos_vigas!$B$5)))*AB12*K12*Datos_vigas!$B$5/Datos_vigas!$B$6,0.0033*J12*K12)))) -> 3.3165 | N12: 3 | O12: 12 | P12: =IF(NOT(ISNUMBER(I12)),"---",IF(I12<=0,"---",IF(I12*100/(Datos_vigas!$B$8*AC12*K12^2*Datos_vigas!$B$5)>=0.5,"REVISAR",MAX((1-SQRT(1-2*I12*100/(Datos_vigas!$B$8*AC12*K12^2*Datos_vigas!$B$5)))*AC12*K12*Datos_vigas!$B$5/Datos_vigas!$B$6,0.0033*J12*K12)))) -> 3.3165 | Q12: 3 | R12: 12 | S12: =F12/(J12*0.85*K12) -> 2.9361327 | T12: =G12/(J12*0.85*K12) -> 2.9361327 | U12: 6 | V12: 30 | W12: =IF(OR(M12="REVISAR",P12="REVISAR"),"SECCION INSUF.",IF(NOT(AND(M12<>"REVISAR",P12<>"REVISAR",IF(ISNUMBER(M12),N12*PI()*(O12/10)^2/4>=M12,TRUE()),IF(ISNUMBER(P12),Q12*PI()*(R12/10)^2/4>=P12,TRUE()),IF(ISNUMBER(M12),M12<=0.0163*AB12*K12,TRUE()),IF(ISNUMBER(P12),P12<=0.0163*AC12*K12,TRUE()))),"NO VERIFICA FLEX.",IF(NOT(F12<=Datos_vigas!$B$9*(0.53*SQRT(Datos_vigas!$B$5)*J12*K12+2*PI()*(U12/10)^2/4*Datos_vigas!$B$6*K12/V12)),"NO VERIF. CORTE",IF(NOT(L12>=C12*100/VLOOKUP(Y12,Datos_vigas!$A$19:$E$23,5,0)),"VERIFICAR FLECHA","VERIFICA")))) -> VERIFICA | X12: Viga de borde: recibe la reaccion de la losa excentrica y queda sometida a TORSION, no verificada en esta planilla. | Y12: Continua | Z12: Invertida | AA12: 12 | AB12: =IF(Z12="Colgante",MIN(C12*100/4,J12+16*AA12),J12) -> 15 | AC12: =IF(Z12="Invertida",MIN(C12*100/4,J12+16*AA12),J12) -> 100.75 | AF12: 0 | AG12: 2.6 | AH12: 3
B13: VI 07c | C13: 8.6 | D13: =(Datos_vigas!$B$10*(VLOOKUP($A$4,Datos_vigas!$A$14:$E$15,2,0)*AF13+Datos_vigas!$B$7*J13*L13/10000+Datos_vigas!$B$16*AG13)+Datos_vigas!$B$11*VLOOKUP($A$4,Datos_vigas!$A$14:$E$15,3,0)*AF13) -> 4718.2 | F13: =VLOOKUP(Y13,Datos_vigas!$A$19:$E$23,4,0)*D13*C13+IF(OR(AD13="",AE13=""),0,AD13*MAX(AE13,C13-AE13)/C13) -> 26369.046 | G13: =F13 -> 26369.046 | H13: =VLOOKUP(Y13,Datos_vigas!$A$19:$E$23,2,0)*D13*C13^2+0.75*1000*IF(OR(AD13="",AE13=""),0,AD13*AE13*(C13-AE13)/C13/1000) -> 27258.789 | I13: =IF(VLOOKUP(Y13,Datos_vigas!$A$19:$E$23,3,0)=0,"---",VLOOKUP(Y13,Datos_vigas!$A$19:$E$23,3,0)*D13*C13^2+0.5*1000*IF(OR(AD13="",AE13=""),0,AD13*AE13*(C13-AE13)/C13/1000)) -> 45435.457 | J13: 15 | K13: =L13-AH13 -> 64 | L13: 70 | M13: =IF(NOT(ISNUMBER(H13)),"---",IF(H13<=0,"---",IF(H13*100/(Datos_vigas!$B$8*AB13*K13^2*Datos_vigas!$B$5)>=0.5,"REVISAR",MAX((1-SQRT(1-2*H13*100/(Datos_vigas!$B$8*AB13*K13^2*Datos_vigas!$B$5)))*AB13*K13*Datos_vigas!$B$5/Datos_vigas!$B$6,0.0033*J13*K13)))) -> 13.038564 | N13: 3 | O13: 25 | P13: =IF(NOT(ISNUMBER(I13)),"---",IF(I13<=0,"---",IF(I13*100/(Datos_vigas!$B$8*AC13*K13^2*Datos_vigas!$B$5)>=0.5,"REVISAR",MAX((1-SQRT(1-2*I13*100/(Datos_vigas!$B$8*AC13*K13^2*Datos_vigas!$B$5)))*AC13*K13*Datos_vigas!$B$5/Datos_vigas!$B$6,0.0033*J13*K13)))) -> 19.055272 | Q13: 4 | R13: 25 | S13: =F13/(J13*0.85*K13) -> 32.315007 | T13: =G13/(J13*0.85*K13) -> 32.315007 | U13: 10 | V13: 15 | W13: =IF(OR(M13="REVISAR",P13="REVISAR"),"SECCION INSUF.",IF(NOT(AND(M13<>"REVISAR",P13<>"REVISAR",IF(ISNUMBER(M13),N13*PI()*(O13/10)^2/4>=M13,TRUE()),IF(ISNUMBER(P13),Q13*PI()*(R13/10)^2/4>=P13,TRUE()),IF(ISNUMBER(M13),M13<=0.0163*AB13*K13,TRUE()),IF(ISNUMBER(P13),P13<=0.0163*AC13*K13,TRUE()))),"NO VERIFICA FLEX.",IF(NOT(F13<=Datos_vigas!$B$9*(0.53*SQRT(Datos_vigas!$B$5)*J13*K13+2*PI()*(U13/10)^2/4*Datos_vigas!$B$6*K13/V13)),"NO VERIF. CORTE",IF(NOT(L13>=C13*100/VLOOKUP(Y13,Datos_vigas!$A$19:$E$23,5,0)),"VERIFICAR FLECHA","VERIFICA")))) -> VERIFICA | X13: Armadura en 2 capas (rec. 6 cm). Apoya en columna COL 02 de 15x30 y en el tabique T05b. La viga chata VCH 05 le descarga 1.735 kg a 3,60 m del apoyo. Se superpone el momento isostatico P a b / L repartido 0,75 al tramo y 0,50 al apoyo, y la reaccion isostatica al corte. Viga de borde: recibe la reaccion de la losa excentrica y queda sometida a TORSION, no verificada en esta planilla. | Y13: Empotrada-apoyada | Z13: Invertida | AA13: 12 | AB13: =IF(Z13="Colgante",MIN(C13*100/4,J13+16*AA13),J13) -> 15 | AC13: =IF(Z13="Invertida",MIN(C13*100/4,J13+16*AA13),J13) -> 207 | AD13: 1735 | AE13: 3.6 | AF13: 3.71 | AG13: 2.6 | AH13: 6
B14: VI 08a | C14: 3.65 | D14: =(Datos_vigas!$B$10*(VLOOKUP($A$4,Datos_vigas!$A$14:$E$15,2,0)*AF14+Datos_vigas!$B$7*J14*L14/10000+Datos_vigas!$B$16*AG14)+Datos_vigas!$B$11*VLOOKUP($A$4,Datos_vigas!$A$14:$E$15,3,0)*AF14) -> 2126.1 | F14: =VLOOKUP(Y14,Datos_vigas!$A$19:$E$23,4,0)*D14*C14+IF(OR(AD14="",AE14=""),0,AD14*MAX(AE14,C14-AE14)/C14) -> 4462.1524 | G14: =F14 -> 4462.1524 | H14: =VLOOKUP(Y14,Datos_vigas!$A$19:$E$23,2,0)*D14*C14^2+0.75*1000*IF(OR(AD14="",AE14=""),0,AD14*AE14*(C14-AE14)/C14/1000) -> 2023.2524 | I14: =IF(VLOOKUP(Y14,Datos_vigas!$A$19:$E$23,3,0)=0,"---",VLOOKUP(Y14,Datos_vigas!$A$19:$E$23,3,0)*D14*C14^2+0.5*1000*IF(OR(AD14="",AE14=""),0,AD14*AE14*(C14-AE14)/C14/1000)) -> 2832.4967 | J14: 15 | K14: =L14-AH14 -> 67 | L14: 70 | M14: =IF(NOT(ISNUMBER(H14)),"---",IF(H14<=0,"---",IF(H14*100/(Datos_vigas!$B$8*AB14*K14^2*Datos_vigas!$B$5)>=0.5,"REVISAR",MAX((1-SQRT(1-2*H14*100/(Datos_vigas!$B$8*AB14*K14^2*Datos_vigas!$B$5)))*AB14*K14*Datos_vigas!$B$5/Datos_vigas!$B$6,0.0033*J14*K14)))) -> 3.3165 | N14: 3 | O14: 12 | P14: =IF(NOT(ISNUMBER(I14)),"---",IF(I14<=0,"---",IF(I14*100/(Datos_vigas!$B$8*AC14*K14^2*Datos_vigas!$B$5)>=0.5,"REVISAR",MAX((1-SQRT(1-2*I14*100/(Datos_vigas!$B$8*AC14*K14^2*Datos_vigas!$B$5)))*AC14*K14*Datos_vigas!$B$5/Datos_vigas!$B$6,0.0033*J14*K14)))) -> 3.3165 | Q14: 3 | R14: 12 | S14: =F14/(J14*0.85*K14) -> 5.2234737 | T14: =G14/(J14*0.85*K14) -> 5.2234737 | U14: 6 | V14: 30 | W14: =IF(OR(M14="REVISAR",P14="REVISAR"),"SECCION INSUF.",IF(NOT(AND(M14<>"REVISAR",P14<>"REVISAR",IF(ISNUMBER(M14),N14*PI()*(O14/10)^2/4>=M14,TRUE()),IF(ISNUMBER(P14),Q14*PI()*(R14/10)^2/4>=P14,TRUE()),IF(ISNUMBER(M14),M14<=0.0163*AB14*K14,TRUE()),IF(ISNUMBER(P14),P14<=0.0163*AC14*K14,TRUE()))),"NO VERIFICA FLEX.",IF(NOT(F14<=Datos_vigas!$B$9*(0.53*SQRT(Datos_vigas!$B$5)*J14*K14+2*PI()*(U14/10)^2/4*Datos_vigas!$B$6*K14/V14)),"NO VERIF. CORTE",IF(NOT(L14>=C14*100/VLOOKUP(Y14,Datos_vigas!$A$19:$E$23,5,0)),"VERIFICAR FLECHA","VERIFICA")))) -> VERIFICA | Y14: Continua | Z14: Invertida | AA14: 12 | AB14: =IF(Z14="Colgante",MIN(C14*100/4,J14+16*AA14),J14) -> 15 | AC14: =IF(Z14="Invertida",MIN(C14*100/4,J14+16*AA14),J14) -> 91.25 | AF14: 1.065 | AG14: 2.6 | AH14: 3
B15: VI 08b | C15: 4.87 | D15: =(Datos_vigas!$B$10*(VLOOKUP($A$4,Datos_vigas!$A$14:$E$15,2,0)*AF15+Datos_vigas!$B$7*J15*L15/10000+Datos_vigas!$B$16*AG15)+Datos_vigas!$B$11*VLOOKUP($A$4,Datos_vigas!$A$14:$E$15,3,0)*AF15) -> 2126.1 | F15: =VLOOKUP(Y15,Datos_vigas!$A$19:$E$23,4,0)*D15*C15+IF(OR(AD15="",AE15=""),0,AD15*MAX(AE15,C15-AE15)/C15) -> 5953.6115 | G15: =F15 -> 5953.6115 | H15: =VLOOKUP(Y15,Datos_vigas!$A$19:$E$23,2,0)*D15*C15^2+0.75*1000*IF(OR(AD15="",AE15=""),0,AD15*AE15*(C15-AE15)/C15/1000) -> 3601.8221 | I15: =IF(VLOOKUP(Y15,Datos_vigas!$A$19:$E$23,3,0)=0,"---",VLOOKUP(Y15,Datos_vigas!$A$19:$E$23,3,0)*D15*C15^2+0.5*1000*IF(OR(AD15="",AE15=""),0,AD15*AE15*(C15-AE15)/C15/1000)) -> 5042.4501 | J15: 15 | K15: =L15-AH15 -> 67 | L15: 70 | M15: =IF(NOT(ISNUMBER(H15)),"---",IF(H15<=0,"---",IF(H15*100/(Datos_vigas!$B$8*AB15*K15^2*Datos_vigas!$B$5)>=0.5,"REVISAR",MAX((1-SQRT(1-2*H15*100/(Datos_vigas!$B$8*AB15*K15^2*Datos_vigas!$B$5)))*AB15*K15*Datos_vigas!$B$5/Datos_vigas!$B$6,0.0033*J15*K15)))) -> 3.3165 | N15: 3 | O15: 12 | P15: =IF(NOT(ISNUMBER(I15)),"---",IF(I15<=0,"---",IF(I15*100/(Datos_vigas!$B$8*AC15*K15^2*Datos_vigas!$B$5)>=0.5,"REVISAR",MAX((1-SQRT(1-2*I15*100/(Datos_vigas!$B$8*AC15*K15^2*Datos_vigas!$B$5)))*AC15*K15*Datos_vigas!$B$5/Datos_vigas!$B$6,0.0033*J15*K15)))) -> 3.3165 | Q15: 3 | R15: 12 | S15: =F15/(J15*0.85*K15) -> 6.9694018 | T15: =G15/(J15*0.85*K15) -> 6.9694018 | U15: 6 | V15: 30 | W15: =IF(OR(M15="REVISAR",P15="REVISAR"),"SECCION INSUF.",IF(NOT(AND(M15<>"REVISAR",P15<>"REVISAR",IF(ISNUMBER(M15),N15*PI()*(O15/10)^2/4>=M15,TRUE()),IF(ISNUMBER(P15),Q15*PI()*(R15/10)^2/4>=P15,TRUE()),IF(ISNUMBER(M15),M15<=0.0163*AB15*K15,TRUE()),IF(ISNUMBER(P15),P15<=0.0163*AC15*K15,TRUE()))),"NO VERIFICA FLEX.",IF(NOT(F15<=Datos_vigas!$B$9*(0.53*SQRT(Datos_vigas!$B$5)*J15*K15+2*PI()*(U15/10)^2/4*Datos_vigas!$B$6*K15/V15)),"NO VERIF. CORTE",IF(NOT(L15>=C15*100/VLOOKUP(Y15,Datos_vigas!$A$19:$E$23,5,0)),"VERIFICAR FLECHA","VERIFICA")))) -> VERIFICA | X15: Descarga en la COL 04 de 20x20 y en VI 06. | Y15: Continua | Z15: Invertida | AA15: 12 | AB15: =IF(Z15="Colgante",MIN(C15*100/4,J15+16*AA15),J15) -> 15 | AC15: =IF(Z15="Invertida",MIN(C15*100/4,J15+16*AA15),J15) -> 121.75 | AF15: 1.065 | AG15: 2.6 | AH15: 3
B16: VI 09 | C16: 4.87 | D16: =(Datos_vigas!$B$10*(VLOOKUP($A$4,Datos_vigas!$A$14:$E$15,2,0)*AF16+Datos_vigas!$B$7*J16*L16/10000+Datos_vigas!$B$16*AG16)+Datos_vigas!$B$11*VLOOKUP($A$4,Datos_vigas!$A$14:$E$15,3,0)*AF16) -> 2600.42 | F16: =VLOOKUP(Y16,Datos_vigas!$A$19:$E$23,4,0)*D16*C16+IF(OR(AD16="",AE16=""),0,AD16*MAX(AE16,C16-AE16)/C16) -> 6332.0227 | G16: =F16 -> 6332.0227 | H16: =VLOOKUP(Y16,Datos_vigas!$A$19:$E$23,2,0)*D16*C16^2+0.75*1000*IF(OR(AD16="",AE16=""),0,AD16*AE16*(C16-AE16)/C16/1000) -> 7709.2376 | I16: =IF(VLOOKUP(Y16,Datos_vigas!$A$19:$E$23,3,0)=0,"---",VLOOKUP(Y16,Datos_vigas!$A$19:$E$23,3,0)*D16*C16^2+0.5*1000*IF(OR(AD16="",AE16=""),0,AD16*AE16*(C16-AE16)/C16/1000)) -> --- | J16: 15 | K16: =L16-AH16 -> 67 | L16: 70 | M16: =IF(NOT(ISNUMBER(H16)),"---",IF(H16<=0,"---",IF(H16*100/(Datos_vigas!$B$8*AB16*K16^2*Datos_vigas!$B$5)>=0.5,"REVISAR",MAX((1-SQRT(1-2*H16*100/(Datos_vigas!$B$8*AB16*K16^2*Datos_vigas!$B$5)))*AB16*K16*Datos_vigas!$B$5/Datos_vigas!$B$6,0.0033*J16*K16)))) -> 3.3165 | N16: 3 | O16: 12 | P16: =IF(NOT(ISNUMBER(I16)),"---",IF(I16<=0,"---",IF(I16*100/(Datos_vigas!$B$8*AC16*K16^2*Datos_vigas!$B$5)>=0.5,"REVISAR",MAX((1-SQRT(1-2*I16*100/(Datos_vigas!$B$8*AC16*K16^2*Datos_vigas!$B$5)))*AC16*K16*Datos_vigas!$B$5/Datos_vigas!$B$6,0.0033*J16*K16)))) -> --- | Q16: --- | R16: --- | S16: =F16/(J16*0.85*K16) -> 7.4123766 | T16: =G16/(J16*0.85*K16) -> 7.4123766 | U16: 6 | V16: 30 | W16: =IF(OR(M16="REVISAR",P16="REVISAR"),"SECCION INSUF.",IF(NOT(AND(M16<>"REVISAR",P16<>"REVISAR",IF(ISNUMBER(M16),N16*PI()*(O16/10)^2/4>=M16,TRUE()),IF(ISNUMBER(P16),Q16*PI()*(R16/10)^2/4>=P16,TRUE()),IF(ISNUMBER(M16),M16<=0.0163*AB16*K16,TRUE()),IF(ISNUMBER(P16),P16<=0.0163*AC16*K16,TRUE()))),"NO VERIFICA FLEX.",IF(NOT(F16<=Datos_vigas!$B$9*(0.53*SQRT(Datos_vigas!$B$5)*J16*K16+2*PI()*(U16/10)^2/4*Datos_vigas!$B$6*K16/V16)),"NO VERIF. CORTE",IF(NOT(L16>=C16*100/VLOOKUP(Y16,Datos_vigas!$A$19:$E$23,5,0)),"VERIFICAR FLECHA","VERIFICA")))) -> VERIFICA | X16: Viga secundaria: sus dos extremos descargan en otras vigas, VI 04a y VI 06, no en columnas ni tabiques. | Y16: Simplemente apoyada | Z16: Invertida | AA16: 12 | AB16: =IF(Z16="Colgante",MIN(C16*100/4,J16+16*AA16),J16) -> 15 | AC16: =IF(Z16="Invertida",MIN(C16*100/4,J16+16*AA16),J16) -> 121.75 | AF16: 1.549 | AG16: 2.6 | AH16: 3
B17: VI 10a | C17: 2.55 | D17: =(Datos_vigas!$B$10*(VLOOKUP($A$4,Datos_vigas!$A$14:$E$15,2,0)*AF17+Datos_vigas!$B$7*J17*L17/10000+Datos_vigas!$B$16*AG17)+Datos_vigas!$B$11*VLOOKUP($A$4,Datos_vigas!$A$14:$E$15,3,0)*AF17) -> 1082.4 | F17: =VLOOKUP(Y17,Datos_vigas!$A$19:$E$23,4,0)*D17*C17+IF(OR(AD17="",AE17=""),0,AD17*MAX(AE17,C17-AE17)/C17) -> 1587.069 | G17: =F17 -> 1587.069 | H17: =VLOOKUP(Y17,Datos_vigas!$A$19:$E$23,2,0)*D17*C17^2+0.75*1000*IF(OR(AD17="",AE17=""),0,AD17*AE17*(C17-AE17)/C17/1000) -> 502.7462 | I17: =IF(VLOOKUP(Y17,Datos_vigas!$A$19:$E$23,3,0)=0,"---",VLOOKUP(Y17,Datos_vigas!$A$19:$E$23,3,0)*D17*C17^2+0.5*1000*IF(OR(AD17="",AE17=""),0,AD17*AE17*(C17-AE17)/C17/1000)) -> 703.8306 | J17: 15 | K17: =L17-AH17 -> 67 | L17: 70 | M17: =IF(NOT(ISNUMBER(H17)),"---",IF(H17<=0,"---",IF(H17*100/(Datos_vigas!$B$8*AB17*K17^2*Datos_vigas!$B$5)>=0.5,"REVISAR",MAX((1-SQRT(1-2*H17*100/(Datos_vigas!$B$8*AB17*K17^2*Datos_vigas!$B$5)))*AB17*K17*Datos_vigas!$B$5/Datos_vigas!$B$6,0.0033*J17*K17)))) -> 3.3165 | N17: 3 | O17: 12 | P17: =IF(NOT(ISNUMBER(I17)),"---",IF(I17<=0,"---",IF(I17*100/(Datos_vigas!$B$8*AC17*K17^2*Datos_vigas!$B$5)>=0.5,"REVISAR",MAX((1-SQRT(1-2*I17*100/(Datos_vigas!$B$8*AC17*K17^2*Datos_vigas!$B$5)))*AC17*K17*Datos_vigas!$B$5/Datos_vigas!$B$6,0.0033*J17*K17)))) -> 3.3165 | Q17: 3 | R17: 12 | S17: =F17/(J17*0.85*K17) -> 1.8578507 | T17: =G17/(J17*0.85*K17) -> 1.8578507 | U17: 6 | V17: 30 | W17: =IF(OR(M17="REVISAR",P17="REVISAR"),"SECCION INSUF.",IF(NOT(AND(M17<>"REVISAR",P17<>"REVISAR",IF(ISNUMBER(M17),N17*PI()*(O17/10)^2/4>=M17,TRUE()),IF(ISNUMBER(P17),Q17*PI()*(R17/10)^2/4>=P17,TRUE()),IF(ISNUMBER(M17),M17<=0.0163*AB17*K17,TRUE()),IF(ISNUMBER(P17),P17<=0.0163*AC17*K17,TRUE()))),"NO VERIFICA FLEX.",IF(NOT(F17<=Datos_vigas!$B$9*(0.53*SQRT(Datos_vigas!$B$5)*J17*K17+2*PI()*(U17/10)^2/4*Datos_vigas!$B$6*K17/V17)),"NO VERIF. CORTE",IF(NOT(L17>=C17*100/VLOOKUP(Y17,Datos_vigas!$A$19:$E$23,5,0)),"VERIFICAR FLECHA","VERIFICA")))) -> VERIFICA | Y17: Continua | Z17: Invertida | AA17: 12 | AB17: =IF(Z17="Colgante",MIN(C17*100/4,J17+16*AA17),J17) -> 15 | AC17: =IF(Z17="Invertida",MIN(C17*100/4,J17+16*AA17),J17) -> 63.75 | AF17: 0 | AG17: 2.6 | AH17: 3
B18: VI 10b | C18: 4 | D18: =(Datos_vigas!$B$10*(VLOOKUP($A$4,Datos_vigas!$A$14:$E$15,2,0)*AF18+Datos_vigas!$B$7*J18*L18/10000+Datos_vigas!$B$16*AG18)+Datos_vigas!$B$11*VLOOKUP($A$4,Datos_vigas!$A$14:$E$15,3,0)*AF18) -> 2870.9 | F18: =VLOOKUP(Y18,Datos_vigas!$A$19:$E$23,4,0)*D18*C18+IF(OR(AD18="",AE18=""),0,AD18*MAX(AE18,C18-AE18)/C18) -> 6603.07 | G18: =F18 -> 6603.07 | H18: =VLOOKUP(Y18,Datos_vigas!$A$19:$E$23,2,0)*D18*C18^2+0.75*1000*IF(OR(AD18="",AE18=""),0,AD18*AE18*(C18-AE18)/C18/1000) -> 3281.0942 | I18: =IF(VLOOKUP(Y18,Datos_vigas!$A$19:$E$23,3,0)=0,"---",VLOOKUP(Y18,Datos_vigas!$A$19:$E$23,3,0)*D18*C18^2+0.5*1000*IF(OR(AD18="",AE18=""),0,AD18*AE18*(C18-AE18)/C18/1000)) -> 4593.44 | J18: 15 | K18: =L18-AH18 -> 67 | L18: 70 | M18: =IF(NOT(ISNUMBER(H18)),"---",IF(H18<=0,"---",IF(H18*100/(Datos_vigas!$B$8*AB18*K18^2*Datos_vigas!$B$5)>=0.5,"REVISAR",MAX((1-SQRT(1-2*H18*100/(Datos_vigas!$B$8*AB18*K18^2*Datos_vigas!$B$5)))*AB18*K18*Datos_vigas!$B$5/Datos_vigas!$B$6,0.0033*J18*K18)))) -> 3.3165 | N18: 3 | O18: 12 | P18: =IF(NOT(ISNUMBER(I18)),"---",IF(I18<=0,"---",IF(I18*100/(Datos_vigas!$B$8*AC18*K18^2*Datos_vigas!$B$5)>=0.5,"REVISAR",MAX((1-SQRT(1-2*I18*100/(Datos_vigas!$B$8*AC18*K18^2*Datos_vigas!$B$5)))*AC18*K18*Datos_vigas!$B$5/Datos_vigas!$B$6,0.0033*J18*K18)))) -> 3.3165 | Q18: 3 | R18: 12 | S18: =F18/(J18*0.85*K18) -> 7.7296693 | T18: =G18/(J18*0.85*K18) -> 7.7296693 | U18: 6 | V18: 30 | W18: =IF(OR(M18="REVISAR",P18="REVISAR"),"SECCION INSUF.",IF(NOT(AND(M18<>"REVISAR",P18<>"REVISAR",IF(ISNUMBER(M18),N18*PI()*(O18/10)^2/4>=M18,TRUE()),IF(ISNUMBER(P18),Q18*PI()*(R18/10)^2/4>=P18,TRUE()),IF(ISNUMBER(M18),M18<=0.0163*AB18*K18,TRUE()),IF(ISNUMBER(P18),P18<=0.0163*AC18*K18,TRUE()))),"NO VERIFICA FLEX.",IF(NOT(F18<=Datos_vigas!$B$9*(0.53*SQRT(Datos_vigas!$B$5)*J18*K18+2*PI()*(U18/10)^2/4*Datos_vigas!$B$6*K18/V18)),"NO VERIF. CORTE",IF(NOT(L18>=C18*100/VLOOKUP(Y18,Datos_vigas!$A$19:$E$23,5,0)),"VERIFICAR FLECHA","VERIFICA")))) -> VERIFICA | Y18: Continua | Z18: Invertida | AA18: 12 | AB18: =IF(Z18="Colgante",MIN(C18*100/4,J18+16*AA18),J18) -> 15 | AC18: =IF(Z18="Invertida",MIN(C18*100/4,J18+16*AA18),J18) -> 100 | AF18: 1.825 | AG18: 2.6 | AH18: 3
B19: VI 10c | C19: 3.6 | D19: =(Datos_vigas!$B$10*(VLOOKUP($A$4,Datos_vigas!$A$14:$E$15,2,0)*AF19+Datos_vigas!$B$7*J19*L19/10000+Datos_vigas!$B$16*AG19)+Datos_vigas!$B$11*VLOOKUP($A$4,Datos_vigas!$A$14:$E$15,3,0)*AF19) -> 1082.4 | F19: =VLOOKUP(Y19,Datos_vigas!$A$19:$E$23,4,0)*D19*C19+IF(OR(AD19="",AE19=""),0,AD19*MAX(AE19,C19-AE19)/C19) -> 2240.568 | G19: =F19 -> 2240.568 | H19: =VLOOKUP(Y19,Datos_vigas!$A$19:$E$23,2,0)*D19*C19^2+0.75*1000*IF(OR(AD19="",AE19=""),0,AD19*AE19*(C19-AE19)/C19/1000) -> 1002.0132 | I19: =IF(VLOOKUP(Y19,Datos_vigas!$A$19:$E$23,3,0)=0,"---",VLOOKUP(Y19,Datos_vigas!$A$19:$E$23,3,0)*D19*C19^2+0.5*1000*IF(OR(AD19="",AE19=""),0,AD19*AE19*(C19-AE19)/C19/1000)) -> 1402.7904 | J19: 15 | K19: =L19-AH19 -> 67 | L19: 70 | M19: =IF(NOT(ISNUMBER(H19)),"---",IF(H19<=0,"---",IF(H19*100/(Datos_vigas!$B$8*AB19*K19^2*Datos_vigas!$B$5)>=0.5,"REVISAR",MAX((1-SQRT(1-2*H19*100/(Datos_vigas!$B$8*AB19*K19^2*Datos_vigas!$B$5)))*AB19*K19*Datos_vigas!$B$5/Datos_vigas!$B$6,0.0033*J19*K19)))) -> 3.3165 | N19: 3 | O19: 12 | P19: =IF(NOT(ISNUMBER(I19)),"---",IF(I19<=0,"---",IF(I19*100/(Datos_vigas!$B$8*AC19*K19^2*Datos_vigas!$B$5)>=0.5,"REVISAR",MAX((1-SQRT(1-2*I19*100/(Datos_vigas!$B$8*AC19*K19^2*Datos_vigas!$B$5)))*AC19*K19*Datos_vigas!$B$5/Datos_vigas!$B$6,0.0033*J19*K19)))) -> 3.3165 | Q19: 3 | R19: 12 | S19: =F19/(J19*0.85*K19) -> 2.6228481 | T19: =G19/(J19*0.85*K19) -> 2.6228481 | U19: 6 | V19: 30 | W19: =IF(OR(M19="REVISAR",P19="REVISAR"),"SECCION INSUF.",IF(NOT(AND(M19<>"REVISAR",P19<>"REVISAR",IF(ISNUMBER(M19),N19*PI()*(O19/10)^2/4>=M19,TRUE()),IF(ISNUMBER(P19),Q19*PI()*(R19/10)^2/4>=P19,TRUE()),IF(ISNUMBER(M19),M19<=0.0163*AB19*K19,TRUE()),IF(ISNUMBER(P19),P19<=0.0163*AC19*K19,TRUE()))),"NO VERIFICA FLEX.",IF(NOT(F19<=Datos_vigas!$B$9*(0.53*SQRT(Datos_vigas!$B$5)*J19*K19+2*PI()*(U19/10)^2/4*Datos_vigas!$B$6*K19/V19)),"NO VERIF. CORTE",IF(NOT(L19>=C19*100/VLOOKUP(Y19,Datos_vigas!$A$19:$E$23,5,0)),"VERIFICAR FLECHA","VERIFICA")))) -> VERIFICA | Y19: Continua | Z19: Invertida | AA19: 12 | AB19: =IF(Z19="Colgante",MIN(C19*100/4,J19+16*AA19),J19) -> 15 | AC19: =IF(Z19="Invertida",MIN(C19*100/4,J19+16*AA19),J19) -> 90 | AF19: 0 | AG19: 2.6 | AH19: 3
B20: VI 11a | C20: 7.68 | D20: =(Datos_vigas!$B$10*(VLOOKUP($A$4,Datos_vigas!$A$14:$E$15,2,0)*AF20+Datos_vigas!$B$7*J20*L20/10000+Datos_vigas!$B$16*AG20)+Datos_vigas!$B$11*VLOOKUP($A$4,Datos_vigas!$A$14:$E$15,3,0)*AF20) -> 2870.9 | F20: =VLOOKUP(Y20,Datos_vigas!$A$19:$E$23,4,0)*D20*C20+IF(OR(AD20="",AE20=""),0,AD20*MAX(AE20,C20-AE20)/C20) -> 13780.32 | G20: =F20 -> 13780.32 | H20: =VLOOKUP(Y20,Datos_vigas!$A$19:$E$23,2,0)*D20*C20^2+0.75*1000*IF(OR(AD20="",AE20=""),0,AD20*AE20*(C20-AE20)/C20/1000) -> 11905.773 | I20: =IF(VLOOKUP(Y20,Datos_vigas!$A$19:$E$23,3,0)=0,"---",VLOOKUP(Y20,Datos_vigas!$A$19:$E$23,3,0)*D20*C20^2+0.5*1000*IF(OR(AD20="",AE20=""),0,AD20*AE20*(C20-AE20)/C20/1000)) -> 21166.572 | J20: 15 | K20: =L20-AH20 -> 67 | L20: 70 | M20: =IF(NOT(ISNUMBER(H20)),"---",IF(H20<=0,"---",IF(H20*100/(Datos_vigas!$B$8*AB20*K20^2*Datos_vigas!$B$5)>=0.5,"REVISAR",MAX((1-SQRT(1-2*H20*100/(Datos_vigas!$B$8*AB20*K20^2*Datos_vigas!$B$5)))*AB20*K20*Datos_vigas!$B$5/Datos_vigas!$B$6,0.0033*J20*K20)))) -> 4.9442478 | N20: 2 | O20: 20 | P20: =IF(NOT(ISNUMBER(I20)),"---",IF(I20<=0,"---",IF(I20*100/(Datos_vigas!$B$8*AC20*K20^2*Datos_vigas!$B$5)>=0.5,"REVISAR",MAX((1-SQRT(1-2*I20*100/(Datos_vigas!$B$8*AC20*K20^2*Datos_vigas!$B$5)))*AC20*K20*Datos_vigas!$B$5/Datos_vigas!$B$6,0.0033*J20*K20)))) -> 8.4126611 | Q20: 2 | R20: 25 | S20: =F20/(J20*0.85*K20) -> 16.131484 | T20: =G20/(J20*0.85*K20) -> 16.131484 | U20: 6 | V20: 10 | W20: =IF(OR(M20="REVISAR",P20="REVISAR"),"SECCION INSUF.",IF(NOT(AND(M20<>"REVISAR",P20<>"REVISAR",IF(ISNUMBER(M20),N20*PI()*(O20/10)^2/4>=M20,TRUE()),IF(ISNUMBER(P20),Q20*PI()*(R20/10)^2/4>=P20,TRUE()),IF(ISNUMBER(M20),M20<=0.0163*AB20*K20,TRUE()),IF(ISNUMBER(P20),P20<=0.0163*AC20*K20,TRUE()))),"NO VERIFICA FLEX.",IF(NOT(F20<=Datos_vigas!$B$9*(0.53*SQRT(Datos_vigas!$B$5)*J20*K20+2*PI()*(U20/10)^2/4*Datos_vigas!$B$6*K20/V20)),"NO VERIF. CORTE",IF(NOT(L20>=C20*100/VLOOKUP(Y20,Datos_vigas!$A$19:$E$23,5,0)),"VERIFICAR FLECHA","VERIFICA")))) -> VERIFICA | X20: El plano rotula 'VI 111'; se interpreta 11a por el orden a-b-c. Sin apoyo intermedio, empotrada en tabiques. Apoya en columna COL 02 de 15x30 y en el tabique T08a. Viga de borde: recibe la reaccion de la losa excentrica y queda sometida a TORSION, no verificada en esta planilla. | Y20: Empotrada-apoyada | Z20: Invertida | AA20: 12 | AB20: =IF(Z20="Colgante",MIN(C20*100/4,J20+16*AA20),J20) -> 15 | AC20: =IF(Z20="Invertida",MIN(C20*100/4,J20+16*AA20),J20) -> 192 | AF20: 1.825 | AG20: 2.6 | AH20: 3
B21: VI 11b | C21: 3.45 | D21: =(Datos_vigas!$B$10*(VLOOKUP($A$4,Datos_vigas!$A$14:$E$15,2,0)*AF21+Datos_vigas!$B$7*J21*L21/10000+Datos_vigas!$B$16*AG21)+Datos_vigas!$B$11*VLOOKUP($A$4,Datos_vigas!$A$14:$E$15,3,0)*AF21) -> 1082.4 | F21: =VLOOKUP(Y21,Datos_vigas!$A$19:$E$23,4,0)*D21*C21+IF(OR(AD21="",AE21=""),0,AD21*MAX(AE21,C21-AE21)/C21) -> 2147.211 | G21: =F21 -> 2147.211 | H21: =VLOOKUP(Y21,Datos_vigas!$A$19:$E$23,2,0)*D21*C21^2+0.75*1000*IF(OR(AD21="",AE21=""),0,AD21*AE21*(C21-AE21)/C21/1000) -> 920.25169 | I21: =IF(VLOOKUP(Y21,Datos_vigas!$A$19:$E$23,3,0)=0,"---",VLOOKUP(Y21,Datos_vigas!$A$19:$E$23,3,0)*D21*C21^2+0.5*1000*IF(OR(AD21="",AE21=""),0,AD21*AE21*(C21-AE21)/C21/1000)) -> 1288.3266 | J21: 15 | K21: =L21-AH21 -> 67 | L21: 70 | M21: =IF(NOT(ISNUMBER(H21)),"---",IF(H21<=0,"---",IF(H21*100/(Datos_vigas!$B$8*AB21*K21^2*Datos_vigas!$B$5)>=0.5,"REVISAR",MAX((1-SQRT(1-2*H21*100/(Datos_vigas!$B$8*AB21*K21^2*Datos_vigas!$B$5)))*AB21*K21*Datos_vigas!$B$5/Datos_vigas!$B$6,0.0033*J21*K21)))) -> 3.3165 | N21: 3 | O21: 12 | P21: =IF(NOT(ISNUMBER(I21)),"---",IF(I21<=0,"---",IF(I21*100/(Datos_vigas!$B$8*AC21*K21^2*Datos_vigas!$B$5)>=0.5,"REVISAR",MAX((1-SQRT(1-2*I21*100/(Datos_vigas!$B$8*AC21*K21^2*Datos_vigas!$B$5)))*AC21*K21*Datos_vigas!$B$5/Datos_vigas!$B$6,0.0033*J21*K21)))) -> 3.3165 | Q21: 3 | R21: 12 | S21: =F21/(J21*0.85*K21) -> 2.5135628 | T21: =G21/(J21*0.85*K21) -> 2.5135628 | U21: 6 | V21: 30 | W21: =IF(OR(M21="REVISAR",P21="REVISAR"),"SECCION INSUF.",IF(NOT(AND(M21<>"REVISAR",P21<>"REVISAR",IF(ISNUMBER(M21),N21*PI()*(O21/10)^2/4>=M21,TRUE()),IF(ISNUMBER(P21),Q21*PI()*(R21/10)^2/4>=P21,TRUE()),IF(ISNUMBER(M21),M21<=0.0163*AB21*K21,TRUE()),IF(ISNUMBER(P21),P21<=0.0163*AC21*K21,TRUE()))),"NO VERIFICA FLEX.",IF(NOT(F21<=Datos_vigas!$B$9*(0.53*SQRT(Datos_vigas!$B$5)*J21*K21+2*PI()*(U21/10)^2/4*Datos_vigas!$B$6*K21/V21)),"NO VERIF. CORTE",IF(NOT(L21>=C21*100/VLOOKUP(Y21,Datos_vigas!$A$19:$E$23,5,0)),"VERIFICAR FLECHA","VERIFICA")))) -> VERIFICA | X21: Viga de borde: recibe la reaccion de la losa excentrica y queda sometida a TORSION, no verificada en esta planilla. | Y21: Continua | Z21: Invertida | AA21: 12 | AB21: =IF(Z21="Colgante",MIN(C21*100/4,J21+16*AA21),J21) -> 15 | AC21: =IF(Z21="Invertida",MIN(C21*100/4,J21+16*AA21),J21) -> 86.25 | AF21: 0 | AG21: 2.6 | AH21: 3
B22: VI 11c | C22: 5.02 | D22: =(Datos_vigas!$B$10*(VLOOKUP($A$4,Datos_vigas!$A$14:$E$15,2,0)*AF22+Datos_vigas!$B$7*J22*L22/10000+Datos_vigas!$B$16*AG22)+Datos_vigas!$B$11*VLOOKUP($A$4,Datos_vigas!$A$14:$E$15,3,0)*AF22) -> 2600.42 | F22: =VLOOKUP(Y22,Datos_vigas!$A$19:$E$23,4,0)*D22*C22+IF(OR(AD22="",AE22=""),0,AD22*MAX(AE22,C22-AE22)/C22) -> 7506.1123 | G22: =F22 -> 7506.1123 | H22: =VLOOKUP(Y22,Datos_vigas!$A$19:$E$23,2,0)*D22*C22^2+0.75*1000*IF(OR(AD22="",AE22=""),0,AD22*AE22*(C22-AE22)/C22/1000) -> 4680.9239 | I22: =IF(VLOOKUP(Y22,Datos_vigas!$A$19:$E$23,3,0)=0,"---",VLOOKUP(Y22,Datos_vigas!$A$19:$E$23,3,0)*D22*C22^2+0.5*1000*IF(OR(AD22="",AE22=""),0,AD22*AE22*(C22-AE22)/C22/1000)) -> 6553.1624 | J22: 15 | K22: =L22-AH22 -> 67 | L22: 70 | M22: =IF(NOT(ISNUMBER(H22)),"---",IF(H22<=0,"---",IF(H22*100/(Datos_vigas!$B$8*AB22*K22^2*Datos_vigas!$B$5)>=0.5,"REVISAR",MAX((1-SQRT(1-2*H22*100/(Datos_vigas!$B$8*AB22*K22^2*Datos_vigas!$B$5)))*AB22*K22*Datos_vigas!$B$5/Datos_vigas!$B$6,0.0033*J22*K22)))) -> 3.3165 | N22: 3 | O22: 12 | P22: =IF(NOT(ISNUMBER(I22)),"---",IF(I22<=0,"---",IF(I22*100/(Datos_vigas!$B$8*AC22*K22^2*Datos_vigas!$B$5)>=0.5,"REVISAR",MAX((1-SQRT(1-2*I22*100/(Datos_vigas!$B$8*AC22*K22^2*Datos_vigas!$B$5)))*AC22*K22*Datos_vigas!$B$5/Datos_vigas!$B$6,0.0033*J22*K22)))) -> 3.3165 | Q22: 3 | R22: 12 | S22: =F22/(J22*0.85*K22) -> 8.7867865 | T22: =G22/(J22*0.85*K22) -> 8.7867865 | U22: 6 | V22: 30 | W22: =IF(OR(M22="REVISAR",P22="REVISAR"),"SECCION INSUF.",IF(NOT(AND(M22<>"REVISAR",P22<>"REVISAR",IF(ISNUMBER(M22),N22*PI()*(O22/10)^2/4>=M22,TRUE()),IF(ISNUMBER(P22),Q22*PI()*(R22/10)^2/4>=P22,TRUE()),IF(ISNUMBER(M22),M22<=0.0163*AB22*K22,TRUE()),IF(ISNUMBER(P22),P22<=0.0163*AC22*K22,TRUE()))),"NO VERIFICA FLEX.",IF(NOT(F22<=Datos_vigas!$B$9*(0.53*SQRT(Datos_vigas!$B$5)*J22*K22+2*PI()*(U22/10)^2/4*Datos_vigas!$B$6*K22/V22)),"NO VERIF. CORTE",IF(NOT(L22>=C22*100/VLOOKUP(Y22,Datos_vigas!$A$19:$E$23,5,0)),"VERIFICAR FLECHA","VERIFICA")))) -> VERIFICA | X22: Viga de borde: recibe la reaccion de la losa excentrica y queda sometida a TORSION, no verificada en esta planilla. | Y22: Continua | Z22: Invertida | AA22: 12 | AB22: =IF(Z22="Colgante",MIN(C22*100/4,J22+16*AA22),J22) -> 15 | AC22: =IF(Z22="Invertida",MIN(C22*100/4,J22+16*AA22),J22) -> 125.5 | AF22: 1.549 | AG22: 2.6 | AH22: 3
B23: VCH 03a | C23: 3.71 | D23: =(Datos_vigas!$B$10*(VLOOKUP($A$4,Datos_vigas!$A$14:$E$15,2,0)*AF23+Datos_vigas!$B$7*J23*L23/10000+Datos_vigas!$B$16*AG23)+Datos_vigas!$B$11*VLOOKUP($A$4,Datos_vigas!$A$14:$E$15,3,0)*AF23) -> 2987.76 | F23: =VLOOKUP(Y23,Datos_vigas!$A$19:$E$23,4,0)*D23*C23+IF(OR(AD23="",AE23=""),0,AD23*MAX(AE23,C23-AE23)/C23) -> 6373.639 | G23: =F23 -> 6373.639 | H23: =VLOOKUP(Y23,Datos_vigas!$A$19:$E$23,2,0)*D23*C23^2+0.75*1000*IF(OR(AD23="",AE23=""),0,AD23*AE23*(C23-AE23)/C23/1000) -> 2937.475 | I23: =IF(VLOOKUP(Y23,Datos_vigas!$A$19:$E$23,3,0)=0,"---",VLOOKUP(Y23,Datos_vigas!$A$19:$E$23,3,0)*D23*C23^2+0.5*1000*IF(OR(AD23="",AE23=""),0,AD23*AE23*(C23-AE23)/C23/1000)) -> 4112.3827 | J23: 40 | K23: =L23-AH23 -> 10 | L23: 13 | M23: =IF(NOT(ISNUMBER(H23)),"---",IF(H23<=0,"---",IF(H23*100/(Datos_vigas!$B$8*AB23*K23^2*Datos_vigas!$B$5)>=0.5,"REVISAR",MAX((1-SQRT(1-2*H23*100/(Datos_vigas!$B$8*AB23*K23^2*Datos_vigas!$B$5)))*AB23*K23*Datos_vigas!$B$5/Datos_vigas!$B$6,0.0033*J23*K23)))) -> 8.561361 | N23: 8 | O23: 12 | P23: =IF(NOT(ISNUMBER(I23)),"---",IF(I23<=0,"---",IF(I23*100/(Datos_vigas!$B$8*AC23*K23^2*Datos_vigas!$B$5)>=0.5,"REVISAR",MAX((1-SQRT(1-2*I23*100/(Datos_vigas!$B$8*AC23*K23^2*Datos_vigas!$B$5)))*AC23*K23*Datos_vigas!$B$5/Datos_vigas!$B$6,0.0033*J23*K23)))) -> REVISAR | Q23: 5 | R23: 6 | S23: =F23/(J23*0.85*K23) -> 18.745997 | T23: =G23/(J23*0.85*K23) -> 18.745997 | U23: 12 | V23: 5 | W23: =IF(OR(M23="REVISAR",P23="REVISAR"),"SECCION INSUF.",IF(NOT(AND(M23<>"REVISAR",P23<>"REVISAR",IF(ISNUMBER(M23),N23*PI()*(O23/10)^2/4>=M23,TRUE()),IF(ISNUMBER(P23),Q23*PI()*(R23/10)^2/4>=P23,TRUE()),IF(ISNUMBER(M23),M23<=0.0163*AB23*K23,TRUE()),IF(ISNUMBER(P23),P23<=0.0163*AC23*K23,TRUE()))),"NO VERIFICA FLEX.",IF(NOT(F23<=Datos_vigas!$B$9*(0.53*SQRT(Datos_vigas!$B$5)*J23*K23+2*PI()*(U23/10)^2/4*Datos_vigas!$B$6*K23/V23)),"NO VERIF. CORTE",IF(NOT(L23>=C23*100/VLOOKUP(Y23,Datos_vigas!$A$19:$E$23,5,0)),"VERIFICAR FLECHA","VERIFICA")))) -> SECCION INSUF. | X23: Excede cuantia maxima y no llega a la altura minima por flecha. Revisar el ancho tributario real. Separacion de estribos menor a 10 cm: revisar constructividad. | Y23: Continua | Z23: Colgante | AA23: 12 | AB23: =IF(Z23="Colgante",MIN(C23*100/4,J23+16*AA23),J23) -> 92.75 | AC23: =IF(Z23="Invertida",MIN(C23*100/4,J23+16*AA23),J23) -> 40 | AF23: 2.1 | AG23: 2.6 | AH23: 3
B24: VCH 03b | C24: 2.13 | D24: =(Datos_vigas!$B$10*(VLOOKUP($A$4,Datos_vigas!$A$14:$E$15,2,0)*AF24+Datos_vigas!$B$7*J24*L24/10000+Datos_vigas!$B$16*AG24)+Datos_vigas!$B$11*VLOOKUP($A$4,Datos_vigas!$A$14:$E$15,3,0)*AF24) -> 2987.76 | F24: =VLOOKUP(Y24,Datos_vigas!$A$19:$E$23,4,0)*D24*C24+IF(OR(AD24="",AE24=""),0,AD24*MAX(AE24,C24-AE24)/C24) -> 3659.2591 | G24: =F24 -> 3659.2591 | H24: =VLOOKUP(Y24,Datos_vigas!$A$19:$E$23,2,0)*D24*C24^2+0.75*1000*IF(OR(AD24="",AE24=""),0,AD24*AE24*(C24-AE24)/C24/1000) -> 968.24567 | I24: =IF(VLOOKUP(Y24,Datos_vigas!$A$19:$E$23,3,0)=0,"---",VLOOKUP(Y24,Datos_vigas!$A$19:$E$23,3,0)*D24*C24^2+0.5*1000*IF(OR(AD24="",AE24=""),0,AD24*AE24*(C24-AE24)/C24/1000)) -> 1355.5168 | J24: 40 | K24: =L24-AH24 -> 10 | L24: 13 | M24: =IF(NOT(ISNUMBER(H24)),"---",IF(H24<=0,"---",IF(H24*100/(Datos_vigas!$B$8*AB24*K24^2*Datos_vigas!$B$5)>=0.5,"REVISAR",MAX((1-SQRT(1-2*H24*100/(Datos_vigas!$B$8*AB24*K24^2*Datos_vigas!$B$5)))*AB24*K24*Datos_vigas!$B$5/Datos_vigas!$B$6,0.0033*J24*K24)))) -> 2.6982172 | N24: 10 | O24: 6 | P24: =IF(NOT(ISNUMBER(I24)),"---",IF(I24<=0,"---",IF(I24*100/(Datos_vigas!$B$8*AC24*K24^2*Datos_vigas!$B$5)>=0.5,"REVISAR",MAX((1-SQRT(1-2*I24*100/(Datos_vigas!$B$8*AC24*K24^2*Datos_vigas!$B$5)))*AC24*K24*Datos_vigas!$B$5/Datos_vigas!$B$6,0.0033*J24*K24)))) -> 3.9825387 | Q24: 8 | R24: 8 | S24: =F24/(J24*0.85*K24) -> 10.762527 | T24: =G24/(J24*0.85*K24) -> 10.762527 | U24: 12 | V24: 5 | W24: =IF(OR(M24="REVISAR",P24="REVISAR"),"SECCION INSUF.",IF(NOT(AND(M24<>"REVISAR",P24<>"REVISAR",IF(ISNUMBER(M24),N24*PI()*(O24/10)^2/4>=M24,TRUE()),IF(ISNUMBER(P24),Q24*PI()*(R24/10)^2/4>=P24,TRUE()),IF(ISNUMBER(M24),M24<=0.0163*AB24*K24,TRUE()),IF(ISNUMBER(P24),P24<=0.0163*AC24*K24,TRUE()))),"NO VERIFICA FLEX.",IF(NOT(F24<=Datos_vigas!$B$9*(0.53*SQRT(Datos_vigas!$B$5)*J24*K24+2*PI()*(U24/10)^2/4*Datos_vigas!$B$6*K24/V24)),"NO VERIF. CORTE",IF(NOT(L24>=C24*100/VLOOKUP(Y24,Datos_vigas!$A$19:$E$23,5,0)),"VERIFICAR FLECHA","VERIFICA")))) -> VERIFICA | X24: Separacion de estribos menor a 10 cm: revisar constructividad. | Y24: Continua | Z24: Colgante | AA24: 12 | AB24: =IF(Z24="Colgante",MIN(C24*100/4,J24+16*AA24),J24) -> 53.25 | AC24: =IF(Z24="Invertida",MIN(C24*100/4,J24+16*AA24),J24) -> 40 | AF24: 2.1 | AG24: 2.6 | AH24: 3
B25: VCH 05 | C25: 3.71 | D25: =(Datos_vigas!$B$10*(VLOOKUP($A$4,Datos_vigas!$A$14:$E$15,2,0)*AF25+Datos_vigas!$B$7*J25*L25/10000+Datos_vigas!$B$16*AG25)+Datos_vigas!$B$11*VLOOKUP($A$4,Datos_vigas!$A$14:$E$15,3,0)*AF25) -> 935.52 | F25: =VLOOKUP(Y25,Datos_vigas!$A$19:$E$23,4,0)*D25*C25+IF(OR(AD25="",AE25=""),0,AD25*MAX(AE25,C25-AE25)/C25) -> 1735.3896 | G25: =F25 -> 1735.3896 | H25: =VLOOKUP(Y25,Datos_vigas!$A$19:$E$23,2,0)*D25*C25^2+0.75*1000*IF(OR(AD25="",AE25=""),0,AD25*AE25*(C25-AE25)/C25/1000) -> 1609.5739 | I25: =IF(VLOOKUP(Y25,Datos_vigas!$A$19:$E$23,3,0)=0,"---",VLOOKUP(Y25,Datos_vigas!$A$19:$E$23,3,0)*D25*C25^2+0.5*1000*IF(OR(AD25="",AE25=""),0,AD25*AE25*(C25-AE25)/C25/1000)) -> --- | J25: 12 | K25: =L25-AH25 -> 42 | L25: 45 | M25: =IF(NOT(ISNUMBER(H25)),"---",IF(H25<=0,"---",IF(H25*100/(Datos_vigas!$B$8*AB25*K25^2*Datos_vigas!$B$5)>=0.5,"REVISAR",MAX((1-SQRT(1-2*H25*100/(Datos_vigas!$B$8*AB25*K25^2*Datos_vigas!$B$5)))*AB25*K25*Datos_vigas!$B$5/Datos_vigas!$B$6,0.0033*J25*K25)))) -> 1.6632 | N25: 2 | O25: 12 | P25: =IF(NOT(ISNUMBER(I25)),"---",IF(I25<=0,"---",IF(I25*100/(Datos_vigas!$B$8*AC25*K25^2*Datos_vigas!$B$5)>=0.5,"REVISAR",MAX((1-SQRT(1-2*I25*100/(Datos_vigas!$B$8*AC25*K25^2*Datos_vigas!$B$5)))*AC25*K25*Datos_vigas!$B$5/Datos_vigas!$B$6,0.0033*J25*K25)))) -> --- | Q25: --- | R25: --- | S25: =F25/(J25*0.85*K25) -> 4.0508627 | T25: =G25/(J25*0.85*K25) -> 4.0508627 | U25: 6 | V25: 20 | W25: =IF(OR(M25="REVISAR",P25="REVISAR"),"SECCION INSUF.",IF(NOT(AND(M25<>"REVISAR",P25<>"REVISAR",IF(ISNUMBER(M25),N25*PI()*(O25/10)^2/4>=M25,TRUE()),IF(ISNUMBER(P25),Q25*PI()*(R25/10)^2/4>=P25,TRUE()),IF(ISNUMBER(M25),M25<=0.0163*AB25*K25,TRUE()),IF(ISNUMBER(P25),P25<=0.0163*AC25*K25,TRUE()))),"NO VERIFICA FLEX.",IF(NOT(F25<=Datos_vigas!$B$9*(0.53*SQRT(Datos_vigas!$B$5)*J25*K25+2*PI()*(U25/10)^2/4*Datos_vigas!$B$6*K25/V25)),"NO VERIF. CORTE",IF(NOT(L25>=C25*100/VLOOKUP(Y25,Datos_vigas!$A$19:$E$23,5,0)),"VERIFICAR FLECHA","VERIFICA")))) -> VERIFICA | Y25: Simplemente apoyada | Z25: Colgante | AA25: 12 | AB25: =IF(Z25="Colgante",MIN(C25*100/4,J25+16*AA25),J25) -> 92.75 | AC25: =IF(Z25="Invertida",MIN(C25*100/4,J25+16*AA25),J25) -> 12 | AF25: 0 | AG25: 2.6 | AH25: 3
A26: TECHO | B26: VI 12 | C26: 9.9 | D26: =(Datos_vigas!$B$10*(VLOOKUP($A$26,Datos_vigas!$A$14:$E$15,2,0)*AF26+Datos_vigas!$B$7*J26*L26/10000+Datos_vigas!$B$16*AG26)+Datos_vigas!$B$11*VLOOKUP($A$26,Datos_vigas!$A$14:$E$15,3,0)*AF26) -> 2349.6 | F26: =VLOOKUP(Y26,Datos_vigas!$A$19:$E$23,4,0)*D26*C26+IF(OR(AD26="",AE26=""),0,AD26*MAX(AE26,C26-AE26)/C26) -> 13375.098 | G26: =F26 -> 13375.098 | H26: =VLOOKUP(Y26,Datos_vigas!$A$19:$E$23,2,0)*D26*C26^2+0.75*1000*IF(OR(AD26="",AE26=""),0,AD26*AE26*(C26-AE26)/C26/1000) -> 16449.207 | I26: =IF(VLOOKUP(Y26,Datos_vigas!$A$19:$E$23,3,0)=0,"---",VLOOKUP(Y26,Datos_vigas!$A$19:$E$23,3,0)*D26*C26^2+0.5*1000*IF(OR(AD26="",AE26=""),0,AD26*AE26*(C26-AE26)/C26/1000)) -> 23028.43 | J26: 15 | K26: =L26-AH26 -> 67 | L26: 70 | M26: =IF(NOT(ISNUMBER(H26)),"---",IF(H26<=0,"---",IF(H26*100/(Datos_vigas!$B$8*AB26*K26^2*Datos_vigas!$B$5)>=0.5,"REVISAR",MAX((1-SQRT(1-2*H26*100/(Datos_vigas!$B$8*AB26*K26^2*Datos_vigas!$B$5)))*AB26*K26*Datos_vigas!$B$5/Datos_vigas!$B$6,0.0033*J26*K26)))) -> 6.979731 | N26: 2 | O26: 25 | P26: =IF(NOT(ISNUMBER(I26)),"---",IF(I26<=0,"---",IF(I26*100/(Datos_vigas!$B$8*AC26*K26^2*Datos_vigas!$B$5)>=0.5,"REVISAR",MAX((1-SQRT(1-2*I26*100/(Datos_vigas!$B$8*AC26*K26^2*Datos_vigas!$B$5)))*AC26*K26*Datos_vigas!$B$5/Datos_vigas!$B$6,0.0033*J26*K26)))) -> 9.1532107 | Q26: 2 | R26: 25 | S26: =F26/(J26*0.85*K26) -> 15.657124 | T26: =G26/(J26*0.85*K26) -> 15.657124 | U26: 6 | V26: 15 | W26: =IF(OR(M26="REVISAR",P26="REVISAR"),"SECCION INSUF.",IF(NOT(AND(M26<>"REVISAR",P26<>"REVISAR",IF(ISNUMBER(M26),N26*PI()*(O26/10)^2/4>=M26,TRUE()),IF(ISNUMBER(P26),Q26*PI()*(R26/10)^2/4>=P26,TRUE()),IF(ISNUMBER(M26),M26<=0.0163*AB26*K26,TRUE()),IF(ISNUMBER(P26),P26<=0.0163*AC26*K26,TRUE()))),"NO VERIFICA FLEX.",IF(NOT(F26<=Datos_vigas!$B$9*(0.53*SQRT(Datos_vigas!$B$5)*J26*K26+2*PI()*(U26/10)^2/4*Datos_vigas!$B$6*K26/V26)),"NO VERIF. CORTE",IF(NOT(L26>=C26*100/VLOOKUP(Y26,Datos_vigas!$A$19:$E$23,5,0)),"VERIFICAR FLECHA","VERIFICA")))) -> VERIFICA | Y26: Continua | Z26: Invertida | AA26: 12 | AB26: =IF(Z26="Colgante",MIN(C26*100/4,J26+16*AA26),J26) -> 15 | AC26: =IF(Z26="Invertida",MIN(C26*100/4,J26+16*AA26),J26) -> 207 | AF26: 2.1 | AG26: 1 | AH26: 3
B27: VI 13a | C27: 6 | D27: =(Datos_vigas!$B$10*(VLOOKUP($A$26,Datos_vigas!$A$14:$E$15,2,0)*AF27+Datos_vigas!$B$7*J27*L27/10000+Datos_vigas!$B$16*AG27)+Datos_vigas!$B$11*VLOOKUP($A$26,Datos_vigas!$A$14:$E$15,3,0)*AF27) -> 3763.168 | F27: =VLOOKUP(Y27,Datos_vigas!$A$19:$E$23,4,0)*D27*C27+IF(OR(AD27="",AE27=""),0,AD27*MAX(AE27,C27-AE27)/C27) -> 12982.93 | G27: =F27 -> 12982.93 | H27: =VLOOKUP(Y27,Datos_vigas!$A$19:$E$23,2,0)*D27*C27^2+0.75*1000*IF(OR(AD27="",AE27=""),0,AD27*AE27*(C27-AE27)/C27/1000) -> 9676.9112 | I27: =IF(VLOOKUP(Y27,Datos_vigas!$A$19:$E$23,3,0)=0,"---",VLOOKUP(Y27,Datos_vigas!$A$19:$E$23,3,0)*D27*C27^2+0.5*1000*IF(OR(AD27="",AE27=""),0,AD27*AE27*(C27-AE27)/C27/1000)) -> 13547.405 | J27: 15 | K27: =L27-AH27 -> 67 | L27: 70 | M27: =IF(NOT(ISNUMBER(H27)),"---",IF(H27<=0,"---",IF(H27*100/(Datos_vigas!$B$8*AB27*K27^2*Datos_vigas!$B$5)>=0.5,"REVISAR",MAX((1-SQRT(1-2*H27*100/(Datos_vigas!$B$8*AB27*K27^2*Datos_vigas!$B$5)))*AB27*K27*Datos_vigas!$B$5/Datos_vigas!$B$6,0.0033*J27*K27)))) -> 3.9784311 | N27: 2 | O27: 16 | P27: =IF(NOT(ISNUMBER(I27)),"---",IF(I27<=0,"---",IF(I27*100/(Datos_vigas!$B$8*AC27*K27^2*Datos_vigas!$B$5)>=0.5,"REVISAR",MAX((1-SQRT(1-2*I27*100/(Datos_vigas!$B$8*AC27*K27^2*Datos_vigas!$B$5)))*AC27*K27*Datos_vigas!$B$5/Datos_vigas!$B$6,0.0033*J27*K27)))) -> 5.3779871 | Q27: 2 | R27: 20 | S27: =F27/(J27*0.85*K27) -> 15.198045 | T27: =G27/(J27*0.85*K27) -> 15.198045 | U27: 6 | V27: 15 | W27: =IF(OR(M27="REVISAR",P27="REVISAR"),"SECCION INSUF.",IF(NOT(AND(M27<>"REVISAR",P27<>"REVISAR",IF(ISNUMBER(M27),N27*PI()*(O27/10)^2/4>=M27,TRUE()),IF(ISNUMBER(P27),Q27*PI()*(R27/10)^2/4>=P27,TRUE()),IF(ISNUMBER(M27),M27<=0.0163*AB27*K27,TRUE()),IF(ISNUMBER(P27),P27<=0.0163*AC27*K27,TRUE()))),"NO VERIFICA FLEX.",IF(NOT(F27<=Datos_vigas!$B$9*(0.53*SQRT(Datos_vigas!$B$5)*J27*K27+2*PI()*(U27/10)^2/4*Datos_vigas!$B$6*K27/V27)),"NO VERIF. CORTE",IF(NOT(L27>=C27*100/VLOOKUP(Y27,Datos_vigas!$A$19:$E$23,5,0)),"VERIFICAR FLECHA","VERIFICA")))) -> VERIFICA | Y27: Continua | Z27: Invertida | AA27: 12 | AB27: =IF(Z27="Colgante",MIN(C27*100/4,J27+16*AA27),J27) -> 15 | AC27: =IF(Z27="Invertida",MIN(C27*100/4,J27+16*AA27),J27) -> 150 | AF27: 3.799 | AG27: 1 | AH27: 3
B28: VI 13b | C28: 3.75 | D28: =(Datos_vigas!$B$10*(VLOOKUP($A$26,Datos_vigas!$A$14:$E$15,2,0)*AF28+Datos_vigas!$B$7*J28*L28/10000+Datos_vigas!$B$16*AG28)+Datos_vigas!$B$11*VLOOKUP($A$26,Datos_vigas!$A$14:$E$15,3,0)*AF28) -> 2349.6 | F28: =VLOOKUP(Y28,Datos_vigas!$A$19:$E$23,4,0)*D28*C28+IF(OR(AD28="",AE28=""),0,AD28*MAX(AE28,C28-AE28)/C28) -> 5066.325 | G28: =F28 -> 5066.325 | H28: =VLOOKUP(Y28,Datos_vigas!$A$19:$E$23,2,0)*D28*C28^2+0.75*1000*IF(OR(AD28="",AE28=""),0,AD28*AE28*(C28-AE28)/C28/1000) -> 2360.1365 | I28: =IF(VLOOKUP(Y28,Datos_vigas!$A$19:$E$23,3,0)=0,"---",VLOOKUP(Y28,Datos_vigas!$A$19:$E$23,3,0)*D28*C28^2+0.5*1000*IF(OR(AD28="",AE28=""),0,AD28*AE28*(C28-AE28)/C28/1000)) -> 3304.125 | J28: 15 | K28: =L28-AH28 -> 67 | L28: 70 | M28: =IF(NOT(ISNUMBER(H28)),"---",IF(H28<=0,"---",IF(H28*100/(Datos_vigas!$B$8*AB28*K28^2*Datos_vigas!$B$5)>=0.5,"REVISAR",MAX((1-SQRT(1-2*H28*100/(Datos_vigas!$B$8*AB28*K28^2*Datos_vigas!$B$5)))*AB28*K28*Datos_vigas!$B$5/Datos_vigas!$B$6,0.0033*J28*K28)))) -> 3.3165 | N28: 3 | O28: 12 | P28: =IF(NOT(ISNUMBER(I28)),"---",IF(I28<=0,"---",IF(I28*100/(Datos_vigas!$B$8*AC28*K28^2*Datos_vigas!$B$5)>=0.5,"REVISAR",MAX((1-SQRT(1-2*I28*100/(Datos_vigas!$B$8*AC28*K28^2*Datos_vigas!$B$5)))*AC28*K28*Datos_vigas!$B$5/Datos_vigas!$B$6,0.0033*J28*K28)))) -> 3.3165 | Q28: 3 | R28: 12 | S28: =F28/(J28*0.85*K28) -> 5.9307287 | T28: =G28/(J28*0.85*K28) -> 5.9307287 | U28: 6 | V28: 30 | W28: =IF(OR(M28="REVISAR",P28="REVISAR"),"SECCION INSUF.",IF(NOT(AND(M28<>"REVISAR",P28<>"REVISAR",IF(ISNUMBER(M28),N28*PI()*(O28/10)^2/4>=M28,TRUE()),IF(ISNUMBER(P28),Q28*PI()*(R28/10)^2/4>=P28,TRUE()),IF(ISNUMBER(M28),M28<=0.0163*AB28*K28,TRUE()),IF(ISNUMBER(P28),P28<=0.0163*AC28*K28,TRUE()))),"NO VERIFICA FLEX.",IF(NOT(F28<=Datos_vigas!$B$9*(0.53*SQRT(Datos_vigas!$B$5)*J28*K28+2*PI()*(U28/10)^2/4*Datos_vigas!$B$6*K28/V28)),"NO VERIF. CORTE",IF(NOT(L28>=C28*100/VLOOKUP(Y28,Datos_vigas!$A$19:$E$23,5,0)),"VERIFICAR FLECHA","VERIFICA")))) -> VERIFICA | Y28: Continua | Z28: Invertida | AA28: 12 | AB28: =IF(Z28="Colgante",MIN(C28*100/4,J28+16*AA28),J28) -> 15 | AC28: =IF(Z28="Invertida",MIN(C28*100/4,J28+16*AA28),J28) -> 93.75 | AF28: 2.1 | AG28: 1 | AH28: 3
B29: VI 14 | C29: 6 | D29: =(Datos_vigas!$B$10*(VLOOKUP($A$26,Datos_vigas!$A$14:$E$15,2,0)*AF29+Datos_vigas!$B$7*J29*L29/10000+Datos_vigas!$B$16*AG29)+Datos_vigas!$B$11*VLOOKUP($A$26,Datos_vigas!$A$14:$E$15,3,0)*AF29) -> 2015.968 | F29: =VLOOKUP(Y29,Datos_vigas!$A$19:$E$23,4,0)*D29*C29+IF(OR(AD29="",AE29=""),0,AD29*MAX(AE29,C29-AE29)/C29) -> 6955.0896 | G29: =F29 -> 6955.0896 | H29: =VLOOKUP(Y29,Datos_vigas!$A$19:$E$23,2,0)*D29*C29^2+0.75*1000*IF(OR(AD29="",AE29=""),0,AD29*AE29*(C29-AE29)/C29/1000) -> 5184.0214 | I29: =IF(VLOOKUP(Y29,Datos_vigas!$A$19:$E$23,3,0)=0,"---",VLOOKUP(Y29,Datos_vigas!$A$19:$E$23,3,0)*D29*C29^2+0.5*1000*IF(OR(AD29="",AE29=""),0,AD29*AE29*(C29-AE29)/C29/1000)) -> 7257.4848 | J29: 15 | K29: =L29-AH29 -> 67 | L29: 70 | M29: =IF(NOT(ISNUMBER(H29)),"---",IF(H29<=0,"---",IF(H29*100/(Datos_vigas!$B$8*AB29*K29^2*Datos_vigas!$B$5)>=0.5,"REVISAR",MAX((1-SQRT(1-2*H29*100/(Datos_vigas!$B$8*AB29*K29^2*Datos_vigas!$B$5)))*AB29*K29*Datos_vigas!$B$5/Datos_vigas!$B$6,0.0033*J29*K29)))) -> 3.3165 | N29: 3 | O29: 12 | P29: =IF(NOT(ISNUMBER(I29)),"---",IF(I29<=0,"---",IF(I29*100/(Datos_vigas!$B$8*AC29*K29^2*Datos_vigas!$B$5)>=0.5,"REVISAR",MAX((1-SQRT(1-2*I29*100/(Datos_vigas!$B$8*AC29*K29^2*Datos_vigas!$B$5)))*AC29*K29*Datos_vigas!$B$5/Datos_vigas!$B$6,0.0033*J29*K29)))) -> 3.3165 | Q29: 3 | R29: 12 | S29: =F29/(J29*0.85*K29) -> 8.1417496 | T29: =G29/(J29*0.85*K29) -> 8.1417496 | U29: 6 | V29: 30 | W29: =IF(OR(M29="REVISAR",P29="REVISAR"),"SECCION INSUF.",IF(NOT(AND(M29<>"REVISAR",P29<>"REVISAR",IF(ISNUMBER(M29),N29*PI()*(O29/10)^2/4>=M29,TRUE()),IF(ISNUMBER(P29),Q29*PI()*(R29/10)^2/4>=P29,TRUE()),IF(ISNUMBER(M29),M29<=0.0163*AB29*K29,TRUE()),IF(ISNUMBER(P29),P29<=0.0163*AC29*K29,TRUE()))),"NO VERIFICA FLEX.",IF(NOT(F29<=Datos_vigas!$B$9*(0.53*SQRT(Datos_vigas!$B$5)*J29*K29+2*PI()*(U29/10)^2/4*Datos_vigas!$B$6*K29/V29)),"NO VERIF. CORTE",IF(NOT(L29>=C29*100/VLOOKUP(Y29,Datos_vigas!$A$19:$E$23,5,0)),"VERIFICAR FLECHA","VERIFICA")))) -> VERIFICA | Y29: Continua | Z29: Invertida | AA29: 12 | AB29: =IF(Z29="Colgante",MIN(C29*100/4,J29+16*AA29),J29) -> 15 | AC29: =IF(Z29="Invertida",MIN(C29*100/4,J29+16*AA29),J29) -> 150 | AF29: 1.699 | AG29: 1 | AH29: 3
B30: VI 15a | C30: 4.03 | D30: =(Datos_vigas!$B$10*(VLOOKUP($A$26,Datos_vigas!$A$14:$E$15,2,0)*AF30+Datos_vigas!$B$7*J30*L30/10000+Datos_vigas!$B$16*AG30)+Datos_vigas!$B$11*VLOOKUP($A$26,Datos_vigas!$A$14:$E$15,3,0)*AF30) -> 602.4 | F30: =VLOOKUP(Y30,Datos_vigas!$A$19:$E$23,4,0)*D30*C30+IF(OR(AD30="",AE30=""),0,AD30*MAX(AE30,C30-AE30)/C30) -> 1395.9114 | G30: =F30 -> 1395.9114 | H30: =VLOOKUP(Y30,Datos_vigas!$A$19:$E$23,2,0)*D30*C30^2+0.75*1000*IF(OR(AD30="",AE30=""),0,AD30*AE30*(C30-AE30)/C30/1000) -> 698.8367 | I30: =IF(VLOOKUP(Y30,Datos_vigas!$A$19:$E$23,3,0)=0,"---",VLOOKUP(Y30,Datos_vigas!$A$19:$E$23,3,0)*D30*C30^2+0.5*1000*IF(OR(AD30="",AE30=""),0,AD30*AE30*(C30-AE30)/C30/1000)) -> 978.35182 | J30: 15 | K30: =L30-AH30 -> 67 | L30: 70 | M30: =IF(NOT(ISNUMBER(H30)),"---",IF(H30<=0,"---",IF(H30*100/(Datos_vigas!$B$8*AB30*K30^2*Datos_vigas!$B$5)>=0.5,"REVISAR",MAX((1-SQRT(1-2*H30*100/(Datos_vigas!$B$8*AB30*K30^2*Datos_vigas!$B$5)))*AB30*K30*Datos_vigas!$B$5/Datos_vigas!$B$6,0.0033*J30*K30)))) -> 3.3165 | N30: 3 | O30: 12 | P30: =IF(NOT(ISNUMBER(I30)),"---",IF(I30<=0,"---",IF(I30*100/(Datos_vigas!$B$8*AC30*K30^2*Datos_vigas!$B$5)>=0.5,"REVISAR",MAX((1-SQRT(1-2*I30*100/(Datos_vigas!$B$8*AC30*K30^2*Datos_vigas!$B$5)))*AC30*K30*Datos_vigas!$B$5/Datos_vigas!$B$6,0.0033*J30*K30)))) -> 3.3165 | Q30: 3 | R30: 12 | S30: =F30/(J30*0.85*K30) -> 1.6340783 | T30: =G30/(J30*0.85*K30) -> 1.6340783 | U30: 6 | V30: 30 | W30: =IF(OR(M30="REVISAR",P30="REVISAR"),"SECCION INSUF.",IF(NOT(AND(M30<>"REVISAR",P30<>"REVISAR",IF(ISNUMBER(M30),N30*PI()*(O30/10)^2/4>=M30,TRUE()),IF(ISNUMBER(P30),Q30*PI()*(R30/10)^2/4>=P30,TRUE()),IF(ISNUMBER(M30),M30<=0.0163*AB30*K30,TRUE()),IF(ISNUMBER(P30),P30<=0.0163*AC30*K30,TRUE()))),"NO VERIFICA FLEX.",IF(NOT(F30<=Datos_vigas!$B$9*(0.53*SQRT(Datos_vigas!$B$5)*J30*K30+2*PI()*(U30/10)^2/4*Datos_vigas!$B$6*K30/V30)),"NO VERIF. CORTE",IF(NOT(L30>=C30*100/VLOOKUP(Y30,Datos_vigas!$A$19:$E$23,5,0)),"VERIFICAR FLECHA","VERIFICA")))) -> VERIFICA | X30: Viga de borde: recibe la reaccion de la losa excentrica y queda sometida a TORSION, no verificada en esta planilla. | Y30: Continua | Z30: Invertida | AA30: 12 | AB30: =IF(Z30="Colgante",MIN(C30*100/4,J30+16*AA30),J30) -> 15 | AC30: =IF(Z30="Invertida",MIN(C30*100/4,J30+16*AA30),J30) -> 100.75 | AF30: 0 | AG30: 1 | AH30: 3
B31: VI 15b | C31: 4.85 | D31: =(Datos_vigas!$B$10*(VLOOKUP($A$26,Datos_vigas!$A$14:$E$15,2,0)*AF31+Datos_vigas!$B$7*J31*L31/10000+Datos_vigas!$B$16*AG31)+Datos_vigas!$B$11*VLOOKUP($A$26,Datos_vigas!$A$14:$E$15,3,0)*AF31) -> 2015.968 | F31: =VLOOKUP(Y31,Datos_vigas!$A$19:$E$23,4,0)*D31*C31+IF(OR(AD31="",AE31=""),0,AD31*MAX(AE31,C31-AE31)/C31) -> 5622.0308 | G31: =F31 -> 5622.0308 | H31: =VLOOKUP(Y31,Datos_vigas!$A$19:$E$23,2,0)*D31*C31^2+0.75*1000*IF(OR(AD31="",AE31=""),0,AD31*AE31*(C31-AE31)/C31/1000) -> 3387.254 | I31: =IF(VLOOKUP(Y31,Datos_vigas!$A$19:$E$23,3,0)=0,"---",VLOOKUP(Y31,Datos_vigas!$A$19:$E$23,3,0)*D31*C31^2+0.5*1000*IF(OR(AD31="",AE31=""),0,AD31*AE31*(C31-AE31)/C31/1000)) -> 4742.0607 | J31: 15 | K31: =L31-AH31 -> 67 | L31: 70 | M31: =IF(NOT(ISNUMBER(H31)),"---",IF(H31<=0,"---",IF(H31*100/(Datos_vigas!$B$8*AB31*K31^2*Datos_vigas!$B$5)>=0.5,"REVISAR",MAX((1-SQRT(1-2*H31*100/(Datos_vigas!$B$8*AB31*K31^2*Datos_vigas!$B$5)))*AB31*K31*Datos_vigas!$B$5/Datos_vigas!$B$6,0.0033*J31*K31)))) -> 3.3165 | N31: 3 | O31: 12 | P31: =IF(NOT(ISNUMBER(I31)),"---",IF(I31<=0,"---",IF(I31*100/(Datos_vigas!$B$8*AC31*K31^2*Datos_vigas!$B$5)>=0.5,"REVISAR",MAX((1-SQRT(1-2*I31*100/(Datos_vigas!$B$8*AC31*K31^2*Datos_vigas!$B$5)))*AC31*K31*Datos_vigas!$B$5/Datos_vigas!$B$6,0.0033*J31*K31)))) -> 3.3165 | Q31: 3 | R31: 12 | S31: =F31/(J31*0.85*K31) -> 6.5812476 | T31: =G31/(J31*0.85*K31) -> 6.5812476 | U31: 6 | V31: 30 | W31: =IF(OR(M31="REVISAR",P31="REVISAR"),"SECCION INSUF.",IF(NOT(AND(M31<>"REVISAR",P31<>"REVISAR",IF(ISNUMBER(M31),N31*PI()*(O31/10)^2/4>=M31,TRUE()),IF(ISNUMBER(P31),Q31*PI()*(R31/10)^2/4>=P31,TRUE()),IF(ISNUMBER(M31),M31<=0.0163*AB31*K31,TRUE()),IF(ISNUMBER(P31),P31<=0.0163*AC31*K31,TRUE()))),"NO VERIFICA FLEX.",IF(NOT(F31<=Datos_vigas!$B$9*(0.53*SQRT(Datos_vigas!$B$5)*J31*K31+2*PI()*(U31/10)^2/4*Datos_vigas!$B$6*K31/V31)),"NO VERIF. CORTE",IF(NOT(L31>=C31*100/VLOOKUP(Y31,Datos_vigas!$A$19:$E$23,5,0)),"VERIFICAR FLECHA","VERIFICA")))) -> VERIFICA | X31: Viga de borde: recibe la reaccion de la losa excentrica y queda sometida a TORSION, no verificada en esta planilla. | Y31: Continua | Z31: Invertida | AA31: 12 | AB31: =IF(Z31="Colgante",MIN(C31*100/4,J31+16*AA31),J31) -> 15 | AC31: =IF(Z31="Invertida",MIN(C31*100/4,J31+16*AA31),J31) -> 121.25 | AF31: 1.699 | AG31: 1 | AH31: 3
B32: VI 16a | C32: 3.58 | D32: =(Datos_vigas!$B$10*(VLOOKUP($A$26,Datos_vigas!$A$14:$E$15,2,0)*AF32+Datos_vigas!$B$7*J32*L32/10000+Datos_vigas!$B$16*AG32)+Datos_vigas!$B$11*VLOOKUP($A$26,Datos_vigas!$A$14:$E$15,3,0)*AF32) -> 2015.968 | F32: =VLOOKUP(Y32,Datos_vigas!$A$19:$E$23,4,0)*D32*C32+IF(OR(AD32="",AE32=""),0,AD32*MAX(AE32,C32-AE32)/C32) -> 4149.8701 | G32: =F32 -> 4149.8701 | H32: =VLOOKUP(Y32,Datos_vigas!$A$19:$E$23,2,0)*D32*C32^2+0.75*1000*IF(OR(AD32="",AE32=""),0,AD32*AE32*(C32-AE32)/C32/1000) -> 1845.5692 | I32: =IF(VLOOKUP(Y32,Datos_vigas!$A$19:$E$23,3,0)=0,"---",VLOOKUP(Y32,Datos_vigas!$A$19:$E$23,3,0)*D32*C32^2+0.5*1000*IF(OR(AD32="",AE32=""),0,AD32*AE32*(C32-AE32)/C32/1000)) -> 2583.7452 | J32: 15 | K32: =L32-AH32 -> 67 | L32: 70 | M32: =IF(NOT(ISNUMBER(H32)),"---",IF(H32<=0,"---",IF(H32*100/(Datos_vigas!$B$8*AB32*K32^2*Datos_vigas!$B$5)>=0.5,"REVISAR",MAX((1-SQRT(1-2*H32*100/(Datos_vigas!$B$8*AB32*K32^2*Datos_vigas!$B$5)))*AB32*K32*Datos_vigas!$B$5/Datos_vigas!$B$6,0.0033*J32*K32)))) -> 3.3165 | N32: 3 | O32: 12 | P32: =IF(NOT(ISNUMBER(I32)),"---",IF(I32<=0,"---",IF(I32*100/(Datos_vigas!$B$8*AC32*K32^2*Datos_vigas!$B$5)>=0.5,"REVISAR",MAX((1-SQRT(1-2*I32*100/(Datos_vigas!$B$8*AC32*K32^2*Datos_vigas!$B$5)))*AC32*K32*Datos_vigas!$B$5/Datos_vigas!$B$6,0.0033*J32*K32)))) -> 3.3165 | Q32: 3 | R32: 12 | S32: =F32/(J32*0.85*K32) -> 4.8579106 | T32: =G32/(J32*0.85*K32) -> 4.8579106 | U32: 6 | V32: 30 | W32: =IF(OR(M32="REVISAR",P32="REVISAR"),"SECCION INSUF.",IF(NOT(AND(M32<>"REVISAR",P32<>"REVISAR",IF(ISNUMBER(M32),N32*PI()*(O32/10)^2/4>=M32,TRUE()),IF(ISNUMBER(P32),Q32*PI()*(R32/10)^2/4>=P32,TRUE()),IF(ISNUMBER(M32),M32<=0.0163*AB32*K32,TRUE()),IF(ISNUMBER(P32),P32<=0.0163*AC32*K32,TRUE()))),"NO VERIFICA FLEX.",IF(NOT(F32<=Datos_vigas!$B$9*(0.53*SQRT(Datos_vigas!$B$5)*J32*K32+2*PI()*(U32/10)^2/4*Datos_vigas!$B$6*K32/V32)),"NO VERIF. CORTE",IF(NOT(L32>=C32*100/VLOOKUP(Y32,Datos_vigas!$A$19:$E$23,5,0)),"VERIFICAR FLECHA","VERIFICA")))) -> VERIFICA | Y32: Continua | Z32: Invertida | AA32: 12 | AB32: =IF(Z32="Colgante",MIN(C32*100/4,J32+16*AA32),J32) -> 15 | AC32: =IF(Z32="Invertida",MIN(C32*100/4,J32+16*AA32),J32) -> 89.5 | AF32: 1.699 | AG32: 1 | AH32: 3
B33: VI 16b | C33: 1.12 | D33: =(Datos_vigas!$B$10*(VLOOKUP($A$26,Datos_vigas!$A$14:$E$15,2,0)*AF33+Datos_vigas!$B$7*J33*L33/10000+Datos_vigas!$B$16*AG33)+Datos_vigas!$B$11*VLOOKUP($A$26,Datos_vigas!$A$14:$E$15,3,0)*AF33) -> 2015.968 | F33: =VLOOKUP(Y33,Datos_vigas!$A$19:$E$23,4,0)*D33*C33+IF(OR(AD33="",AE33=""),0,AD33*MAX(AE33,C33-AE33)/C33) -> 1298.2834 | G33: =F33 -> 1298.2834 | H33: =VLOOKUP(Y33,Datos_vigas!$A$19:$E$23,2,0)*D33*C33^2+0.75*1000*IF(OR(AD33="",AE33=""),0,AD33*AE33*(C33-AE33)/C33/1000) -> 180.63435 | I33: =IF(VLOOKUP(Y33,Datos_vigas!$A$19:$E$23,3,0)=0,"---",VLOOKUP(Y33,Datos_vigas!$A$19:$E$23,3,0)*D33*C33^2+0.5*1000*IF(OR(AD33="",AE33=""),0,AD33*AE33*(C33-AE33)/C33/1000)) -> 252.88303 | J33: 15 | K33: =L33-AH33 -> 67 | L33: 70 | M33: =IF(NOT(ISNUMBER(H33)),"---",IF(H33<=0,"---",IF(H33*100/(Datos_vigas!$B$8*AB33*K33^2*Datos_vigas!$B$5)>=0.5,"REVISAR",MAX((1-SQRT(1-2*H33*100/(Datos_vigas!$B$8*AB33*K33^2*Datos_vigas!$B$5)))*AB33*K33*Datos_vigas!$B$5/Datos_vigas!$B$6,0.0033*J33*K33)))) -> 3.3165 | N33: 3 | O33: 12 | P33: =IF(NOT(ISNUMBER(I33)),"---",IF(I33<=0,"---",IF(I33*100/(Datos_vigas!$B$8*AC33*K33^2*Datos_vigas!$B$5)>=0.5,"REVISAR",MAX((1-SQRT(1-2*I33*100/(Datos_vigas!$B$8*AC33*K33^2*Datos_vigas!$B$5)))*AC33*K33*Datos_vigas!$B$5/Datos_vigas!$B$6,0.0033*J33*K33)))) -> 3.3165 | Q33: 3 | R33: 12 | S33: =F33/(J33*0.85*K33) -> 1.5197933 | T33: =G33/(J33*0.85*K33) -> 1.5197933 | U33: 6 | V33: 30 | W33: =IF(OR(M33="REVISAR",P33="REVISAR"),"SECCION INSUF.",IF(NOT(AND(M33<>"REVISAR",P33<>"REVISAR",IF(ISNUMBER(M33),N33*PI()*(O33/10)^2/4>=M33,TRUE()),IF(ISNUMBER(P33),Q33*PI()*(R33/10)^2/4>=P33,TRUE()),IF(ISNUMBER(M33),M33<=0.0163*AB33*K33,TRUE()),IF(ISNUMBER(P33),P33<=0.0163*AC33*K33,TRUE()))),"NO VERIFICA FLEX.",IF(NOT(F33<=Datos_vigas!$B$9*(0.53*SQRT(Datos_vigas!$B$5)*J33*K33+2*PI()*(U33/10)^2/4*Datos_vigas!$B$6*K33/V33)),"NO VERIF. CORTE",IF(NOT(L33>=C33*100/VLOOKUP(Y33,Datos_vigas!$A$19:$E$23,5,0)),"VERIFICAR FLECHA","VERIFICA")))) -> VERIFICA | Y33: Continua | Z33: Invertida | AA33: 12 | AB33: =IF(Z33="Colgante",MIN(C33*100/4,J33+16*AA33),J33) -> 15 | AC33: =IF(Z33="Invertida",MIN(C33*100/4,J33+16*AA33),J33) -> 28 | AF33: 1.699 | AG33: 1 | AH33: 3
B34: VI 17 | C34: 4.35 | D34: =(Datos_vigas!$B$10*(VLOOKUP($A$26,Datos_vigas!$A$14:$E$15,2,0)*AF34+Datos_vigas!$B$7*J34*L34/10000+Datos_vigas!$B$16*AG34)+Datos_vigas!$B$11*VLOOKUP($A$26,Datos_vigas!$A$14:$E$15,3,0)*AF34) -> 602.4 | F34: =VLOOKUP(Y34,Datos_vigas!$A$19:$E$23,4,0)*D34*C34+IF(OR(AD34="",AE34=""),0,AD34*MAX(AE34,C34-AE34)/C34) -> 1310.22 | G34: =F34 -> 1310.22 | H34: =VLOOKUP(Y34,Datos_vigas!$A$19:$E$23,2,0)*D34*C34^2+0.75*1000*IF(OR(AD34="",AE34=""),0,AD34*AE34*(C34-AE34)/C34/1000) -> 1424.8643 | I34: =IF(VLOOKUP(Y34,Datos_vigas!$A$19:$E$23,3,0)=0,"---",VLOOKUP(Y34,Datos_vigas!$A$19:$E$23,3,0)*D34*C34^2+0.5*1000*IF(OR(AD34="",AE34=""),0,AD34*AE34*(C34-AE34)/C34/1000)) -> --- | J34: 15 | K34: =L34-AH34 -> 67 | L34: 70 | M34: =IF(NOT(ISNUMBER(H34)),"---",IF(H34<=0,"---",IF(H34*100/(Datos_vigas!$B$8*AB34*K34^2*Datos_vigas!$B$5)>=0.5,"REVISAR",MAX((1-SQRT(1-2*H34*100/(Datos_vigas!$B$8*AB34*K34^2*Datos_vigas!$B$5)))*AB34*K34*Datos_vigas!$B$5/Datos_vigas!$B$6,0.0033*J34*K34)))) -> 3.3165 | N34: 3 | O34: 12 | P34: =IF(NOT(ISNUMBER(I34)),"---",IF(I34<=0,"---",IF(I34*100/(Datos_vigas!$B$8*AC34*K34^2*Datos_vigas!$B$5)>=0.5,"REVISAR",MAX((1-SQRT(1-2*I34*100/(Datos_vigas!$B$8*AC34*K34^2*Datos_vigas!$B$5)))*AC34*K34*Datos_vigas!$B$5/Datos_vigas!$B$6,0.0033*J34*K34)))) -> --- | Q34: --- | R34: --- | S34: =F34/(J34*0.85*K34) -> 1.5337665 | T34: =G34/(J34*0.85*K34) -> 1.5337665 | U34: 6 | V34: 30 | W34: =IF(OR(M34="REVISAR",P34="REVISAR"),"SECCION INSUF.",IF(NOT(AND(M34<>"REVISAR",P34<>"REVISAR",IF(ISNUMBER(M34),N34*PI()*(O34/10)^2/4>=M34,TRUE()),IF(ISNUMBER(P34),Q34*PI()*(R34/10)^2/4>=P34,TRUE()),IF(ISNUMBER(M34),M34<=0.0163*AB34*K34,TRUE()),IF(ISNUMBER(P34),P34<=0.0163*AC34*K34,TRUE()))),"NO VERIFICA FLEX.",IF(NOT(F34<=Datos_vigas!$B$9*(0.53*SQRT(Datos_vigas!$B$5)*J34*K34+2*PI()*(U34/10)^2/4*Datos_vigas!$B$6*K34/V34)),"NO VERIF. CORTE",IF(NOT(L34>=C34*100/VLOOKUP(Y34,Datos_vigas!$A$19:$E$23,5,0)),"VERIFICAR FLECHA","VERIFICA")))) -> VERIFICA | Y34: Simplemente apoyada | Z34: Invertida | AA34: 12 | AB34: =IF(Z34="Colgante",MIN(C34*100/4,J34+16*AA34),J34) -> 15 | AC34: =IF(Z34="Invertida",MIN(C34*100/4,J34+16*AA34),J34) -> 108.75 | AF34: 0 | AG34: 1 | AH34: 3

Sheet Planilla losas
A1: LOSAS DE H°A° H-21 ACERO 42/50
A2: NIVEL | B2: POSICION | C2: LUZ (m) | D2: GRADO DE EMPOTRAMIENTO | E2: CARGAS (kg/m) | G2: DIMENSIONES | I2: MOMENTO TRAMO (kgm) | J2: ARMADURA PRINCIPAL | M2: ARMADURA REPARTICION | P2: REACCIONES (kg) | R2: OBSERVACIONES | S2: DATOS AUXILIARES
E3: p | F3: diagrama | G3: h | H3: d | J3: cm2 | K3: o | L3: separ | M3: cm2 | N3: o | O3: separ | P3: Rx | Q3: Ry | S3: luz transv. | T3: k carga
A4: S/PB | B4: L01 | C4: 3.65 | D4: 1/8 | E4: =(Datos_losas!$B$9*H4/100+VLOOKUP($A$4,Datos_losas!$A$16:$C$17,2,0)+VLOOKUP($A$4,Datos_losas!$A$16:$C$17,3,0))*T4 -> 706 | G4: =H4-Datos_losas!$B$10 -> 9.5 | H4: 11 | I4: =IF(C4="","",VLOOKUP(D4,Datos_losas!$A$21:$D$25,2,0)*E4*C4^2) -> 1175.7106 | J4: =IF(I4="","",MAX(I4*100/(Datos_losas!$B$7*Datos_losas!$B$8*G4),Datos_losas!$B$13)) -> 5.7295839 | K4: 12 | L4: =IF(J4="","",MIN(Datos_losas!$B$11,ROUND(100*PI()*(K4/10)^2/4/J4,0))) -> 20 | M4: =IF(J4="","",MAX(Datos_losas!$B$12*J4,Datos_losas!$B$13)) -> 1.1459168 | N4: 6 | O4: =IF(M4="","",MIN(Datos_losas!$B$11,ROUND(100*PI()*(N4/10)^2/4/M4,0))) -> 20 | P4: =IF(C4="","",VLOOKUP(D4,Datos_losas!$A$21:$D$25,3,0)*E4*C4) -> 1288.45 | Q4: =IF(C4="","",IF(VLOOKUP(D4,Datos_losas!$A$21:$D$25,4,0)="Voladizo","---",P4)) -> 1288.45 | T4: =IF(S4="",1,S4^4/(C4^4+S4^4)) -> 1
B5: L02 | C5: 0.8 | D5: 1/2 | E5: =(Datos_losas!$B$9*H5/100+VLOOKUP($A$4,Datos_losas!$A$16:$C$17,2,0)+VLOOKUP($A$4,Datos_losas!$A$16:$C$17,3,0))*T5 -> 658 | G5: =H5-Datos_losas!$B$10 -> 7.5 | H5: 9 | I5: =IF(C5="","",VLOOKUP(D5,Datos_losas!$A$21:$D$25,2,0)*E5*C5^2) -> 210.56 | J5: =IF(I5="","",MAX(I5*100/(Datos_losas!$B$7*Datos_losas!$B$8*G5),Datos_losas!$B$13)) -> 1.2997531 | K5: 12 | L5: =IF(J5="","",MIN(Datos_losas!$B$11,ROUND(100*PI()*(K5/10)^2/4/J5,0))) -> 20 | M5: =IF(J5="","",MAX(Datos_losas!$B$12*J5,Datos_losas!$B$13)) -> 0.3 | N5: 6 | O5: =IF(M5="","",MIN(Datos_losas!$B$11,ROUND(100*PI()*(N5/10)^2/4/M5,0))) -> 20 | P5: =IF(C5="","",VLOOKUP(D5,Datos_losas!$A$21:$D$25,3,0)*E5*C5) -> 526.4 | Q5: =IF(C5="","",IF(VLOOKUP(D5,Datos_losas!$A$21:$D$25,4,0)="Voladizo","---",P5)) -> --- | R5: Voladizo: un solo apoyo. | T5: =IF(S5="",1,S5^4/(C5^4+S5^4)) -> 1
B6: L03 | C6: 4.15 | D6: 1/8 | E6: =(Datos_losas!$B$9*H6/100+VLOOKUP($A$4,Datos_losas!$A$16:$C$17,2,0)+VLOOKUP($A$4,Datos_losas!$A$16:$C$17,3,0))*T6 -> 754 | G6: =H6-Datos_losas!$B$10 -> 11.5 | H6: 13 | I6: =IF(C6="","",VLOOKUP(D6,Datos_losas!$A$21:$D$25,2,0)*E6*C6^2) -> 1623.2206 | J6: =IF(I6="","",MAX(I6*100/(Datos_losas!$B$7*Datos_losas!$B$8*G6),Datos_losas!$B$13)) -> 6.5347046 | K6: 12 | L6: =IF(J6="","",MIN(Datos_losas!$B$11,ROUND(100*PI()*(K6/10)^2/4/J6,0))) -> 17 | M6: =IF(J6="","",MAX(Datos_losas!$B$12*J6,Datos_losas!$B$13)) -> 1.3069409 | N6: 6 | O6: =IF(M6="","",MIN(Datos_losas!$B$11,ROUND(100*PI()*(N6/10)^2/4/M6,0))) -> 20 | P6: =IF(C6="","",VLOOKUP(D6,Datos_losas!$A$21:$D$25,3,0)*E6*C6) -> 1564.55 | Q6: =IF(C6="","",IF(VLOOKUP(D6,Datos_losas!$A$21:$D$25,4,0)="Voladizo","---",P6)) -> 1564.55 | T6: =IF(S6="",1,S6^4/(C6^4+S6^4)) -> 1
B7: L04 | C7: 3.73 | D7: 1/8 | E7: =(Datos_losas!$B$9*H7/100+VLOOKUP($A$4,Datos_losas!$A$16:$C$17,2,0)+VLOOKUP($A$4,Datos_losas!$A$16:$C$17,3,0))*T7 -> 706 | G7: =H7-Datos_losas!$B$10 -> 9.5 | H7: 11 | I7: =IF(C7="","",VLOOKUP(D7,Datos_losas!$A$21:$D$25,2,0)*E7*C7^2) -> 1227.8134 | J7: =IF(I7="","",MAX(I7*100/(Datos_losas!$B$7*Datos_losas!$B$8*G7),Datos_losas!$B$13)) -> 5.9834962 | K7: 12 | L7: =IF(J7="","",MIN(Datos_losas!$B$11,ROUND(100*PI()*(K7/10)^2/4/J7,0))) -> 19 | M7: =IF(J7="","",MAX(Datos_losas!$B$12*J7,Datos_losas!$B$13)) -> 1.1966992 | N7: 6 | O7: =IF(M7="","",MIN(Datos_losas!$B$11,ROUND(100*PI()*(N7/10)^2/4/M7,0))) -> 20 | P7: =IF(C7="","",VLOOKUP(D7,Datos_losas!$A$21:$D$25,3,0)*E7*C7) -> 1316.69 | Q7: =IF(C7="","",IF(VLOOKUP(D7,Datos_losas!$A$21:$D$25,4,0)="Voladizo","---",P7)) -> 1316.69 | T7: =IF(S7="",1,S7^4/(C7^4+S7^4)) -> 1
B8: L05 | C8: 3.73 | D8: 1/8 | E8: =(Datos_losas!$B$9*H8/100+VLOOKUP($A$4,Datos_losas!$A$16:$C$17,2,0)+VLOOKUP($A$4,Datos_losas!$A$16:$C$17,3,0))*T8 -> 706 | G8: =H8-Datos_losas!$B$10 -> 9.5 | H8: 11 | I8: =IF(C8="","",VLOOKUP(D8,Datos_losas!$A$21:$D$25,2,0)*E8*C8^2) -> 1227.8134 | J8: =IF(I8="","",MAX(I8*100/(Datos_losas!$B$7*Datos_losas!$B$8*G8),Datos_losas!$B$13)) -> 5.9834962 | K8: 12 | L8: =IF(J8="","",MIN(Datos_losas!$B$11,ROUND(100*PI()*(K8/10)^2/4/J8,0))) -> 19 | M8: =IF(J8="","",MAX(Datos_losas!$B$12*J8,Datos_losas!$B$13)) -> 1.1966992 | N8: 6 | O8: =IF(M8="","",MIN(Datos_losas!$B$11,ROUND(100*PI()*(N8/10)^2/4/M8,0))) -> 20 | P8: =IF(C8="","",VLOOKUP(D8,Datos_losas!$A$21:$D$25,3,0)*E8*C8) -> 1316.69 | Q8: =IF(C8="","",IF(VLOOKUP(D8,Datos_losas!$A$21:$D$25,4,0)="Voladizo","---",P8)) -> 1316.69 | T8: =IF(S8="",1,S8^4/(C8^4+S8^4)) -> 1
B9: L06 | C9: 2.15 | D9: 1/8 | E9: =(Datos_losas!$B$9*H9/100+VLOOKUP($A$4,Datos_losas!$A$16:$C$17,2,0)+VLOOKUP($A$4,Datos_losas!$A$16:$C$17,3,0))*T9 -> 634 | G9: =H9-Datos_losas!$B$10 -> 6.5 | H9: 8 | I9: =IF(C9="","",VLOOKUP(D9,Datos_losas!$A$21:$D$25,2,0)*E9*C9^2) -> 366.33312 | J9: =IF(I9="","",MAX(I9*100/(Datos_losas!$B$7*Datos_losas!$B$8*G9),Datos_losas!$B$13)) -> 2.6092103 | K9: 12 | L9: =IF(J9="","",MIN(Datos_losas!$B$11,ROUND(100*PI()*(K9/10)^2/4/J9,0))) -> 20 | M9: =IF(J9="","",MAX(Datos_losas!$B$12*J9,Datos_losas!$B$13)) -> 0.52184206 | N9: 6 | O9: =IF(M9="","",MIN(Datos_losas!$B$11,ROUND(100*PI()*(N9/10)^2/4/M9,0))) -> 20 | P9: =IF(C9="","",VLOOKUP(D9,Datos_losas!$A$21:$D$25,3,0)*E9*C9) -> 681.55 | Q9: =IF(C9="","",IF(VLOOKUP(D9,Datos_losas!$A$21:$D$25,4,0)="Voladizo","---",P9)) -> 681.55 | T9: =IF(S9="",1,S9^4/(C9^4+S9^4)) -> 1
B10: L07 (x) | C10: 4.85 | D10: 1/8 | E10: =(Datos_losas!$B$9*H10/100+VLOOKUP($A$4,Datos_losas!$A$16:$C$17,2,0)+VLOOKUP($A$4,Datos_losas!$A$16:$C$17,3,0))*T10 -> 467.16425 | G10: =H10-Datos_losas!$B$10 -> 10.5 | H10: 12 | I10: =IF(C10="","",VLOOKUP(D10,Datos_losas!$A$21:$D$25,2,0)*E10*C10^2) -> 1373.6089 | J10: =IF(I10="","",MAX(I10*100/(Datos_losas!$B$7*Datos_losas!$B$8*G10),Datos_losas!$B$13)) -> 6.0564765 | K10: 12 | L10: =IF(J10="","",MIN(Datos_losas!$B$11,ROUND(100*PI()*(K10/10)^2/4/J10,0))) -> 19 | M10: =IF(J10="","",MAX(Datos_losas!$B$12*J10,Datos_losas!$B$13)) -> 1.2112953 | N10: 6 | O10: =IF(M10="","",MIN(Datos_losas!$B$11,ROUND(100*PI()*(N10/10)^2/4/M10,0))) -> 20 | P10: =IF(C10="","",VLOOKUP(D10,Datos_losas!$A$21:$D$25,3,0)*E10*C10) -> 1132.8733 | Q10: =IF(C10="","",IF(VLOOKUP(D10,Datos_losas!$A$21:$D$25,4,0)="Voladizo","---",P10)) -> 1132.8733 | R10: Losa cruzada 4,85 x 5,60 (ly/lx = 1,15). Direccion corta: toma el 64% de la carga por reparto de Marcus. | S10: 5.6 | T10: =IF(S10="",1,S10^4/(C10^4+S10^4)) -> 0.63995102
B11: L07 (y) | C11: 5.6 | D11: 1/8 | E11: =(Datos_losas!$B$9*H11/100+VLOOKUP($A$4,Datos_losas!$A$16:$C$17,2,0)+VLOOKUP($A$4,Datos_losas!$A$16:$C$17,3,0))*T11 -> 262.83575 | G11: =H11-Datos_losas!$B$10 -> 10.5 | H11: 12 | I11: =IF(C11="","",VLOOKUP(D11,Datos_losas!$A$21:$D$25,2,0)*E11*C11^2) -> 1030.3162 | J11: =IF(I11="","",MAX(I11*100/(Datos_losas!$B$7*Datos_losas!$B$8*G11),Datos_losas!$B$13)) -> 4.5428402 | K11: 12 | L11: =IF(J11="","",MIN(Datos_losas!$B$11,ROUND(100*PI()*(K11/10)^2/4/J11,0))) -> 20 | M11: =IF(J11="","",MAX(Datos_losas!$B$12*J11,Datos_losas!$B$13)) -> 0.90856804 | N11: 6 | O11: =IF(M11="","",MIN(Datos_losas!$B$11,ROUND(100*PI()*(N11/10)^2/4/M11,0))) -> 20 | P11: =IF(C11="","",VLOOKUP(D11,Datos_losas!$A$21:$D$25,3,0)*E11*C11) -> 735.94011 | Q11: =IF(C11="","",IF(VLOOKUP(D11,Datos_losas!$A$21:$D$25,4,0)="Voladizo","---",P11)) -> 735.94011 | R11: Misma losa, direccion larga: toma el 36% restante. La armadura va cruzada con la fila anterior. | S11: 4.85 | T11: =IF(S11="",1,S11^4/(C11^4+S11^4)) -> 0.36004898
B12: L08 | C12: 0.75 | D12: 1/2 | E12: =(Datos_losas!$B$9*H12/100+VLOOKUP($A$4,Datos_losas!$A$16:$C$17,2,0)+VLOOKUP($A$4,Datos_losas!$A$16:$C$17,3,0))*T12 -> 682 | G12: =H12-Datos_losas!$B$10 -> 8.5 | H12: 10 | I12: =IF(C12="","",VLOOKUP(D12,Datos_losas!$A$21:$D$25,2,0)*E12*C12^2) -> 191.8125 | J12: =IF(I12="","",MAX(I12*100/(Datos_losas!$B$7*Datos_losas!$B$8*G12),Datos_losas!$B$13)) -> 1.0447304 | K12: 12 | L12: =IF(J12="","",MIN(Datos_losas!$B$11,ROUND(100*PI()*(K12/10)^2/4/J12,0))) -> 20 | M12: =IF(J12="","",MAX(Datos_losas!$B$12*J12,Datos_losas!$B$13)) -> 0.3 | N12: 6 | O12: =IF(M12="","",MIN(Datos_losas!$B$11,ROUND(100*PI()*(N12/10)^2/4/M12,0))) -> 20 | P12: =IF(C12="","",VLOOKUP(D12,Datos_losas!$A$21:$D$25,3,0)*E12*C12) -> 511.5 | Q12: =IF(C12="","",IF(VLOOKUP(D12,Datos_losas!$A$21:$D$25,4,0)="Voladizo","---",P12)) -> --- | R12: Voladizo: un solo apoyo. | T12: =IF(S12="",1,S12^4/(C12^4+S12^4)) -> 1
A13: S/PA | B13: L09 | C13: 4.2 | D13: 1/8 | E13: =(Datos_losas!$B$9*H13/100+VLOOKUP($A$13,Datos_losas!$A$16:$C$17,2,0)+VLOOKUP($A$13,Datos_losas!$A$16:$C$17,3,0))*T13 -> 664 | G13: =H13-Datos_losas!$B$10 -> 11.5 | H13: 13 | I13: =IF(C13="","",VLOOKUP(D13,Datos_losas!$A$21:$D$25,2,0)*E13*C13^2) -> 1464.12 | J13: =IF(I13="","",MAX(I13*100/(Datos_losas!$B$7*Datos_losas!$B$8*G13),Datos_losas!$B$13)) -> 5.8942029 | K13: 12 | L13: =IF(J13="","",MIN(Datos_losas!$B$11,ROUND(100*PI()*(K13/10)^2/4/J13,0))) -> 19 | M13: =IF(J13="","",MAX(Datos_losas!$B$12*J13,Datos_losas!$B$13)) -> 1.1788406 | N13: 6 | O13: =IF(M13="","",MIN(Datos_losas!$B$11,ROUND(100*PI()*(N13/10)^2/4/M13,0))) -> 20 | P13: =IF(C13="","",VLOOKUP(D13,Datos_losas!$A$21:$D$25,3,0)*E13*C13) -> 1394.4 | Q13: =IF(C13="","",IF(VLOOKUP(D13,Datos_losas!$A$21:$D$25,4,0)="Voladizo","---",P13)) -> 1394.4 | T13: =IF(S13="",1,S13^4/(C13^4+S13^4)) -> 1
B14: L10 (x) | C14: 4.85 | D14: 1/8 | E14: =(Datos_losas!$B$9*H14/100+VLOOKUP($A$13,Datos_losas!$A$16:$C$17,2,0)+VLOOKUP($A$13,Datos_losas!$A$16:$C$17,3,0))*T14 -> 448.51371 | G14: =H14-Datos_losas!$B$10 -> 10.5 | H14: 12 | I14: =IF(C14="","",VLOOKUP(D14,Datos_losas!$A$21:$D$25,2,0)*E14*C14^2) -> 1318.7705 | J14: =IF(I14="","",MAX(I14*100/(Datos_losas!$B$7*Datos_losas!$B$8*G14),Datos_losas!$B$13)) -> 5.8146846 | K14: 12 | L14: =IF(J14="","",MIN(Datos_losas!$B$11,ROUND(100*PI()*(K14/10)^2/4/J14,0))) -> 19 | M14: =IF(J14="","",MAX(Datos_losas!$B$12*J14,Datos_losas!$B$13)) -> 1.1629369 | N14: 6 | O14: =IF(M14="","",MIN(Datos_losas!$B$11,ROUND(100*PI()*(N14/10)^2/4/M14,0))) -> 20 | P14: =IF(C14="","",VLOOKUP(D14,Datos_losas!$A$21:$D$25,3,0)*E14*C14) -> 1087.6458 | Q14: =IF(C14="","",IF(VLOOKUP(D14,Datos_losas!$A$21:$D$25,4,0)="Voladizo","---",P14)) -> 1087.6458 | R14: Losa cruzada 4,85 x 6,00 (ly/lx = 1,24). Direccion corta: toma el 70% de la carga por reparto de Marcus. | S14: 6 | T14: =IF(S14="",1,S14^4/(C14^4+S14^4)) -> 0.70080268
B15: L10 (y) | C15: 6 | D15: 1/8 | E15: =(Datos_losas!$B$9*H15/100+VLOOKUP($A$13,Datos_losas!$A$16:$C$17,2,0)+VLOOKUP($A$13,Datos_losas!$A$16:$C$17,3,0))*T15 -> 191.48629 | G15: =H15-Datos_losas!$B$10 -> 10.5 | H15: 12 | I15: =IF(C15="","",VLOOKUP(D15,Datos_losas!$A$21:$D$25,2,0)*E15*C15^2) -> 861.68829 | J15: =IF(I15="","",MAX(I15*100/(Datos_losas!$B$7*Datos_losas!$B$8*G15),Datos_losas!$B$13)) -> 3.7993311 | K15: 12 | L15: =IF(J15="","",MIN(Datos_losas!$B$11,ROUND(100*PI()*(K15/10)^2/4/J15,0))) -> 20 | M15: =IF(J15="","",MAX(Datos_losas!$B$12*J15,Datos_losas!$B$13)) -> 0.75986622 | N15: 6 | O15: =IF(M15="","",MIN(Datos_losas!$B$11,ROUND(100*PI()*(N15/10)^2/4/M15,0))) -> 20 | P15: =IF(C15="","",VLOOKUP(D15,Datos_losas!$A$21:$D$25,3,0)*E15*C15) -> 574.45886 | Q15: =IF(C15="","",IF(VLOOKUP(D15,Datos_losas!$A$21:$D$25,4,0)="Voladizo","---",P15)) -> 574.45886 | R15: Misma losa, direccion larga: toma el 30% restante. La armadura va cruzada con la fila anterior. | S15: 4.85 | T15: =IF(S15="",1,S15^4/(C15^4+S15^4)) -> 0.29919732

Sheet Planilla columnas
A1: COLUMNAS H°A° H-21 ACERO 42/50
A2: NIVEL | B2: POSICION | C2: ALTURA (m) | D2: CARGA (t) | E2: DIMENSIONES (cm) | H2: ARMADURA | K2: ESTRIBOS | M2: VERIFICACION | N2: OBSERVACIONES | O2: DATOS AUXILIARES
E3: A | F3: B | G3: area | H3: cm2 | I3: n | J3: o | K3: o | L3: SEPAR | O3: As prov | P3: fi Pn (t) | Q3: esbeltez | R3: carga estim.
A4: PA | B4: C6 | C4: 3.22 | D4: 12.71 | E4: 20 | F4: 20 | G4: =E4*F4 -> 400 | H4: =Datos_columnas!$B$8*G4 -> 3.2 | I4: 4 | J4: 12 | K4: 6 | L4: =FLOOR(MIN(12*J4/10,48*K4/10,MIN(E4,F4)),5) -> 10 | M4: =IF(D4="","FALTA CARGA",IF(O4<H4,"ARM. INSUFIC.",IF(D4>P4,"NO VERIFICA",IF(D4>0.85*P4,"AL LIMITE",IF(Q4>34,"VERIF. ESBELTEZ","VERIFICA"))))) -> VERIF. ESBELTEZ | N4: COL 07 del plano. Carga PROVISORIA por bajada automatica; es un piso, la real es mayor (ver Memoria, punto 5). | O4: =I4*PI()*(J4/10)^2/4 -> 4.5238934 | P4: =Datos_columnas!$B$7*0.8*(0.85*Datos_columnas!$B$4*(G4-O4)+Datos_columnas!$B$5*O4)/1000 -> 46.588275 | Q4: =100*C4/(0.3*MIN(E4,F4)) -> 53.666667 | R4: 12.71
B5: C7 | C5: 3.22 | D5: 22.55 | E5: 30 | F5: 15 | G5: =E5*F5 -> 450 | H5: =Datos_columnas!$B$8*G5 -> 3.6 | I5: 4 | J5: 12 | K5: 6 | L5: =FLOOR(MIN(12*J5/10,48*K5/10,MIN(E5,F5)),5) -> 10 | M5: =IF(D5="","FALTA CARGA",IF(O5<H5,"ARM. INSUFIC.",IF(D5>P5,"NO VERIFICA",IF(D5>0.85*P5,"AL LIMITE",IF(Q5>34,"VERIF. ESBELTEZ","VERIFICA"))))) -> VERIF. ESBELTEZ | N5: COL 06 del plano. Carga PROVISORIA por bajada automatica; es un piso, la real es mayor (ver Memoria, punto 5). | O5: =I5*PI()*(J5/10)^2/4 -> 4.5238934 | P5: =Datos_columnas!$B$7*0.8*(0.85*Datos_columnas!$B$4*(G5-O5)+Datos_columnas!$B$5*O5)/1000 -> 51.229275 | Q5: =100*C5/(0.3*MIN(E5,F5)) -> 71.555556 | R5: 22.55
B6: C8 | C6: 3.22 | D6: 15.12 | E6: 15 | F6: 30 | G6: =E6*F6 -> 450 | H6: =Datos_columnas!$B$8*G6 -> 3.6 | I6: 4 | J6: 12 | K6: 6 | L6: =FLOOR(MIN(12*J6/10,48*K6/10,MIN(E6,F6)),5) -> 10 | M6: =IF(D6="","FALTA CARGA",IF(O6<H6,"ARM. INSUFIC.",IF(D6>P6,"NO VERIFICA",IF(D6>0.85*P6,"AL LIMITE",IF(Q6>34,"VERIF. ESBELTEZ","VERIFICA"))))) -> VERIF. ESBELTEZ | N6: COL 05 del plano. Carga PROVISORIA por bajada automatica; es un piso, la real es mayor (ver Memoria, punto 5). | O6: =I6*PI()*(J6/10)^2/4 -> 4.5238934 | P6: =Datos_columnas!$B$7*0.8*(0.85*Datos_columnas!$B$4*(G6-O6)+Datos_columnas!$B$5*O6)/1000 -> 51.229275 | Q6: =100*C6/(0.3*MIN(E6,F6)) -> 71.555556 | R6: 15.12
B7: C9 | C7: 3.22 | D7: 20.35 | E7: 15 | F7: 30 | G7: =E7*F7 -> 450 | H7: =Datos_columnas!$B$8*G7 -> 3.6 | I7: 4 | J7: 12 | K7: 6 | L7: =FLOOR(MIN(12*J7/10,48*K7/10,MIN(E7,F7)),5) -> 10 | M7: =IF(D7="","FALTA CARGA",IF(O7<H7,"ARM. INSUFIC.",IF(D7>P7,"NO VERIFICA",IF(D7>0.85*P7,"AL LIMITE",IF(Q7>34,"VERIF. ESBELTEZ","VERIFICA"))))) -> VERIF. ESBELTEZ | N7: COL 05 del plano. Carga PROVISORIA por bajada automatica; es un piso, la real es mayor (ver Memoria, punto 5). | O7: =I7*PI()*(J7/10)^2/4 -> 4.5238934 | P7: =Datos_columnas!$B$7*0.8*(0.85*Datos_columnas!$B$4*(G7-O7)+Datos_columnas!$B$5*O7)/1000 -> 51.229275 | Q7: =100*C7/(0.3*MIN(E7,F7)) -> 71.555556 | R7: 20.35
A8: PB | B8: C1 | C8: 3.15 | D8: 2.49 | E8: 15 | F8: 30 | G8: =E8*F8 -> 450 | H8: =Datos_columnas!$B$8*G8 -> 3.6 | I8: 4 | J8: 12 | K8: 6 | L8: =FLOOR(MIN(12*J8/10,48*K8/10,MIN(E8,F8)),5) -> 10 | M8: =IF(D8="","FALTA CARGA",IF(O8<H8,"ARM. INSUFIC.",IF(D8>P8,"NO VERIFICA",IF(D8>0.85*P8,"AL LIMITE",IF(Q8>34,"VERIF. ESBELTEZ","VERIFICA"))))) -> VERIF. ESBELTEZ | N8: COL 02 del plano. Carga PROVISORIA por bajada automatica; es un piso, la real es mayor (ver Memoria, punto 5). | O8: =I8*PI()*(J8/10)^2/4 -> 4.5238934 | P8: =Datos_columnas!$B$7*0.8*(0.85*Datos_columnas!$B$4*(G8-O8)+Datos_columnas!$B$5*O8)/1000 -> 51.229275 | Q8: =100*C8/(0.3*MIN(E8,F8)) -> 70 | R8: 2.49
B9: C2 | C9: 3.15 | D9: 29.46 | E9: 15 | F9: 30 | G9: =E9*F9 -> 450 | H9: =Datos_columnas!$B$8*G9 -> 3.6 | I9: 4 | J9: 12 | K9: 6 | L9: =FLOOR(MIN(12*J9/10,48*K9/10,MIN(E9,F9)),5) -> 10 | M9: =IF(D9="","FALTA CARGA",IF(O9<H9,"ARM. INSUFIC.",IF(D9>P9,"NO VERIFICA",IF(D9>0.85*P9,"AL LIMITE",IF(Q9>34,"VERIF. ESBELTEZ","VERIFICA"))))) -> VERIF. ESBELTEZ | N9: COL 02 del plano. Carga PROVISORIA por bajada automatica; es un piso, la real es mayor (ver Memoria, punto 5). | O9: =I9*PI()*(J9/10)^2/4 -> 4.5238934 | P9: =Datos_columnas!$B$7*0.8*(0.85*Datos_columnas!$B$4*(G9-O9)+Datos_columnas!$B$5*O9)/1000 -> 51.229275 | Q9: =100*C9/(0.3*MIN(E9,F9)) -> 70 | R9: 29.46
B10: C3 | C10: 3.15 | D10: 13.89 | E10: 30 | F10: 15 | G10: =E10*F10 -> 450 | H10: =Datos_columnas!$B$8*G10 -> 3.6 | I10: 4 | J10: 12 | K10: 6 | L10: =FLOOR(MIN(12*J10/10,48*K10/10,MIN(E10,F10)),5) -> 10 | M10: =IF(D10="","FALTA CARGA",IF(O10<H10,"ARM. INSUFIC.",IF(D10>P10,"NO VERIFICA",IF(D10>0.85*P10,"AL LIMITE",IF(Q10>34,"VERIF. ESBELTEZ","VERIFICA"))))) -> VERIF. ESBELTEZ | N10: COL 03 del plano. Carga PROVISORIA por bajada automatica; es un piso, la real es mayor (ver Memoria, punto 5). | O10: =I10*PI()*(J10/10)^2/4 -> 4.5238934 | P10: =Datos_columnas!$B$7*0.8*(0.85*Datos_columnas!$B$4*(G10-O10)+Datos_columnas!$B$5*O10)/1000 -> 51.229275 | Q10: =100*C10/(0.3*MIN(E10,F10)) -> 70 | R10: 13.89
B11: C4 | C11: 3.15 | D11: 10.28 | E11: 10 | F11: 10 | G11: =E11*F11 -> 100 | H11: =Datos_columnas!$B$8*G11 -> 0.8 | I11: 4 | J11: 12 | K11: 6 | L11: =FLOOR(MIN(12*J11/10,48*K11/10,MIN(E11,F11)),5) -> 10 | M11: =IF(D11="","FALTA CARGA",IF(O11<H11,"ARM. INSUFIC.",IF(D11>P11,"NO VERIFICA",IF(D11>0.85*P11,"AL LIMITE",IF(Q11>34,"VERIF. ESBELTEZ","VERIFICA"))))) -> VERIF. ESBELTEZ | N11: COL 01 del plano. Carga PROVISORIA por bajada automatica; es un piso, la real es mayor (ver Memoria, punto 5). Columna de 10x10, confirmada por el proyectista. El computo metrico la omite: ese computo esta incompleto en el item 4.1.3. Esbeltez muy alta (k lu / r = 105) y capacidad de solo 18,7 t: es la columna mas comprometida del conjunto. | O11: =I11*PI()*(J11/10)^2/4 -> 4.5238934 | P11: =Datos_columnas!$B$7*0.8*(0.85*Datos_columnas!$B$4*(G11-O11)+Datos_columnas!$B$5*O11)/1000 -> 18.742275 | Q11: =100*C11/(0.3*MIN(E11,F11)) -> 105 | R11: 10.28
B12: C5 | C12: 3.15 | D12: 15.96 | E12: 15 | F12: 30 | G12: =E12*F12 -> 450 | H12: =Datos_columnas!$B$8*G12 -> 3.6 | I12: 4 | J12: 12 | K12: 6 | L12: =FLOOR(MIN(12*J12/10,48*K12/10,MIN(E12,F12)),5) -> 10 | M12: =IF(D12="","FALTA CARGA",IF(O12<H12,"ARM. INSUFIC.",IF(D12>P12,"NO VERIFICA",IF(D12>0.85*P12,"AL LIMITE",IF(Q12>34,"VERIF. ESBELTEZ","VERIFICA"))))) -> VERIF. ESBELTEZ | N12: COL 02 del plano. Carga PROVISORIA por bajada automatica; es un piso, la real es mayor (ver Memoria, punto 5). | O12: =I12*PI()*(J12/10)^2/4 -> 4.5238934 | P12: =Datos_columnas!$B$7*0.8*(0.85*Datos_columnas!$B$4*(G12-O12)+Datos_columnas!$B$5*O12)/1000 -> 51.229275 | Q12: =100*C12/(0.3*MIN(E12,F12)) -> 70 | R12: 15.96
B13: C6 | C13: 3.15 | D13: 35.39 | E13: 20 | F13: 20 | G13: =E13*F13 -> 400 | H13: =Datos_columnas!$B$8*G13 -> 3.2 | I13: 4 | J13: 12 | K13: 6 | L13: =FLOOR(MIN(12*J13/10,48*K13/10,MIN(E13,F13)),5) -> 10 | M13: =IF(D13="","FALTA CARGA",IF(O13<H13,"ARM. INSUFIC.",IF(D13>P13,"NO VERIFICA",IF(D13>0.85*P13,"AL LIMITE",IF(Q13>34,"VERIF. ESBELTEZ","VERIFICA"))))) -> VERIF. ESBELTEZ | N13: COL 04 del plano. Carga PROVISORIA por bajada automatica; es un piso, la real es mayor (ver Memoria, punto 5). | O13: =I13*PI()*(J13/10)^2/4 -> 4.5238934 | P13: =Datos_columnas!$B$7*0.8*(0.85*Datos_columnas!$B$4*(G13-O13)+Datos_columnas!$B$5*O13)/1000 -> 46.588275 | Q13: =100*C13/(0.3*MIN(E13,F13)) -> 52.5 | R13: 35.39
B14: C7 | C14: 3.15 | D14: 37.78 | E14: 30 | F14: 15 | G14: =E14*F14 -> 450 | H14: =Datos_columnas!$B$8*G14 -> 3.6 | I14: 4 | J14: 12 | K14: 6 | L14: =FLOOR(MIN(12*J14/10,48*K14/10,MIN(E14,F14)),5) -> 10 | M14: =IF(D14="","FALTA CARGA",IF(O14<H14,"ARM. INSUFIC.",IF(D14>P14,"NO VERIFICA",IF(D14>0.85*P14,"AL LIMITE",IF(Q14>34,"VERIF. ESBELTEZ","VERIFICA"))))) -> VERIF. ESBELTEZ | N14: COL 03 del plano. Carga PROVISORIA por bajada automatica; es un piso, la real es mayor (ver Memoria, punto 5). | O14: =I14*PI()*(J14/10)^2/4 -> 4.5238934 | P14: =Datos_columnas!$B$7*0.8*(0.85*Datos_columnas!$B$4*(G14-O14)+Datos_columnas!$B$5*O14)/1000 -> 51.229275 | Q14: =100*C14/(0.3*MIN(E14,F14)) -> 70 | R14: 37.78
B15: C8 | C15: 3.15 | D15: 42.67 | E15: 15 | F15: 30 | G15: =E15*F15 -> 450 | H15: =Datos_columnas!$B$8*G15 -> 3.6 | I15: 4 | J15: 12 | K15: 6 | L15: =FLOOR(MIN(12*J15/10,48*K15/10,MIN(E15,F15)),5) -> 10 | M15: =IF(D15="","FALTA CARGA",IF(O15<H15,"ARM. INSUFIC.",IF(D15>P15,"NO VERIFICA",IF(D15>0.85*P15,"AL LIMITE",IF(Q15>34,"VERIF. ESBELTEZ","VERIFICA"))))) -> VERIF. ESBELTEZ | N15: COL 02 del plano. Carga PROVISORIA por bajada automatica; es un piso, la real es mayor (ver Memoria, punto 5). | O15: =I15*PI()*(J15/10)^2/4 -> 4.5238934 | P15: =Datos_columnas!$B$7*0.8*(0.85*Datos_columnas!$B$4*(G15-O15)+Datos_columnas!$B$5*O15)/1000 -> 51.229275 | Q15: =100*C15/(0.3*MIN(E15,F15)) -> 70 | R15: 42.67
B16: C9 | C16: 3.15 | D16: 55.94 | E16: 15 | F16: 30 | G16: =E16*F16 -> 450 | H16: =Datos_columnas!$B$8*G16 -> 3.6 | I16: 4 | J16: 12 | K16: 6 | L16: =FLOOR(MIN(12*J16/10,48*K16/10,MIN(E16,F16)),5) -> 10 | M16: =IF(D16="","FALTA CARGA",IF(O16<H16,"ARM. INSUFIC.",IF(D16>P16,"NO VERIFICA",IF(D16>0.85*P16,"AL LIMITE",IF(Q16>34,"VERIF. ESBELTEZ","VERIFICA"))))) -> NO VERIFICA | N16: COL 02 del plano. Carga PROVISORIA por bajada automatica; es un piso, la real es mayor (ver Memoria, punto 5). | O16: =I16*PI()*(J16/10)^2/4 -> 4.5238934 | P16: =Datos_columnas!$B$7*0.8*(0.85*Datos_columnas!$B$4*(G16-O16)+Datos_columnas!$B$5*O16)/1000 -> 51.229275 | Q16: =100*C16/(0.3*MIN(E16,F16)) -> 70 | R16: 55.94

Sheet Vigas de fundacion
A1: VIGAS DE FUNDACION H°A° H-21 ACERO 42/50
A2: POSICION | B2: LUZ (m) | C2: CARGAS (kg/m) | F2: REACCIONES | H2: MOMENTO TRAMO (kgm) | I2: MOMENTO APOYO (kgm) | J2: DIMENSIONES | M2: ARMADURA TRAMO | P2: ARMADURA APOYO | S2: T (kg/cm2) | V2: ESTRIBOS | W2: VERIFICACION | X2: OBSERVACIONES | Y2: DATOS AUXILIARES
C3: esquema | D3: p | E3: diagrama | F3: RA | G3: RB | J3: b | K3: h | L3: d | M3: cm2 | N3: n | O3: o | P3: cm2 | Q3: n | R3: o | S3: A | T3: B | U3: o | V3: SEPAR | Y3: h muro | Z3: rec.
A4: VF01 (1) | B4: 0.77 | C4: Continua | D4: =1.2*(Datos_vigas!$B$7*J4*L4/10000+Datos_vigas!$B$16*Y4) -> 1146.6 | F4: =VLOOKUP(C4,Datos_vigas!$A$19:$E$23,4,0)*D4*B4 -> 507.65715 | G4: =F4 -> 507.65715 | H4: =VLOOKUP(C4,Datos_vigas!$A$19:$E$23,2,0)*D4*B4^2 -> 48.559481 | I4: =IF(VLOOKUP(C4,Datos_vigas!$A$19:$E$23,3,0)=0,"---",VLOOKUP(C4,Datos_vigas!$A$19:$E$23,3,0)*D4*B4^2) -> 67.981914 | J4: 20 | K4: =L4-Z4 -> 31 | L4: 35 | M4: =IF(NOT(ISNUMBER(H4)),"---",IF(H4<=0,"---",IF(H4*100/(Datos_vigas!$B$8*J4*K4^2*Datos_vigas!$B$5)>=0.5,"REVISAR",MAX((1-SQRT(1-2*H4*100/(Datos_vigas!$B$8*J4*K4^2*Datos_vigas!$B$5)))*J4*K4*Datos_vigas!$B$5/Datos_vigas!$B$6,0.0033*J4*K4)))) -> 2.046 | N4: 2 | O4: 12 | P4: =IF(NOT(ISNUMBER(I4)),"---",IF(I4<=0,"---",IF(I4*100/(Datos_vigas!$B$8*J4*K4^2*Datos_vigas!$B$5)>=0.5,"REVISAR",MAX((1-SQRT(1-2*I4*100/(Datos_vigas!$B$8*J4*K4^2*Datos_vigas!$B$5)))*J4*K4*Datos_vigas!$B$5/Datos_vigas!$B$6,0.0033*J4*K4)))) -> 2.046 | Q4: 2 | R4: 12 | S4: =F4/(J4*0.85*K4) -> 0.9632963 | T4: =G4/(J4*0.85*K4) -> 0.9632963 | U4: 6 | V4: 15 | W4: =IF(OR(M4="REVISAR",P4="REVISAR"),"SECCION INSUF.",IF(NOT(AND(M4<>"REVISAR",P4<>"REVISAR",IF(ISNUMBER(M4),N4*PI()*(O4/10)^2/4>=M4,TRUE()),IF(ISNUMBER(P4),Q4*PI()*(R4/10)^2/4>=P4,TRUE()),IF(ISNUMBER(M4),M4<=0.0163*J4*K4,TRUE()),IF(ISNUMBER(P4),P4<=0.0163*J4*K4,TRUE()))),"NO VERIFICA FLEX.",IF(NOT(F4<=Datos_vigas!$B$9*(0.53*SQRT(Datos_vigas!$B$5)*J4*K4+2*PI()*(U4/10)^2/4*Datos_vigas!$B$6*K4/V4)),"NO VERIF. CORTE","VERIFICA"))) -> VERIFICA | Y4: 3.15 | Z4: 4
A5: VF01 (2) | B5: 0.77 | C5: Continua | D5: =1.2*(Datos_vigas!$B$7*J5*L5/10000+Datos_vigas!$B$16*Y5) -> 1146.6 | F5: =VLOOKUP(C5,Datos_vigas!$A$19:$E$23,4,0)*D5*B5 -> 507.65715 | G5: =F5 -> 507.65715 | H5: =VLOOKUP(C5,Datos_vigas!$A$19:$E$23,2,0)*D5*B5^2 -> 48.559481 | I5: =IF(VLOOKUP(C5,Datos_vigas!$A$19:$E$23,3,0)=0,"---",VLOOKUP(C5,Datos_vigas!$A$19:$E$23,3,0)*D5*B5^2) -> 67.981914 | J5: 20 | K5: =L5-Z5 -> 31 | L5: 35 | M5: =IF(NOT(ISNUMBER(H5)),"---",IF(H5<=0,"---",IF(H5*100/(Datos_vigas!$B$8*J5*K5^2*Datos_vigas!$B$5)>=0.5,"REVISAR",MAX((1-SQRT(1-2*H5*100/(Datos_vigas!$B$8*J5*K5^2*Datos_vigas!$B$5)))*J5*K5*Datos_vigas!$B$5/Datos_vigas!$B$6,0.0033*J5*K5)))) -> 2.046 | N5: 2 | O5: 12 | P5: =IF(NOT(ISNUMBER(I5)),"---",IF(I5<=0,"---",IF(I5*100/(Datos_vigas!$B$8*J5*K5^2*Datos_vigas!$B$5)>=0.5,"REVISAR",MAX((1-SQRT(1-2*I5*100/(Datos_vigas!$B$8*J5*K5^2*Datos_vigas!$B$5)))*J5*K5*Datos_vigas!$B$5/Datos_vigas!$B$6,0.0033*J5*K5)))) -> 2.046 | Q5: 2 | R5: 12 | S5: =F5/(J5*0.85*K5) -> 0.9632963 | T5: =G5/(J5*0.85*K5) -> 0.9632963 | U5: 6 | V5: 15 | W5: =IF(OR(M5="REVISAR",P5="REVISAR"),"SECCION INSUF.",IF(NOT(AND(M5<>"REVISAR",P5<>"REVISAR",IF(ISNUMBER(M5),N5*PI()*(O5/10)^2/4>=M5,TRUE()),IF(ISNUMBER(P5),Q5*PI()*(R5/10)^2/4>=P5,TRUE()),IF(ISNUMBER(M5),M5<=0.0163*J5*K5,TRUE()),IF(ISNUMBER(P5),P5<=0.0163*J5*K5,TRUE()))),"NO VERIFICA FLEX.",IF(NOT(F5<=Datos_vigas!$B$9*(0.53*SQRT(Datos_vigas!$B$5)*J5*K5+2*PI()*(U5/10)^2/4*Datos_vigas!$B$6*K5/V5)),"NO VERIF. CORTE","VERIFICA"))) -> VERIFICA | Y5: 3.15 | Z5: 4
A6: VF01 (3) | B6: 0.77 | C6: Continua | D6: =1.2*(Datos_vigas!$B$7*J6*L6/10000+Datos_vigas!$B$16*Y6) -> 1146.6 | F6: =VLOOKUP(C6,Datos_vigas!$A$19:$E$23,4,0)*D6*B6 -> 507.65715 | G6: =F6 -> 507.65715 | H6: =VLOOKUP(C6,Datos_vigas!$A$19:$E$23,2,0)*D6*B6^2 -> 48.559481 | I6: =IF(VLOOKUP(C6,Datos_vigas!$A$19:$E$23,3,0)=0,"---",VLOOKUP(C6,Datos_vigas!$A$19:$E$23,3,0)*D6*B6^2) -> 67.981914 | J6: 20 | K6: =L6-Z6 -> 31 | L6: 35 | M6: =IF(NOT(ISNUMBER(H6)),"---",IF(H6<=0,"---",IF(H6*100/(Datos_vigas!$B$8*J6*K6^2*Datos_vigas!$B$5)>=0.5,"REVISAR",MAX((1-SQRT(1-2*H6*100/(Datos_vigas!$B$8*J6*K6^2*Datos_vigas!$B$5)))*J6*K6*Datos_vigas!$B$5/Datos_vigas!$B$6,0.0033*J6*K6)))) -> 2.046 | N6: 2 | O6: 12 | P6: =IF(NOT(ISNUMBER(I6)),"---",IF(I6<=0,"---",IF(I6*100/(Datos_vigas!$B$8*J6*K6^2*Datos_vigas!$B$5)>=0.5,"REVISAR",MAX((1-SQRT(1-2*I6*100/(Datos_vigas!$B$8*J6*K6^2*Datos_vigas!$B$5)))*J6*K6*Datos_vigas!$B$5/Datos_vigas!$B$6,0.0033*J6*K6)))) -> 2.046 | Q6: 2 | R6: 12 | S6: =F6/(J6*0.85*K6) -> 0.9632963 | T6: =G6/(J6*0.85*K6) -> 0.9632963 | U6: 6 | V6: 15 | W6: =IF(OR(M6="REVISAR",P6="REVISAR"),"SECCION INSUF.",IF(NOT(AND(M6<>"REVISAR",P6<>"REVISAR",IF(ISNUMBER(M6),N6*PI()*(O6/10)^2/4>=M6,TRUE()),IF(ISNUMBER(P6),Q6*PI()*(R6/10)^2/4>=P6,TRUE()),IF(ISNUMBER(M6),M6<=0.0163*J6*K6,TRUE()),IF(ISNUMBER(P6),P6<=0.0163*J6*K6,TRUE()))),"NO VERIFICA FLEX.",IF(NOT(F6<=Datos_vigas!$B$9*(0.53*SQRT(Datos_vigas!$B$5)*J6*K6+2*PI()*(U6/10)^2/4*Datos_vigas!$B$6*K6/V6)),"NO VERIF. CORTE","VERIFICA"))) -> VERIFICA | Y6: 3.15 | Z6: 4
A7: VF02 | B7: 2.94 | C7: Simplemente apoyada | D7: =1.2*(Datos_vigas!$B$7*J7*L7/10000+Datos_vigas!$B$16*Y7) -> 1197 | F7: =VLOOKUP(C7,Datos_vigas!$A$19:$E$23,4,0)*D7*B7 -> 1759.59 | G7: =F7 -> 1759.59 | H7: =VLOOKUP(C7,Datos_vigas!$A$19:$E$23,2,0)*D7*B7^2 -> 1293.2986 | I7: =IF(VLOOKUP(C7,Datos_vigas!$A$19:$E$23,3,0)=0,"---",VLOOKUP(C7,Datos_vigas!$A$19:$E$23,3,0)*D7*B7^2) -> --- | J7: 25 | K7: =L7-Z7 -> 31 | L7: 35 | M7: =IF(NOT(ISNUMBER(H7)),"---",IF(H7<=0,"---",IF(H7*100/(Datos_vigas!$B$8*J7*K7^2*Datos_vigas!$B$5)>=0.5,"REVISAR",MAX((1-SQRT(1-2*H7*100/(Datos_vigas!$B$8*J7*K7^2*Datos_vigas!$B$5)))*J7*K7*Datos_vigas!$B$5/Datos_vigas!$B$6,0.0033*J7*K7)))) -> 2.5575 | N7: 6 | O7: 8 | P7: =IF(NOT(ISNUMBER(I7)),"---",IF(I7<=0,"---",IF(I7*100/(Datos_vigas!$B$8*J7*K7^2*Datos_vigas!$B$5)>=0.5,"REVISAR",MAX((1-SQRT(1-2*I7*100/(Datos_vigas!$B$8*J7*K7^2*Datos_vigas!$B$5)))*J7*K7*Datos_vigas!$B$5/Datos_vigas!$B$6,0.0033*J7*K7)))) -> --- | Q7: --- | R7: --- | S7: =F7/(J7*0.85*K7) -> 2.6711044 | T7: =G7/(J7*0.85*K7) -> 2.6711044 | U7: 6 | V7: 15 | W7: =IF(OR(M7="REVISAR",P7="REVISAR"),"SECCION INSUF.",IF(NOT(AND(M7<>"REVISAR",P7<>"REVISAR",IF(ISNUMBER(M7),N7*PI()*(O7/10)^2/4>=M7,TRUE()),IF(ISNUMBER(P7),Q7*PI()*(R7/10)^2/4>=P7,TRUE()),IF(ISNUMBER(M7),M7<=0.0163*J7*K7,TRUE()),IF(ISNUMBER(P7),P7<=0.0163*J7*K7,TRUE()))),"NO VERIFICA FLEX.",IF(NOT(F7<=Datos_vigas!$B$9*(0.53*SQRT(Datos_vigas!$B$5)*J7*K7+2*PI()*(U7/10)^2/4*Datos_vigas!$B$6*K7/V7)),"NO VERIF. CORTE","VERIFICA"))) -> VERIFICA | X7: Longitud total 3.28 m. La luz de calculo es la mayor entre pilotes, deducida de la posicion de los pilotes dibujados en el plano. | Y7: 3.15 | Z7: 4
A8: VF03 | B8: 9.01 | C8: Continua | D8: =1.2*(Datos_vigas!$B$7*J8*L8/10000+Datos_vigas!$B$16*Y8) -> 1103.4 | F8: =VLOOKUP(C8,Datos_vigas!$A$19:$E$23,4,0)*D8*B8 -> 5716.4396 | G8: =F8 -> 5716.4396 | H8: =VLOOKUP(C8,Datos_vigas!$A$19:$E$23,2,0)*D8*B8^2 -> 6398.2796 | I8: =IF(VLOOKUP(C8,Datos_vigas!$A$19:$E$23,3,0)=0,"---",VLOOKUP(C8,Datos_vigas!$A$19:$E$23,3,0)*D8*B8^2) -> 8957.4122 | J8: 22 | K8: =L8-Z8 -> 18 | L8: 25 | M8: =IF(NOT(ISNUMBER(H8)),"---",IF(H8<=0,"---",IF(H8*100/(Datos_vigas!$B$8*J8*K8^2*Datos_vigas!$B$5)>=0.5,"REVISAR",MAX((1-SQRT(1-2*H8*100/(Datos_vigas!$B$8*J8*K8^2*Datos_vigas!$B$5)))*J8*K8*Datos_vigas!$B$5/Datos_vigas!$B$6,0.0033*J8*K8)))) -> 15.366789 | N8: 2 | O8: 25 | P8: =IF(NOT(ISNUMBER(I8)),"---",IF(I8<=0,"---",IF(I8*100/(Datos_vigas!$B$8*J8*K8^2*Datos_vigas!$B$5)>=0.5,"REVISAR",MAX((1-SQRT(1-2*I8*100/(Datos_vigas!$B$8*J8*K8^2*Datos_vigas!$B$5)))*J8*K8*Datos_vigas!$B$5/Datos_vigas!$B$6,0.0033*J8*K8)))) -> REVISAR | Q8: 5 | R8: 6 | S8: =F8/(J8*0.85*K8) -> 16.982886 | T8: =G8/(J8*0.85*K8) -> 16.982886 | U8: 12 | V8: 5 | W8: =IF(OR(M8="REVISAR",P8="REVISAR"),"SECCION INSUF.",IF(NOT(AND(M8<>"REVISAR",P8<>"REVISAR",IF(ISNUMBER(M8),N8*PI()*(O8/10)^2/4>=M8,TRUE()),IF(ISNUMBER(P8),Q8*PI()*(R8/10)^2/4>=P8,TRUE()),IF(ISNUMBER(M8),M8<=0.0163*J8*K8,TRUE()),IF(ISNUMBER(P8),P8<=0.0163*J8*K8,TRUE()))),"NO VERIFICA FLEX.",IF(NOT(F8<=Datos_vigas!$B$9*(0.53*SQRT(Datos_vigas!$B$5)*J8*K8+2*PI()*(U8/10)^2/4*Datos_vigas!$B$6*K8/V8)),"NO VERIF. CORTE","VERIFICA"))) -> SECCION INSUF. | X8: Longitud total 9.28 m. La luz de calculo es la mayor entre pilotes, deducida de la posicion de los pilotes dibujados en el plano. No se detectaron pilotes intermedios en este tramo. Verificar: puede estar apoyada directamente sobre el terreno, en cuyo caso no flexiona como viga de luz libre. Relacion luz/altura alta. En una viga de fundacion enterrada la flecha no suele gobernar, por eso no se la incluye en la verificacion. | Y8: 3.15 | Z8: 7
A9: VF04a | B9: 3.8 | C9: Continua | D9: =1.2*(Datos_vigas!$B$7*J9*L9/10000+Datos_vigas!$B$16*Y9) -> 1166.76 | F9: =VLOOKUP(C9,Datos_vigas!$A$19:$E$23,4,0)*D9*B9 -> 2549.3706 | G9: =F9 -> 2549.3706 | H9: =VLOOKUP(C9,Datos_vigas!$A$19:$E$23,2,0)*D9*B9^2 -> 1203.4537 | I9: =IF(VLOOKUP(C9,Datos_vigas!$A$19:$E$23,3,0)=0,"---",VLOOKUP(C9,Datos_vigas!$A$19:$E$23,3,0)*D9*B9^2) -> 1684.8014 | J9: 22 | K9: =L9-Z9 -> 31 | L9: 35 | M9: =IF(NOT(ISNUMBER(H9)),"---",IF(H9<=0,"---",IF(H9*100/(Datos_vigas!$B$8*J9*K9^2*Datos_vigas!$B$5)>=0.5,"REVISAR",MAX((1-SQRT(1-2*H9*100/(Datos_vigas!$B$8*J9*K9^2*Datos_vigas!$B$5)))*J9*K9*Datos_vigas!$B$5/Datos_vigas!$B$6,0.0033*J9*K9)))) -> 2.2506 | N9: 2 | O9: 12 | P9: =IF(NOT(ISNUMBER(I9)),"---",IF(I9<=0,"---",IF(I9*100/(Datos_vigas!$B$8*J9*K9^2*Datos_vigas!$B$5)>=0.5,"REVISAR",MAX((1-SQRT(1-2*I9*100/(Datos_vigas!$B$8*J9*K9^2*Datos_vigas!$B$5)))*J9*K9*Datos_vigas!$B$5/Datos_vigas!$B$6,0.0033*J9*K9)))) -> 2.2506 | Q9: 2 | R9: 12 | S9: =F9/(J9*0.85*K9) -> 4.3977412 | T9: =G9/(J9*0.85*K9) -> 4.3977412 | U9: 6 | V9: 15 | W9: =IF(OR(M9="REVISAR",P9="REVISAR"),"SECCION INSUF.",IF(NOT(AND(M9<>"REVISAR",P9<>"REVISAR",IF(ISNUMBER(M9),N9*PI()*(O9/10)^2/4>=M9,TRUE()),IF(ISNUMBER(P9),Q9*PI()*(R9/10)^2/4>=P9,TRUE()),IF(ISNUMBER(M9),M9<=0.0163*J9*K9,TRUE()),IF(ISNUMBER(P9),P9<=0.0163*J9*K9,TRUE()))),"NO VERIFICA FLEX.",IF(NOT(F9<=Datos_vigas!$B$9*(0.53*SQRT(Datos_vigas!$B$5)*J9*K9+2*PI()*(U9/10)^2/4*Datos_vigas!$B$6*K9/V9)),"NO VERIF. CORTE","VERIFICA"))) -> VERIFICA | X9: El ancho quedo cortado en el PDF: se adopta 20 cm. Confirmar si es 20 o 22. Longitud total 5.33 m. La luz de calculo es la mayor entre pilotes, deducida de la posicion de los pilotes dibujados en el plano. | Y9: 3.15 | Z9: 4
A10: VF04b | B10: 3.3 | C10: Continua | D10: =1.2*(Datos_vigas!$B$7*J10*L10/10000+Datos_vigas!$B$16*Y10) -> 1089 | F10: =VLOOKUP(C10,Datos_vigas!$A$19:$E$23,4,0)*D10*B10 -> 2066.3775 | G10: =F10 -> 2066.3775 | H10: =VLOOKUP(C10,Datos_vigas!$A$19:$E$23,2,0)*D10*B10^2 -> 847.10337 | I10: =IF(VLOOKUP(C10,Datos_vigas!$A$19:$E$23,3,0)=0,"---",VLOOKUP(C10,Datos_vigas!$A$19:$E$23,3,0)*D10*B10^2) -> 1185.921 | J10: 20 | K10: =L10-Z10 -> 21 | L10: 25 | M10: =IF(NOT(ISNUMBER(H10)),"---",IF(H10<=0,"---",IF(H10*100/(Datos_vigas!$B$8*J10*K10^2*Datos_vigas!$B$5)>=0.5,"REVISAR",MAX((1-SQRT(1-2*H10*100/(Datos_vigas!$B$8*J10*K10^2*Datos_vigas!$B$5)))*J10*K10*Datos_vigas!$B$5/Datos_vigas!$B$6,0.0033*J10*K10)))) -> 1.386 | N10: 5 | O10: 6 | P10: =IF(NOT(ISNUMBER(I10)),"---",IF(I10<=0,"---",IF(I10*100/(Datos_vigas!$B$8*J10*K10^2*Datos_vigas!$B$5)>=0.5,"REVISAR",MAX((1-SQRT(1-2*I10*100/(Datos_vigas!$B$8*J10*K10^2*Datos_vigas!$B$5)))*J10*K10*Datos_vigas!$B$5/Datos_vigas!$B$6,0.0033*J10*K10)))) -> 1.5512762 | Q10: 2 | R10: 10 | S10: =F10/(J10*0.85*K10) -> 5.7881723 | T10: =G10/(J10*0.85*K10) -> 5.7881723 | U10: 6 | V10: 10 | W10: =IF(OR(M10="REVISAR",P10="REVISAR"),"SECCION INSUF.",IF(NOT(AND(M10<>"REVISAR",P10<>"REVISAR",IF(ISNUMBER(M10),N10*PI()*(O10/10)^2/4>=M10,TRUE()),IF(ISNUMBER(P10),Q10*PI()*(R10/10)^2/4>=P10,TRUE()),IF(ISNUMBER(M10),M10<=0.0163*J10*K10,TRUE()),IF(ISNUMBER(P10),P10<=0.0163*J10*K10,TRUE()))),"NO VERIFICA FLEX.",IF(NOT(F10<=Datos_vigas!$B$9*(0.53*SQRT(Datos_vigas!$B$5)*J10*K10+2*PI()*(U10/10)^2/4*Datos_vigas!$B$6*K10/V10)),"NO VERIF. CORTE","VERIFICA"))) -> VERIFICA | Y10: 3.15 | Z10: 4
A11: VF04c | B11: 3.08 | C11: Continua | D11: =1.2*(Datos_vigas!$B$7*J11*L11/10000+Datos_vigas!$B$16*Y11) -> 1089 | F11: =VLOOKUP(C11,Datos_vigas!$A$19:$E$23,4,0)*D11*B11 -> 1928.619 | G11: =F11 -> 1928.619 | H11: =VLOOKUP(C11,Datos_vigas!$A$19:$E$23,2,0)*D11*B11^2 -> 737.92116 | I11: =IF(VLOOKUP(C11,Datos_vigas!$A$19:$E$23,3,0)=0,"---",VLOOKUP(C11,Datos_vigas!$A$19:$E$23,3,0)*D11*B11^2) -> 1033.069 | J11: 20 | K11: =L11-Z11 -> 21 | L11: 25 | M11: =IF(NOT(ISNUMBER(H11)),"---",IF(H11<=0,"---",IF(H11*100/(Datos_vigas!$B$8*J11*K11^2*Datos_vigas!$B$5)>=0.5,"REVISAR",MAX((1-SQRT(1-2*H11*100/(Datos_vigas!$B$8*J11*K11^2*Datos_vigas!$B$5)))*J11*K11*Datos_vigas!$B$5/Datos_vigas!$B$6,0.0033*J11*K11)))) -> 1.386 | N11: 5 | O11: 6 | P11: =IF(NOT(ISNUMBER(I11)),"---",IF(I11<=0,"---",IF(I11*100/(Datos_vigas!$B$8*J11*K11^2*Datos_vigas!$B$5)>=0.5,"REVISAR",MAX((1-SQRT(1-2*I11*100/(Datos_vigas!$B$8*J11*K11^2*Datos_vigas!$B$5)))*J11*K11*Datos_vigas!$B$5/Datos_vigas!$B$6,0.0033*J11*K11)))) -> 1.386 | Q11: 5 | R11: 6 | S11: =F11/(J11*0.85*K11) -> 5.4022941 | T11: =G11/(J11*0.85*K11) -> 5.4022941 | U11: 6 | V11: 10 | W11: =IF(OR(M11="REVISAR",P11="REVISAR"),"SECCION INSUF.",IF(NOT(AND(M11<>"REVISAR",P11<>"REVISAR",IF(ISNUMBER(M11),N11*PI()*(O11/10)^2/4>=M11,TRUE()),IF(ISNUMBER(P11),Q11*PI()*(R11/10)^2/4>=P11,TRUE()),IF(ISNUMBER(M11),M11<=0.0163*J11*K11,TRUE()),IF(ISNUMBER(P11),P11<=0.0163*J11*K11,TRUE()))),"NO VERIFICA FLEX.",IF(NOT(F11<=Datos_vigas!$B$9*(0.53*SQRT(Datos_vigas!$B$5)*J11*K11+2*PI()*(U11/10)^2/4*Datos_vigas!$B$6*K11/V11)),"NO VERIF. CORTE","VERIFICA"))) -> VERIFICA | Y11: 3.15 | Z11: 4
A12: VF05 | B12: 2.26 | C12: Simplemente apoyada | D12: =1.2*(Datos_vigas!$B$7*J12*L12/10000+Datos_vigas!$B$16*Y12) -> 1053 | F12: =VLOOKUP(C12,Datos_vigas!$A$19:$E$23,4,0)*D12*B12 -> 1189.89 | G12: =F12 -> 1189.89 | H12: =VLOOKUP(C12,Datos_vigas!$A$19:$E$23,2,0)*D12*B12^2 -> 672.28785 | I12: =IF(VLOOKUP(C12,Datos_vigas!$A$19:$E$23,3,0)=0,"---",VLOOKUP(C12,Datos_vigas!$A$19:$E$23,3,0)*D12*B12^2) -> --- | J12: 15 | K12: =L12-Z12 -> 21 | L12: 25 | M12: =IF(NOT(ISNUMBER(H12)),"---",IF(H12<=0,"---",IF(H12*100/(Datos_vigas!$B$8*J12*K12^2*Datos_vigas!$B$5)>=0.5,"REVISAR",MAX((1-SQRT(1-2*H12*100/(Datos_vigas!$B$8*J12*K12^2*Datos_vigas!$B$5)))*J12*K12*Datos_vigas!$B$5/Datos_vigas!$B$6,0.0033*J12*K12)))) -> 1.0395 | N12: 3 | O12: 8 | P12: =IF(NOT(ISNUMBER(I12)),"---",IF(I12<=0,"---",IF(I12*100/(Datos_vigas!$B$8*J12*K12^2*Datos_vigas!$B$5)>=0.5,"REVISAR",MAX((1-SQRT(1-2*I12*100/(Datos_vigas!$B$8*J12*K12^2*Datos_vigas!$B$5)))*J12*K12*Datos_vigas!$B$5/Datos_vigas!$B$6,0.0033*J12*K12)))) -> --- | Q12: --- | R12: --- | S12: =F12/(J12*0.85*K12) -> 4.4440336 | T12: =G12/(J12*0.85*K12) -> 4.4440336 | U12: 6 | V12: 10 | W12: =IF(OR(M12="REVISAR",P12="REVISAR"),"SECCION INSUF.",IF(NOT(AND(M12<>"REVISAR",P12<>"REVISAR",IF(ISNUMBER(M12),N12*PI()*(O12/10)^2/4>=M12,TRUE()),IF(ISNUMBER(P12),Q12*PI()*(R12/10)^2/4>=P12,TRUE()),IF(ISNUMBER(M12),M12<=0.0163*J12*K12,TRUE()),IF(ISNUMBER(P12),P12<=0.0163*J12*K12,TRUE()))),"NO VERIFICA FLEX.",IF(NOT(F12<=Datos_vigas!$B$9*(0.53*SQRT(Datos_vigas!$B$5)*J12*K12+2*PI()*(U12/10)^2/4*Datos_vigas!$B$6*K12/V12)),"NO VERIF. CORTE","VERIFICA"))) -> VERIFICA | Y12: 3.15 | Z12: 4
A13: VF06a | B13: 0.23 | C13: Continua | D13: =1.2*(Datos_vigas!$B$7*J13*L13/10000+Datos_vigas!$B$16*Y13) -> 1053 | F13: =VLOOKUP(C13,Datos_vigas!$A$19:$E$23,4,0)*D13*B13 -> 139.25925 | G13: =F13 -> 139.25925 | H13: =VLOOKUP(C13,Datos_vigas!$A$19:$E$23,2,0)*D13*B13^2 -> 3.9789153 | I13: =IF(VLOOKUP(C13,Datos_vigas!$A$19:$E$23,3,0)=0,"---",VLOOKUP(C13,Datos_vigas!$A$19:$E$23,3,0)*D13*B13^2) -> 5.57037 | J13: 15 | K13: =L13-Z13 -> 21 | L13: 25 | M13: =IF(NOT(ISNUMBER(H13)),"---",IF(H13<=0,"---",IF(H13*100/(Datos_vigas!$B$8*J13*K13^2*Datos_vigas!$B$5)>=0.5,"REVISAR",MAX((1-SQRT(1-2*H13*100/(Datos_vigas!$B$8*J13*K13^2*Datos_vigas!$B$5)))*J13*K13*Datos_vigas!$B$5/Datos_vigas!$B$6,0.0033*J13*K13)))) -> 1.0395 | N13: 3 | O13: 8 | P13: =IF(NOT(ISNUMBER(I13)),"---",IF(I13<=0,"---",IF(I13*100/(Datos_vigas!$B$8*J13*K13^2*Datos_vigas!$B$5)>=0.5,"REVISAR",MAX((1-SQRT(1-2*I13*100/(Datos_vigas!$B$8*J13*K13^2*Datos_vigas!$B$5)))*J13*K13*Datos_vigas!$B$5/Datos_vigas!$B$6,0.0033*J13*K13)))) -> 1.0395 | Q13: 3 | R13: 8 | S13: =F13/(J13*0.85*K13) -> 0.52010924 | T13: =G13/(J13*0.85*K13) -> 0.52010924 | U13: 6 | V13: 10 | W13: =IF(OR(M13="REVISAR",P13="REVISAR"),"SECCION INSUF.",IF(NOT(AND(M13<>"REVISAR",P13<>"REVISAR",IF(ISNUMBER(M13),N13*PI()*(O13/10)^2/4>=M13,TRUE()),IF(ISNUMBER(P13),Q13*PI()*(R13/10)^2/4>=P13,TRUE()),IF(ISNUMBER(M13),M13<=0.0163*J13*K13,TRUE()),IF(ISNUMBER(P13),P13<=0.0163*J13*K13,TRUE()))),"NO VERIFICA FLEX.",IF(NOT(F13<=Datos_vigas!$B$9*(0.53*SQRT(Datos_vigas!$B$5)*J13*K13+2*PI()*(U13/10)^2/4*Datos_vigas!$B$6*K13/V13)),"NO VERIF. CORTE","VERIFICA"))) -> VERIFICA | Y13: 3.15 | Z13: 4
A14: VF06b | B14: 1.83 | C14: Continua | D14: =1.2*(Datos_vigas!$B$7*J14*L14/10000+Datos_vigas!$B$16*Y14) -> 1089 | F14: =VLOOKUP(C14,Datos_vigas!$A$19:$E$23,4,0)*D14*B14 -> 1145.9002 | G14: =F14 -> 1145.9002 | H14: =VLOOKUP(C14,Datos_vigas!$A$19:$E$23,2,0)*D14*B14^2 -> 260.50179 | I14: =IF(VLOOKUP(C14,Datos_vigas!$A$19:$E$23,3,0)=0,"---",VLOOKUP(C14,Datos_vigas!$A$19:$E$23,3,0)*D14*B14^2) -> 364.69521 | J14: 20 | K14: =L14-Z14 -> 21 | L14: 25 | M14: =IF(NOT(ISNUMBER(H14)),"---",IF(H14<=0,"---",IF(H14*100/(Datos_vigas!$B$8*J14*K14^2*Datos_vigas!$B$5)>=0.5,"REVISAR",MAX((1-SQRT(1-2*H14*100/(Datos_vigas!$B$8*J14*K14^2*Datos_vigas!$B$5)))*J14*K14*Datos_vigas!$B$5/Datos_vigas!$B$6,0.0033*J14*K14)))) -> 1.386 | N14: 5 | O14: 6 | P14: =IF(NOT(ISNUMBER(I14)),"---",IF(I14<=0,"---",IF(I14*100/(Datos_vigas!$B$8*J14*K14^2*Datos_vigas!$B$5)>=0.5,"REVISAR",MAX((1-SQRT(1-2*I14*100/(Datos_vigas!$B$8*J14*K14^2*Datos_vigas!$B$5)))*J14*K14*Datos_vigas!$B$5/Datos_vigas!$B$6,0.0033*J14*K14)))) -> 1.386 | Q14: 5 | R14: 6 | S14: =F14/(J14*0.85*K14) -> 3.2098046 | T14: =G14/(J14*0.85*K14) -> 3.2098046 | U14: 6 | V14: 10 | W14: =IF(OR(M14="REVISAR",P14="REVISAR"),"SECCION INSUF.",IF(NOT(AND(M14<>"REVISAR",P14<>"REVISAR",IF(ISNUMBER(M14),N14*PI()*(O14/10)^2/4>=M14,TRUE()),IF(ISNUMBER(P14),Q14*PI()*(R14/10)^2/4>=P14,TRUE()),IF(ISNUMBER(M14),M14<=0.0163*J14*K14,TRUE()),IF(ISNUMBER(P14),P14<=0.0163*J14*K14,TRUE()))),"NO VERIFICA FLEX.",IF(NOT(F14<=Datos_vigas!$B$9*(0.53*SQRT(Datos_vigas!$B$5)*J14*K14+2*PI()*(U14/10)^2/4*Datos_vigas!$B$6*K14/V14)),"NO VERIF. CORTE","VERIFICA"))) -> VERIFICA | Y14: 3.15 | Z14: 4
A15: VF06c | B15: 3.3 | C15: Continua | D15: =1.2*(Datos_vigas!$B$7*J15*L15/10000+Datos_vigas!$B$16*Y15) -> 1089 | F15: =VLOOKUP(C15,Datos_vigas!$A$19:$E$23,4,0)*D15*B15 -> 2066.3775 | G15: =F15 -> 2066.3775 | H15: =VLOOKUP(C15,Datos_vigas!$A$19:$E$23,2,0)*D15*B15^2 -> 847.10337 | I15: =IF(VLOOKUP(C15,Datos_vigas!$A$19:$E$23,3,0)=0,"---",VLOOKUP(C15,Datos_vigas!$A$19:$E$23,3,0)*D15*B15^2) -> 1185.921 | J15: 20 | K15: =L15-Z15 -> 21 | L15: 25 | M15: =IF(NOT(ISNUMBER(H15)),"---",IF(H15<=0,"---",IF(H15*100/(Datos_vigas!$B$8*J15*K15^2*Datos_vigas!$B$5)>=0.5,"REVISAR",MAX((1-SQRT(1-2*H15*100/(Datos_vigas!$B$8*J15*K15^2*Datos_vigas!$B$5)))*J15*K15*Datos_vigas!$B$5/Datos_vigas!$B$6,0.0033*J15*K15)))) -> 1.386 | N15: 5 | O15: 6 | P15: =IF(NOT(ISNUMBER(I15)),"---",IF(I15<=0,"---",IF(I15*100/(Datos_vigas!$B$8*J15*K15^2*Datos_vigas!$B$5)>=0.5,"REVISAR",MAX((1-SQRT(1-2*I15*100/(Datos_vigas!$B$8*J15*K15^2*Datos_vigas!$B$5)))*J15*K15*Datos_vigas!$B$5/Datos_vigas!$B$6,0.0033*J15*K15)))) -> 1.5512762 | Q15: 2 | R15: 10 | S15: =F15/(J15*0.85*K15) -> 5.7881723 | T15: =G15/(J15*0.85*K15) -> 5.7881723 | U15: 6 | V15: 10 | W15: =IF(OR(M15="REVISAR",P15="REVISAR"),"SECCION INSUF.",IF(NOT(AND(M15<>"REVISAR",P15<>"REVISAR",IF(ISNUMBER(M15),N15*PI()*(O15/10)^2/4>=M15,TRUE()),IF(ISNUMBER(P15),Q15*PI()*(R15/10)^2/4>=P15,TRUE()),IF(ISNUMBER(M15),M15<=0.0163*J15*K15,TRUE()),IF(ISNUMBER(P15),P15<=0.0163*J15*K15,TRUE()))),"NO VERIFICA FLEX.",IF(NOT(F15<=Datos_vigas!$B$9*(0.53*SQRT(Datos_vigas!$B$5)*J15*K15+2*PI()*(U15/10)^2/4*Datos_vigas!$B$6*K15/V15)),"NO VERIF. CORTE","VERIFICA"))) -> VERIFICA | Y15: 3.15 | Z15: 4
A16: VF06d | B16: 3.03 | C16: Continua | D16: =1.2*(Datos_vigas!$B$7*J16*L16/10000+Datos_vigas!$B$16*Y16) -> 1103.4 | F16: =VLOOKUP(C16,Datos_vigas!$A$19:$E$23,4,0)*D16*B16 -> 1922.3987 | G16: =F16 -> 1922.3987 | H16: =VLOOKUP(C16,Datos_vigas!$A$19:$E$23,2,0)*D16*B16^2 -> 723.60055 | I16: =IF(VLOOKUP(C16,Datos_vigas!$A$19:$E$23,3,0)=0,"---",VLOOKUP(C16,Datos_vigas!$A$19:$E$23,3,0)*D16*B16^2) -> 1013.0205 | J16: 22 | K16: =L16-Z16 -> 21 | L16: 25 | M16: =IF(NOT(ISNUMBER(H16)),"---",IF(H16<=0,"---",IF(H16*100/(Datos_vigas!$B$8*J16*K16^2*Datos_vigas!$B$5)>=0.5,"REVISAR",MAX((1-SQRT(1-2*H16*100/(Datos_vigas!$B$8*J16*K16^2*Datos_vigas!$B$5)))*J16*K16*Datos_vigas!$B$5/Datos_vigas!$B$6,0.0033*J16*K16)))) -> 1.5246 | N16: 2 | O16: 10 | P16: =IF(NOT(ISNUMBER(I16)),"---",IF(I16<=0,"---",IF(I16*100/(Datos_vigas!$B$8*J16*K16^2*Datos_vigas!$B$5)>=0.5,"REVISAR",MAX((1-SQRT(1-2*I16*100/(Datos_vigas!$B$8*J16*K16^2*Datos_vigas!$B$5)))*J16*K16*Datos_vigas!$B$5/Datos_vigas!$B$6,0.0033*J16*K16)))) -> 1.5246 | Q16: 2 | R16: 10 | S16: =F16/(J16*0.85*K16) -> 4.8953365 | T16: =G16/(J16*0.85*K16) -> 4.8953365 | U16: 6 | V16: 10 | W16: =IF(OR(M16="REVISAR",P16="REVISAR"),"SECCION INSUF.",IF(NOT(AND(M16<>"REVISAR",P16<>"REVISAR",IF(ISNUMBER(M16),N16*PI()*(O16/10)^2/4>=M16,TRUE()),IF(ISNUMBER(P16),Q16*PI()*(R16/10)^2/4>=P16,TRUE()),IF(ISNUMBER(M16),M16<=0.0163*J16*K16,TRUE()),IF(ISNUMBER(P16),P16<=0.0163*J16*K16,TRUE()))),"NO VERIFICA FLEX.",IF(NOT(F16<=Datos_vigas!$B$9*(0.53*SQRT(Datos_vigas!$B$5)*J16*K16+2*PI()*(U16/10)^2/4*Datos_vigas!$B$6*K16/V16)),"NO VERIF. CORTE","VERIFICA"))) -> VERIFICA | Y16: 3.15 | Z16: 4
A17: VF07 | B17: 3.5 | C17: Simplemente apoyada | D17: =1.2*(Datos_vigas!$B$7*J17*L17/10000+Datos_vigas!$B$16*Y17) -> 1089 | F17: =VLOOKUP(C17,Datos_vigas!$A$19:$E$23,4,0)*D17*B17 -> 1905.75 | G17: =F17 -> 1905.75 | H17: =VLOOKUP(C17,Datos_vigas!$A$19:$E$23,2,0)*D17*B17^2 -> 1667.5312 | I17: =IF(VLOOKUP(C17,Datos_vigas!$A$19:$E$23,3,0)=0,"---",VLOOKUP(C17,Datos_vigas!$A$19:$E$23,3,0)*D17*B17^2) -> --- | J17: 20 | K17: =L17-Z17 -> 21 | L17: 25 | M17: =IF(NOT(ISNUMBER(H17)),"---",IF(H17<=0,"---",IF(H17*100/(Datos_vigas!$B$8*J17*K17^2*Datos_vigas!$B$5)>=0.5,"REVISAR",MAX((1-SQRT(1-2*H17*100/(Datos_vigas!$B$8*J17*K17^2*Datos_vigas!$B$5)))*J17*K17*Datos_vigas!$B$5/Datos_vigas!$B$6,0.0033*J17*K17)))) -> 2.2178054 | N17: 2 | O17: 12 | P17: =IF(NOT(ISNUMBER(I17)),"---",IF(I17<=0,"---",IF(I17*100/(Datos_vigas!$B$8*J17*K17^2*Datos_vigas!$B$5)>=0.5,"REVISAR",MAX((1-SQRT(1-2*I17*100/(Datos_vigas!$B$8*J17*K17^2*Datos_vigas!$B$5)))*J17*K17*Datos_vigas!$B$5/Datos_vigas!$B$6,0.0033*J17*K17)))) -> --- | Q17: --- | R17: --- | S17: =F17/(J17*0.85*K17) -> 5.3382353 | T17: =G17/(J17*0.85*K17) -> 5.3382353 | U17: 6 | V17: 10 | W17: =IF(OR(M17="REVISAR",P17="REVISAR"),"SECCION INSUF.",IF(NOT(AND(M17<>"REVISAR",P17<>"REVISAR",IF(ISNUMBER(M17),N17*PI()*(O17/10)^2/4>=M17,TRUE()),IF(ISNUMBER(P17),Q17*PI()*(R17/10)^2/4>=P17,TRUE()),IF(ISNUMBER(M17),M17<=0.0163*J17*K17,TRUE()),IF(ISNUMBER(P17),P17<=0.0163*J17*K17,TRUE()))),"NO VERIFICA FLEX.",IF(NOT(F17<=Datos_vigas!$B$9*(0.53*SQRT(Datos_vigas!$B$5)*J17*K17+2*PI()*(U17/10)^2/4*Datos_vigas!$B$6*K17/V17)),"NO VERIF. CORTE","VERIFICA"))) -> VERIFICA | Y17: 3.15 | Z17: 4
A18: VF08 | B18: 2.04 | C18: Simplemente apoyada | D18: =1.2*(Datos_vigas!$B$7*J18*L18/10000+Datos_vigas!$B$16*Y18) -> 1197 | F18: =VLOOKUP(C18,Datos_vigas!$A$19:$E$23,4,0)*D18*B18 -> 1220.94 | G18: =F18 -> 1220.94 | H18: =VLOOKUP(C18,Datos_vigas!$A$19:$E$23,2,0)*D18*B18^2 -> 622.6794 | I18: =IF(VLOOKUP(C18,Datos_vigas!$A$19:$E$23,3,0)=0,"---",VLOOKUP(C18,Datos_vigas!$A$19:$E$23,3,0)*D18*B18^2) -> --- | J18: 25 | K18: =L18-Z18 -> 31 | L18: 35 | M18: =IF(NOT(ISNUMBER(H18)),"---",IF(H18<=0,"---",IF(H18*100/(Datos_vigas!$B$8*J18*K18^2*Datos_vigas!$B$5)>=0.5,"REVISAR",MAX((1-SQRT(1-2*H18*100/(Datos_vigas!$B$8*J18*K18^2*Datos_vigas!$B$5)))*J18*K18*Datos_vigas!$B$5/Datos_vigas!$B$6,0.0033*J18*K18)))) -> 2.5575 | N18: 6 | O18: 8 | P18: =IF(NOT(ISNUMBER(I18)),"---",IF(I18<=0,"---",IF(I18*100/(Datos_vigas!$B$8*J18*K18^2*Datos_vigas!$B$5)>=0.5,"REVISAR",MAX((1-SQRT(1-2*I18*100/(Datos_vigas!$B$8*J18*K18^2*Datos_vigas!$B$5)))*J18*K18*Datos_vigas!$B$5/Datos_vigas!$B$6,0.0033*J18*K18)))) -> --- | Q18: --- | R18: --- | S18: =F18/(J18*0.85*K18) -> 1.8534194 | T18: =G18/(J18*0.85*K18) -> 1.8534194 | U18: 6 | V18: 15 | W18: =IF(OR(M18="REVISAR",P18="REVISAR"),"SECCION INSUF.",IF(NOT(AND(M18<>"REVISAR",P18<>"REVISAR",IF(ISNUMBER(M18),N18*PI()*(O18/10)^2/4>=M18,TRUE()),IF(ISNUMBER(P18),Q18*PI()*(R18/10)^2/4>=P18,TRUE()),IF(ISNUMBER(M18),M18<=0.0163*J18*K18,TRUE()),IF(ISNUMBER(P18),P18<=0.0163*J18*K18,TRUE()))),"NO VERIFICA FLEX.",IF(NOT(F18<=Datos_vigas!$B$9*(0.53*SQRT(Datos_vigas!$B$5)*J18*K18+2*PI()*(U18/10)^2/4*Datos_vigas!$B$6*K18/V18)),"NO VERIF. CORTE","VERIFICA"))) -> VERIFICA | X18: Longitud total 3.50 m. La luz de calculo es la mayor entre pilotes, deducida de la posicion de los pilotes dibujados en el plano. | Y18: 3.15 | Z18: 4
A19: VF09 (1) | B19: 0.7 | C19: Continua | D19: =1.2*(Datos_vigas!$B$7*J19*L19/10000+Datos_vigas!$B$16*Y19) -> 1197 | F19: =VLOOKUP(C19,Datos_vigas!$A$19:$E$23,4,0)*D19*B19 -> 481.7925 | G19: =F19 -> 481.7925 | H19: =VLOOKUP(C19,Datos_vigas!$A$19:$E$23,2,0)*D19*B19^2 -> 41.895838 | I19: =IF(VLOOKUP(C19,Datos_vigas!$A$19:$E$23,3,0)=0,"---",VLOOKUP(C19,Datos_vigas!$A$19:$E$23,3,0)*D19*B19^2) -> 58.653 | J19: 25 | K19: =L19-Z19 -> 31 | L19: 35 | M19: =IF(NOT(ISNUMBER(H19)),"---",IF(H19<=0,"---",IF(H19*100/(Datos_vigas!$B$8*J19*K19^2*Datos_vigas!$B$5)>=0.5,"REVISAR",MAX((1-SQRT(1-2*H19*100/(Datos_vigas!$B$8*J19*K19^2*Datos_vigas!$B$5)))*J19*K19*Datos_vigas!$B$5/Datos_vigas!$B$6,0.0033*J19*K19)))) -> 2.5575 | N19: 6 | O19: 8 | P19: =IF(NOT(ISNUMBER(I19)),"---",IF(I19<=0,"---",IF(I19*100/(Datos_vigas!$B$8*J19*K19^2*Datos_vigas!$B$5)>=0.5,"REVISAR",MAX((1-SQRT(1-2*I19*100/(Datos_vigas!$B$8*J19*K19^2*Datos_vigas!$B$5)))*J19*K19*Datos_vigas!$B$5/Datos_vigas!$B$6,0.0033*J19*K19)))) -> 2.5575 | Q19: 6 | R19: 8 | S19: =F19/(J19*0.85*K19) -> 0.73137381 | T19: =G19/(J19*0.85*K19) -> 0.73137381 | U19: 6 | V19: 15 | W19: =IF(OR(M19="REVISAR",P19="REVISAR"),"SECCION INSUF.",IF(NOT(AND(M19<>"REVISAR",P19<>"REVISAR",IF(ISNUMBER(M19),N19*PI()*(O19/10)^2/4>=M19,TRUE()),IF(ISNUMBER(P19),Q19*PI()*(R19/10)^2/4>=P19,TRUE()),IF(ISNUMBER(M19),M19<=0.0163*J19*K19,TRUE()),IF(ISNUMBER(P19),P19<=0.0163*J19*K19,TRUE()))),"NO VERIFICA FLEX.",IF(NOT(F19<=Datos_vigas!$B$9*(0.53*SQRT(Datos_vigas!$B$5)*J19*K19+2*PI()*(U19/10)^2/4*Datos_vigas!$B$6*K19/V19)),"NO VERIF. CORTE","VERIFICA"))) -> VERIFICA | Y19: 3.15 | Z19: 4
A20: VF09 (2) | B20: 0.7 | C20: Continua | D20: =1.2*(Datos_vigas!$B$7*J20*L20/10000+Datos_vigas!$B$16*Y20) -> 1197 | F20: =VLOOKUP(C20,Datos_vigas!$A$19:$E$23,4,0)*D20*B20 -> 481.7925 | G20: =F20 -> 481.7925 | H20: =VLOOKUP(C20,Datos_vigas!$A$19:$E$23,2,0)*D20*B20^2 -> 41.895838 | I20: =IF(VLOOKUP(C20,Datos_vigas!$A$19:$E$23,3,0)=0,"---",VLOOKUP(C20,Datos_vigas!$A$19:$E$23,3,0)*D20*B20^2) -> 58.653 | J20: 25 | K20: =L20-Z20 -> 31 | L20: 35 | M20: =IF(NOT(ISNUMBER(H20)),"---",IF(H20<=0,"---",IF(H20*100/(Datos_vigas!$B$8*J20*K20^2*Datos_vigas!$B$5)>=0.5,"REVISAR",MAX((1-SQRT(1-2*H20*100/(Datos_vigas!$B$8*J20*K20^2*Datos_vigas!$B$5)))*J20*K20*Datos_vigas!$B$5/Datos_vigas!$B$6,0.0033*J20*K20)))) -> 2.5575 | N20: 6 | O20: 8 | P20: =IF(NOT(ISNUMBER(I20)),"---",IF(I20<=0,"---",IF(I20*100/(Datos_vigas!$B$8*J20*K20^2*Datos_vigas!$B$5)>=0.5,"REVISAR",MAX((1-SQRT(1-2*I20*100/(Datos_vigas!$B$8*J20*K20^2*Datos_vigas!$B$5)))*J20*K20*Datos_vigas!$B$5/Datos_vigas!$B$6,0.0033*J20*K20)))) -> 2.5575 | Q20: 6 | R20: 8 | S20: =F20/(J20*0.85*K20) -> 0.73137381 | T20: =G20/(J20*0.85*K20) -> 0.73137381 | U20: 6 | V20: 15 | W20: =IF(OR(M20="REVISAR",P20="REVISAR"),"SECCION INSUF.",IF(NOT(AND(M20<>"REVISAR",P20<>"REVISAR",IF(ISNUMBER(M20),N20*PI()*(O20/10)^2/4>=M20,TRUE()),IF(ISNUMBER(P20),Q20*PI()*(R20/10)^2/4>=P20,TRUE()),IF(ISNUMBER(M20),M20<=0.0163*J20*K20,TRUE()),IF(ISNUMBER(P20),P20<=0.0163*J20*K20,TRUE()))),"NO VERIFICA FLEX.",IF(NOT(F20<=Datos_vigas!$B$9*(0.53*SQRT(Datos_vigas!$B$5)*J20*K20+2*PI()*(U20/10)^2/4*Datos_vigas!$B$6*K20/V20)),"NO VERIF. CORTE","VERIFICA"))) -> VERIFICA | Y20: 3.15 | Z20: 4
A21: VF10a | B21: 2.74 | C21: Continua | D21: =1.2*(Datos_vigas!$B$7*J21*L21/10000+Datos_vigas!$B$16*Y21) -> 1146.6 | F21: =VLOOKUP(C21,Datos_vigas!$A$19:$E$23,4,0)*D21*B21 -> 1806.4683 | G21: =F21 -> 1806.4683 | H21: =VLOOKUP(C21,Datos_vigas!$A$19:$E$23,2,0)*D21*B21^2 -> 614.88474 | I21: =IF(VLOOKUP(C21,Datos_vigas!$A$19:$E$23,3,0)=0,"---",VLOOKUP(C21,Datos_vigas!$A$19:$E$23,3,0)*D21*B21^2) -> 860.82142 | J21: 20 | K21: =L21-Z21 -> 31 | L21: 35 | M21: =IF(NOT(ISNUMBER(H21)),"---",IF(H21<=0,"---",IF(H21*100/(Datos_vigas!$B$8*J21*K21^2*Datos_vigas!$B$5)>=0.5,"REVISAR",MAX((1-SQRT(1-2*H21*100/(Datos_vigas!$B$8*J21*K21^2*Datos_vigas!$B$5)))*J21*K21*Datos_vigas!$B$5/Datos_vigas!$B$6,0.0033*J21*K21)))) -> 2.046 | N21: 2 | O21: 12 | P21: =IF(NOT(ISNUMBER(I21)),"---",IF(I21<=0,"---",IF(I21*100/(Datos_vigas!$B$8*J21*K21^2*Datos_vigas!$B$5)>=0.5,"REVISAR",MAX((1-SQRT(1-2*I21*100/(Datos_vigas!$B$8*J21*K21^2*Datos_vigas!$B$5)))*J21*K21*Datos_vigas!$B$5/Datos_vigas!$B$6,0.0033*J21*K21)))) -> 2.046 | Q21: 2 | R21: 12 | S21: =F21/(J21*0.85*K21) -> 3.4278336 | T21: =G21/(J21*0.85*K21) -> 3.4278336 | U21: 6 | V21: 15 | W21: =IF(OR(M21="REVISAR",P21="REVISAR"),"SECCION INSUF.",IF(NOT(AND(M21<>"REVISAR",P21<>"REVISAR",IF(ISNUMBER(M21),N21*PI()*(O21/10)^2/4>=M21,TRUE()),IF(ISNUMBER(P21),Q21*PI()*(R21/10)^2/4>=P21,TRUE()),IF(ISNUMBER(M21),M21<=0.0163*J21*K21,TRUE()),IF(ISNUMBER(P21),P21<=0.0163*J21*K21,TRUE()))),"NO VERIFICA FLEX.",IF(NOT(F21<=Datos_vigas!$B$9*(0.53*SQRT(Datos_vigas!$B$5)*J21*K21+2*PI()*(U21/10)^2/4*Datos_vigas!$B$6*K21/V21)),"NO VERIF. CORTE","VERIFICA"))) -> VERIFICA | X21: Longitud total 3.36 m. La luz de calculo es la mayor entre pilotes, deducida de la posicion de los pilotes dibujados en el plano. | Y21: 3.15 | Z21: 4
A22: VF10b | B22: 2.36 | C22: Continua | D22: =1.2*(Datos_vigas!$B$7*J22*L22/10000+Datos_vigas!$B$16*Y22) -> 1166.76 | F22: =VLOOKUP(C22,Datos_vigas!$A$19:$E$23,4,0)*D22*B22 -> 1583.2933 | G22: =F22 -> 1583.2933 | H22: =VLOOKUP(C22,Datos_vigas!$A$19:$E$23,2,0)*D22*B22^2 -> 464.17975 | I22: =IF(VLOOKUP(C22,Datos_vigas!$A$19:$E$23,3,0)=0,"---",VLOOKUP(C22,Datos_vigas!$A$19:$E$23,3,0)*D22*B22^2) -> 649.83865 | J22: 22 | K22: =L22-Z22 -> 31 | L22: 35 | M22: =IF(NOT(ISNUMBER(H22)),"---",IF(H22<=0,"---",IF(H22*100/(Datos_vigas!$B$8*J22*K22^2*Datos_vigas!$B$5)>=0.5,"REVISAR",MAX((1-SQRT(1-2*H22*100/(Datos_vigas!$B$8*J22*K22^2*Datos_vigas!$B$5)))*J22*K22*Datos_vigas!$B$5/Datos_vigas!$B$6,0.0033*J22*K22)))) -> 2.2506 | N22: 2 | O22: 12 | P22: =IF(NOT(ISNUMBER(I22)),"---",IF(I22<=0,"---",IF(I22*100/(Datos_vigas!$B$8*J22*K22^2*Datos_vigas!$B$5)>=0.5,"REVISAR",MAX((1-SQRT(1-2*I22*100/(Datos_vigas!$B$8*J22*K22^2*Datos_vigas!$B$5)))*J22*K22*Datos_vigas!$B$5/Datos_vigas!$B$6,0.0033*J22*K22)))) -> 2.2506 | Q22: 2 | R22: 12 | S22: =F22/(J22*0.85*K22) -> 2.7312288 | T22: =G22/(J22*0.85*K22) -> 2.7312288 | U22: 6 | V22: 15 | W22: =IF(OR(M22="REVISAR",P22="REVISAR"),"SECCION INSUF.",IF(NOT(AND(M22<>"REVISAR",P22<>"REVISAR",IF(ISNUMBER(M22),N22*PI()*(O22/10)^2/4>=M22,TRUE()),IF(ISNUMBER(P22),Q22*PI()*(R22/10)^2/4>=P22,TRUE()),IF(ISNUMBER(M22),M22<=0.0163*J22*K22,TRUE()),IF(ISNUMBER(P22),P22<=0.0163*J22*K22,TRUE()))),"NO VERIFICA FLEX.",IF(NOT(F22<=Datos_vigas!$B$9*(0.53*SQRT(Datos_vigas!$B$5)*J22*K22+2*PI()*(U22/10)^2/4*Datos_vigas!$B$6*K22/V22)),"NO VERIF. CORTE","VERIFICA"))) -> VERIFICA | X22: Longitud total 3.26 m. La luz de calculo es la mayor entre pilotes, deducida de la posicion de los pilotes dibujados en el plano. | Y22: 3.15 | Z22: 4
A23: VF10c | B23: 5.1 | C23: Continua | D23: =1.2*(Datos_vigas!$B$7*J23*L23/10000+Datos_vigas!$B$16*Y23) -> 1197 | F23: =VLOOKUP(C23,Datos_vigas!$A$19:$E$23,4,0)*D23*B23 -> 3510.2025 | G23: =F23 -> 3510.2025 | H23: =VLOOKUP(C23,Datos_vigas!$A$19:$E$23,2,0)*D23*B23^2 -> 2223.8995 | I23: =IF(VLOOKUP(C23,Datos_vigas!$A$19:$E$23,3,0)=0,"---",VLOOKUP(C23,Datos_vigas!$A$19:$E$23,3,0)*D23*B23^2) -> 3113.397 | J23: 25 | K23: =L23-Z23 -> 31 | L23: 35 | M23: =IF(NOT(ISNUMBER(H23)),"---",IF(H23<=0,"---",IF(H23*100/(Datos_vigas!$B$8*J23*K23^2*Datos_vigas!$B$5)>=0.5,"REVISAR",MAX((1-SQRT(1-2*H23*100/(Datos_vigas!$B$8*J23*K23^2*Datos_vigas!$B$5)))*J23*K23*Datos_vigas!$B$5/Datos_vigas!$B$6,0.0033*J23*K23)))) -> 2.5575 | N23: 6 | O23: 8 | P23: =IF(NOT(ISNUMBER(I23)),"---",IF(I23<=0,"---",IF(I23*100/(Datos_vigas!$B$8*J23*K23^2*Datos_vigas!$B$5)>=0.5,"REVISAR",MAX((1-SQRT(1-2*I23*100/(Datos_vigas!$B$8*J23*K23^2*Datos_vigas!$B$5)))*J23*K23*Datos_vigas!$B$5/Datos_vigas!$B$6,0.0033*J23*K23)))) -> 2.7548614 | Q23: 6 | R23: 8 | S23: =F23/(J23*0.85*K23) -> 5.3285806 | T23: =G23/(J23*0.85*K23) -> 5.3285806 | U23: 6 | V23: 15 | W23: =IF(OR(M23="REVISAR",P23="REVISAR"),"SECCION INSUF.",IF(NOT(AND(M23<>"REVISAR",P23<>"REVISAR",IF(ISNUMBER(M23),N23*PI()*(O23/10)^2/4>=M23,TRUE()),IF(ISNUMBER(P23),Q23*PI()*(R23/10)^2/4>=P23,TRUE()),IF(ISNUMBER(M23),M23<=0.0163*J23*K23,TRUE()),IF(ISNUMBER(P23),P23<=0.0163*J23*K23,TRUE()))),"NO VERIFICA FLEX.",IF(NOT(F23<=Datos_vigas!$B$9*(0.53*SQRT(Datos_vigas!$B$5)*J23*K23+2*PI()*(U23/10)^2/4*Datos_vigas!$B$6*K23/V23)),"NO VERIF. CORTE","VERIFICA"))) -> VERIFICA | X23: Longitud total 8.03 m. La luz de calculo es la mayor entre pilotes, deducida de la posicion de los pilotes dibujados en el plano. | Y23: 3.15 | Z23: 4
A24: VF11 | B24: 4.03 | C24: Simplemente apoyada | D24: =1.2*(Datos_vigas!$B$7*J24*L24/10000+Datos_vigas!$B$16*Y24) -> 1089 | F24: =VLOOKUP(C24,Datos_vigas!$A$19:$E$23,4,0)*D24*B24 -> 2194.335 | G24: =F24 -> 2194.335 | H24: =VLOOKUP(C24,Datos_vigas!$A$19:$E$23,2,0)*D24*B24^2 -> 2210.7925 | I24: =IF(VLOOKUP(C24,Datos_vigas!$A$19:$E$23,3,0)=0,"---",VLOOKUP(C24,Datos_vigas!$A$19:$E$23,3,0)*D24*B24^2) -> --- | J24: 20 | K24: =L24-Z24 -> 21 | L24: 25 | M24: =IF(NOT(ISNUMBER(H24)),"---",IF(H24<=0,"---",IF(H24*100/(Datos_vigas!$B$8*J24*K24^2*Datos_vigas!$B$5)>=0.5,"REVISAR",MAX((1-SQRT(1-2*H24*100/(Datos_vigas!$B$8*J24*K24^2*Datos_vigas!$B$5)))*J24*K24*Datos_vigas!$B$5/Datos_vigas!$B$6,0.0033*J24*K24)))) -> 2.9992541 | N24: 4 | O24: 10 | P24: =IF(NOT(ISNUMBER(I24)),"---",IF(I24<=0,"---",IF(I24*100/(Datos_vigas!$B$8*J24*K24^2*Datos_vigas!$B$5)>=0.5,"REVISAR",MAX((1-SQRT(1-2*I24*100/(Datos_vigas!$B$8*J24*K24^2*Datos_vigas!$B$5)))*J24*K24*Datos_vigas!$B$5/Datos_vigas!$B$6,0.0033*J24*K24)))) -> --- | Q24: --- | R24: --- | S24: =F24/(J24*0.85*K24) -> 6.1465966 | T24: =G24/(J24*0.85*K24) -> 6.1465966 | U24: 6 | V24: 10 | W24: =IF(OR(M24="REVISAR",P24="REVISAR"),"SECCION INSUF.",IF(NOT(AND(M24<>"REVISAR",P24<>"REVISAR",IF(ISNUMBER(M24),N24*PI()*(O24/10)^2/4>=M24,TRUE()),IF(ISNUMBER(P24),Q24*PI()*(R24/10)^2/4>=P24,TRUE()),IF(ISNUMBER(M24),M24<=0.0163*J24*K24,TRUE()),IF(ISNUMBER(P24),P24<=0.0163*J24*K24,TRUE()))),"NO VERIFICA FLEX.",IF(NOT(F24<=Datos_vigas!$B$9*(0.53*SQRT(Datos_vigas!$B$5)*J24*K24+2*PI()*(U24/10)^2/4*Datos_vigas!$B$6*K24/V24)),"NO VERIF. CORTE","VERIFICA"))) -> VERIFICA | X24: Relacion luz/altura alta. En una viga de fundacion enterrada la flecha no suele gobernar, por eso no se la incluye en la verificacion. | Y24: 3.15 | Z24: 4
A25: VF12 | B25: 1.49 | C25: Simplemente apoyada | D25: =1.2*(Datos_vigas!$B$7*J25*L25/10000+Datos_vigas!$B$16*Y25) -> 1053 | F25: =VLOOKUP(C25,Datos_vigas!$A$19:$E$23,4,0)*D25*B25 -> 784.485 | G25: =F25 -> 784.485 | H25: =VLOOKUP(C25,Datos_vigas!$A$19:$E$23,2,0)*D25*B25^2 -> 292.22066 | I25: =IF(VLOOKUP(C25,Datos_vigas!$A$19:$E$23,3,0)=0,"---",VLOOKUP(C25,Datos_vigas!$A$19:$E$23,3,0)*D25*B25^2) -> --- | J25: 15 | K25: =L25-Z25 -> 21 | L25: 25 | M25: =IF(NOT(ISNUMBER(H25)),"---",IF(H25<=0,"---",IF(H25*100/(Datos_vigas!$B$8*J25*K25^2*Datos_vigas!$B$5)>=0.5,"REVISAR",MAX((1-SQRT(1-2*H25*100/(Datos_vigas!$B$8*J25*K25^2*Datos_vigas!$B$5)))*J25*K25*Datos_vigas!$B$5/Datos_vigas!$B$6,0.0033*J25*K25)))) -> 1.0395 | N25: 3 | O25: 8 | P25: =IF(NOT(ISNUMBER(I25)),"---",IF(I25<=0,"---",IF(I25*100/(Datos_vigas!$B$8*J25*K25^2*Datos_vigas!$B$5)>=0.5,"REVISAR",MAX((1-SQRT(1-2*I25*100/(Datos_vigas!$B$8*J25*K25^2*Datos_vigas!$B$5)))*J25*K25*Datos_vigas!$B$5/Datos_vigas!$B$6,0.0033*J25*K25)))) -> --- | Q25: --- | R25: --- | S25: =F25/(J25*0.85*K25) -> 2.929916 | T25: =G25/(J25*0.85*K25) -> 2.929916 | U25: 6 | V25: 10 | W25: =IF(OR(M25="REVISAR",P25="REVISAR"),"SECCION INSUF.",IF(NOT(AND(M25<>"REVISAR",P25<>"REVISAR",IF(ISNUMBER(M25),N25*PI()*(O25/10)^2/4>=M25,TRUE()),IF(ISNUMBER(P25),Q25*PI()*(R25/10)^2/4>=P25,TRUE()),IF(ISNUMBER(M25),M25<=0.0163*J25*K25,TRUE()),IF(ISNUMBER(P25),P25<=0.0163*J25*K25,TRUE()))),"NO VERIFICA FLEX.",IF(NOT(F25<=Datos_vigas!$B$9*(0.53*SQRT(Datos_vigas!$B$5)*J25*K25+2*PI()*(U25/10)^2/4*Datos_vigas!$B$6*K25/V25)),"NO VERIF. CORTE","VERIFICA"))) -> VERIFICA | Y25: 3.15 | Z25: 4
A26: VF13 | B26: 2.28 | C26: Simplemente apoyada | D26: =1.2*(Datos_vigas!$B$7*J26*L26/10000+Datos_vigas!$B$16*Y26) -> 1053 | F26: =VLOOKUP(C26,Datos_vigas!$A$19:$E$23,4,0)*D26*B26 -> 1200.42 | G26: =F26 -> 1200.42 | H26: =VLOOKUP(C26,Datos_vigas!$A$19:$E$23,2,0)*D26*B26^2 -> 684.2394 | I26: =IF(VLOOKUP(C26,Datos_vigas!$A$19:$E$23,3,0)=0,"---",VLOOKUP(C26,Datos_vigas!$A$19:$E$23,3,0)*D26*B26^2) -> --- | J26: 15 | K26: =L26-Z26 -> 21 | L26: 25 | M26: =IF(NOT(ISNUMBER(H26)),"---",IF(H26<=0,"---",IF(H26*100/(Datos_vigas!$B$8*J26*K26^2*Datos_vigas!$B$5)>=0.5,"REVISAR",MAX((1-SQRT(1-2*H26*100/(Datos_vigas!$B$8*J26*K26^2*Datos_vigas!$B$5)))*J26*K26*Datos_vigas!$B$5/Datos_vigas!$B$6,0.0033*J26*K26)))) -> 1.0395 | N26: 3 | O26: 8 | P26: =IF(NOT(ISNUMBER(I26)),"---",IF(I26<=0,"---",IF(I26*100/(Datos_vigas!$B$8*J26*K26^2*Datos_vigas!$B$5)>=0.5,"REVISAR",MAX((1-SQRT(1-2*I26*100/(Datos_vigas!$B$8*J26*K26^2*Datos_vigas!$B$5)))*J26*K26*Datos_vigas!$B$5/Datos_vigas!$B$6,0.0033*J26*K26)))) -> --- | Q26: --- | R26: --- | S26: =F26/(J26*0.85*K26) -> 4.4833613 | T26: =G26/(J26*0.85*K26) -> 4.4833613 | U26: 6 | V26: 10 | W26: =IF(OR(M26="REVISAR",P26="REVISAR"),"SECCION INSUF.",IF(NOT(AND(M26<>"REVISAR",P26<>"REVISAR",IF(ISNUMBER(M26),N26*PI()*(O26/10)^2/4>=M26,TRUE()),IF(ISNUMBER(P26),Q26*PI()*(R26/10)^2/4>=P26,TRUE()),IF(ISNUMBER(M26),M26<=0.0163*J26*K26,TRUE()),IF(ISNUMBER(P26),P26<=0.0163*J26*K26,TRUE()))),"NO VERIFICA FLEX.",IF(NOT(F26<=Datos_vigas!$B$9*(0.53*SQRT(Datos_vigas!$B$5)*J26*K26+2*PI()*(U26/10)^2/4*Datos_vigas!$B$6*K26/V26)),"NO VERIF. CORTE","VERIFICA"))) -> VERIFICA | Y26: 3.15 | Z26: 4
A27: VF14 | B27: 3.09 | C27: Simplemente apoyada | D27: =1.2*(Datos_vigas!$B$7*J27*L27/10000+Datos_vigas!$B$16*Y27) -> 1233 | F27: =VLOOKUP(C27,Datos_vigas!$A$19:$E$23,4,0)*D27*B27 -> 1904.985 | G27: =F27 -> 1904.985 | H27: =VLOOKUP(C27,Datos_vigas!$A$19:$E$23,2,0)*D27*B27^2 -> 1471.6009 | I27: =IF(VLOOKUP(C27,Datos_vigas!$A$19:$E$23,3,0)=0,"---",VLOOKUP(C27,Datos_vigas!$A$19:$E$23,3,0)*D27*B27^2) -> --- | J27: 25 | K27: =L27-Z27 -> 36 | L27: 40 | M27: =IF(NOT(ISNUMBER(H27)),"---",IF(H27<=0,"---",IF(H27*100/(Datos_vigas!$B$8*J27*K27^2*Datos_vigas!$B$5)>=0.5,"REVISAR",MAX((1-SQRT(1-2*H27*100/(Datos_vigas!$B$8*J27*K27^2*Datos_vigas!$B$5)))*J27*K27*Datos_vigas!$B$5/Datos_vigas!$B$6,0.0033*J27*K27)))) -> 2.97 | N27: 6 | O27: 8 | P27: =IF(NOT(ISNUMBER(I27)),"---",IF(I27<=0,"---",IF(I27*100/(Datos_vigas!$B$8*J27*K27^2*Datos_vigas!$B$5)>=0.5,"REVISAR",MAX((1-SQRT(1-2*I27*100/(Datos_vigas!$B$8*J27*K27^2*Datos_vigas!$B$5)))*J27*K27*Datos_vigas!$B$5/Datos_vigas!$B$6,0.0033*J27*K27)))) -> --- | Q27: --- | R27: --- | S27: =F27/(J27*0.85*K27) -> 2.4901765 | T27: =G27/(J27*0.85*K27) -> 2.4901765 | U27: 6 | V27: 15 | W27: =IF(OR(M27="REVISAR",P27="REVISAR"),"SECCION INSUF.",IF(NOT(AND(M27<>"REVISAR",P27<>"REVISAR",IF(ISNUMBER(M27),N27*PI()*(O27/10)^2/4>=M27,TRUE()),IF(ISNUMBER(P27),Q27*PI()*(R27/10)^2/4>=P27,TRUE()),IF(ISNUMBER(M27),M27<=0.0163*J27*K27,TRUE()),IF(ISNUMBER(P27),P27<=0.0163*J27*K27,TRUE()))),"NO VERIFICA FLEX.",IF(NOT(F27<=Datos_vigas!$B$9*(0.53*SQRT(Datos_vigas!$B$5)*J27*K27+2*PI()*(U27/10)^2/4*Datos_vigas!$B$6*K27/V27)),"NO VERIF. CORTE","VERIFICA"))) -> VERIFICA | X27: Longitud total 8.75 m. La luz de calculo es la mayor entre pilotes, deducida de la posicion de los pilotes dibujados en el plano. | Y27: 3.15 | Z27: 4
A28: VF15 | B28: 2.39 | C28: Simplemente apoyada | D28: =1.2*(Datos_vigas!$B$7*J28*L28/10000+Datos_vigas!$B$16*Y28) -> 1089 | F28: =VLOOKUP(C28,Datos_vigas!$A$19:$E$23,4,0)*D28*B28 -> 1301.355 | G28: =F28 -> 1301.355 | H28: =VLOOKUP(C28,Datos_vigas!$A$19:$E$23,2,0)*D28*B28^2 -> 777.55961 | I28: =IF(VLOOKUP(C28,Datos_vigas!$A$19:$E$23,3,0)=0,"---",VLOOKUP(C28,Datos_vigas!$A$19:$E$23,3,0)*D28*B28^2) -> --- | J28: 20 | K28: =L28-Z28 -> 21 | L28: 25 | M28: =IF(NOT(ISNUMBER(H28)),"---",IF(H28<=0,"---",IF(H28*100/(Datos_vigas!$B$8*J28*K28^2*Datos_vigas!$B$5)>=0.5,"REVISAR",MAX((1-SQRT(1-2*H28*100/(Datos_vigas!$B$8*J28*K28^2*Datos_vigas!$B$5)))*J28*K28*Datos_vigas!$B$5/Datos_vigas!$B$6,0.0033*J28*K28)))) -> 1.386 | N28: 5 | O28: 6 | P28: =IF(NOT(ISNUMBER(I28)),"---",IF(I28<=0,"---",IF(I28*100/(Datos_vigas!$B$8*J28*K28^2*Datos_vigas!$B$5)>=0.5,"REVISAR",MAX((1-SQRT(1-2*I28*100/(Datos_vigas!$B$8*J28*K28^2*Datos_vigas!$B$5)))*J28*K28*Datos_vigas!$B$5/Datos_vigas!$B$6,0.0033*J28*K28)))) -> --- | Q28: --- | R28: --- | S28: =F28/(J28*0.85*K28) -> 3.6452521 | T28: =G28/(J28*0.85*K28) -> 3.6452521 | U28: 6 | V28: 10 | W28: =IF(OR(M28="REVISAR",P28="REVISAR"),"SECCION INSUF.",IF(NOT(AND(M28<>"REVISAR",P28<>"REVISAR",IF(ISNUMBER(M28),N28*PI()*(O28/10)^2/4>=M28,TRUE()),IF(ISNUMBER(P28),Q28*PI()*(R28/10)^2/4>=P28,TRUE()),IF(ISNUMBER(M28),M28<=0.0163*J28*K28,TRUE()),IF(ISNUMBER(P28),P28<=0.0163*J28*K28,TRUE()))),"NO VERIFICA FLEX.",IF(NOT(F28<=Datos_vigas!$B$9*(0.53*SQRT(Datos_vigas!$B$5)*J28*K28+2*PI()*(U28/10)^2/4*Datos_vigas!$B$6*K28/V28)),"NO VERIF. CORTE","VERIFICA"))) -> VERIFICA | Y28: 3.15 | Z28: 4
A29: VF16a | B29: 4.47 | C29: Continua | D29: =1.2*(Datos_vigas!$B$7*J29*L29/10000+Datos_vigas!$B$16*Y29) -> 1089 | F29: =VLOOKUP(C29,Datos_vigas!$A$19:$E$23,4,0)*D29*B29 -> 2799.0023 | G29: =F29 -> 2799.0023 | H29: =VLOOKUP(C29,Datos_vigas!$A$19:$E$23,2,0)*D29*B29^2 -> 1554.2597 | I29: =IF(VLOOKUP(C29,Datos_vigas!$A$19:$E$23,3,0)=0,"---",VLOOKUP(C29,Datos_vigas!$A$19:$E$23,3,0)*D29*B29^2) -> 2175.92 | J29: 20 | K29: =L29-Z29 -> 21 | L29: 25 | M29: =IF(NOT(ISNUMBER(H29)),"---",IF(H29<=0,"---",IF(H29*100/(Datos_vigas!$B$8*J29*K29^2*Datos_vigas!$B$5)>=0.5,"REVISAR",MAX((1-SQRT(1-2*H29*100/(Datos_vigas!$B$8*J29*K29^2*Datos_vigas!$B$5)))*J29*K29*Datos_vigas!$B$5/Datos_vigas!$B$6,0.0033*J29*K29)))) -> 2.0589325 | N29: 4 | O29: 8 | P29: =IF(NOT(ISNUMBER(I29)),"---",IF(I29<=0,"---",IF(I29*100/(Datos_vigas!$B$8*J29*K29^2*Datos_vigas!$B$5)>=0.5,"REVISAR",MAX((1-SQRT(1-2*I29*100/(Datos_vigas!$B$8*J29*K29^2*Datos_vigas!$B$5)))*J29*K29*Datos_vigas!$B$5/Datos_vigas!$B$6,0.0033*J29*K29)))) -> 2.9480761 | Q29: 4 | R29: 10 | S29: =F29/(J29*0.85*K29) -> 7.8403424 | T29: =G29/(J29*0.85*K29) -> 7.8403424 | U29: 6 | V29: 10 | W29: =IF(OR(M29="REVISAR",P29="REVISAR"),"SECCION INSUF.",IF(NOT(AND(M29<>"REVISAR",P29<>"REVISAR",IF(ISNUMBER(M29),N29*PI()*(O29/10)^2/4>=M29,TRUE()),IF(ISNUMBER(P29),Q29*PI()*(R29/10)^2/4>=P29,TRUE()),IF(ISNUMBER(M29),M29<=0.0163*J29*K29,TRUE()),IF(ISNUMBER(P29),P29<=0.0163*J29*K29,TRUE()))),"NO VERIFICA FLEX.",IF(NOT(F29<=Datos_vigas!$B$9*(0.53*SQRT(Datos_vigas!$B$5)*J29*K29+2*PI()*(U29/10)^2/4*Datos_vigas!$B$6*K29/V29)),"NO VERIF. CORTE","VERIFICA"))) -> NO VERIFICA FLEX. | X29: Longitud total 6.96 m. La luz de calculo es la mayor entre pilotes, deducida de la posicion de los pilotes dibujados en el plano. | Y29: 3.15 | Z29: 4
A30: VF16b | B30: 3.13 | C30: Continua | D30: =1.2*(Datos_vigas!$B$7*J30*L30/10000+Datos_vigas!$B$16*Y30) -> 1146.6 | F30: =VLOOKUP(C30,Datos_vigas!$A$19:$E$23,4,0)*D30*B30 -> 2063.5934 | G30: =F30 -> 2063.5934 | H30: =VLOOKUP(C30,Datos_vigas!$A$19:$E$23,2,0)*D30*B30^2 -> 802.38216 | I30: =IF(VLOOKUP(C30,Datos_vigas!$A$19:$E$23,3,0)=0,"---",VLOOKUP(C30,Datos_vigas!$A$19:$E$23,3,0)*D30*B30^2) -> 1123.3126 | J30: 20 | K30: =L30-Z30 -> 31 | L30: 35 | M30: =IF(NOT(ISNUMBER(H30)),"---",IF(H30<=0,"---",IF(H30*100/(Datos_vigas!$B$8*J30*K30^2*Datos_vigas!$B$5)>=0.5,"REVISAR",MAX((1-SQRT(1-2*H30*100/(Datos_vigas!$B$8*J30*K30^2*Datos_vigas!$B$5)))*J30*K30*Datos_vigas!$B$5/Datos_vigas!$B$6,0.0033*J30*K30)))) -> 2.046 | N30: 2 | O30: 12 | P30: =IF(NOT(ISNUMBER(I30)),"---",IF(I30<=0,"---",IF(I30*100/(Datos_vigas!$B$8*J30*K30^2*Datos_vigas!$B$5)>=0.5,"REVISAR",MAX((1-SQRT(1-2*I30*100/(Datos_vigas!$B$8*J30*K30^2*Datos_vigas!$B$5)))*J30*K30*Datos_vigas!$B$5/Datos_vigas!$B$6,0.0033*J30*K30)))) -> 2.046 | Q30: 2 | R30: 12 | S30: =F30/(J30*0.85*K30) -> 3.9157369 | T30: =G30/(J30*0.85*K30) -> 3.9157369 | U30: 6 | V30: 15 | W30: =IF(OR(M30="REVISAR",P30="REVISAR"),"SECCION INSUF.",IF(NOT(AND(M30<>"REVISAR",P30<>"REVISAR",IF(ISNUMBER(M30),N30*PI()*(O30/10)^2/4>=M30,TRUE()),IF(ISNUMBER(P30),Q30*PI()*(R30/10)^2/4>=P30,TRUE()),IF(ISNUMBER(M30),M30<=0.0163*J30*K30,TRUE()),IF(ISNUMBER(P30),P30<=0.0163*J30*K30,TRUE()))),"NO VERIFICA FLEX.",IF(NOT(F30<=Datos_vigas!$B$9*(0.53*SQRT(Datos_vigas!$B$5)*J30*K30+2*PI()*(U30/10)^2/4*Datos_vigas!$B$6*K30/V30)),"NO VERIF. CORTE","VERIFICA"))) -> VERIFICA | Y30: 3.15 | Z30: 4
A31: VF17 | B31: 3.53 | C31: Simplemente apoyada | D31: =1.2*(Datos_vigas!$B$7*J31*L31/10000+Datos_vigas!$B$16*Y31) -> 1089 | F31: =VLOOKUP(C31,Datos_vigas!$A$19:$E$23,4,0)*D31*B31 -> 1922.085 | G31: =F31 -> 1922.085 | H31: =VLOOKUP(C31,Datos_vigas!$A$19:$E$23,2,0)*D31*B31^2 -> 1696.24 | I31: =IF(VLOOKUP(C31,Datos_vigas!$A$19:$E$23,3,0)=0,"---",VLOOKUP(C31,Datos_vigas!$A$19:$E$23,3,0)*D31*B31^2) -> --- | J31: 20 | K31: =L31-Z31 -> 21 | L31: 25 | M31: =IF(NOT(ISNUMBER(H31)),"---",IF(H31<=0,"---",IF(H31*100/(Datos_vigas!$B$8*J31*K31^2*Datos_vigas!$B$5)>=0.5,"REVISAR",MAX((1-SQRT(1-2*H31*100/(Datos_vigas!$B$8*J31*K31^2*Datos_vigas!$B$5)))*J31*K31*Datos_vigas!$B$5/Datos_vigas!$B$6,0.0033*J31*K31)))) -> 2.2582858 | N31: 2 | O31: 12 | P31: =IF(NOT(ISNUMBER(I31)),"---",IF(I31<=0,"---",IF(I31*100/(Datos_vigas!$B$8*J31*K31^2*Datos_vigas!$B$5)>=0.5,"REVISAR",MAX((1-SQRT(1-2*I31*100/(Datos_vigas!$B$8*J31*K31^2*Datos_vigas!$B$5)))*J31*K31*Datos_vigas!$B$5/Datos_vigas!$B$6,0.0033*J31*K31)))) -> --- | Q31: --- | R31: --- | S31: =F31/(J31*0.85*K31) -> 5.3839916 | T31: =G31/(J31*0.85*K31) -> 5.3839916 | U31: 6 | V31: 10 | W31: =IF(OR(M31="REVISAR",P31="REVISAR"),"SECCION INSUF.",IF(NOT(AND(M31<>"REVISAR",P31<>"REVISAR",IF(ISNUMBER(M31),N31*PI()*(O31/10)^2/4>=M31,TRUE()),IF(ISNUMBER(P31),Q31*PI()*(R31/10)^2/4>=P31,TRUE()),IF(ISNUMBER(M31),M31<=0.0163*J31*K31,TRUE()),IF(ISNUMBER(P31),P31<=0.0163*J31*K31,TRUE()))),"NO VERIFICA FLEX.",IF(NOT(F31<=Datos_vigas!$B$9*(0.53*SQRT(Datos_vigas!$B$5)*J31*K31+2*PI()*(U31/10)^2/4*Datos_vigas!$B$6*K31/V31)),"NO VERIF. CORTE","VERIFICA"))) -> VERIFICA | Y31: 3.15 | Z31: 4
A32: VF18a | B32: 5.5 | C32: Continua | D32: =1.2*(Datos_vigas!$B$7*J32*L32/10000+Datos_vigas!$B$16*Y32) -> 1197 | F32: =VLOOKUP(C32,Datos_vigas!$A$19:$E$23,4,0)*D32*B32 -> 3785.5125 | G32: =F32 -> 3785.5125 | H32: =VLOOKUP(C32,Datos_vigas!$A$19:$E$23,2,0)*D32*B32^2 -> 2586.4267 | I32: =IF(VLOOKUP(C32,Datos_vigas!$A$19:$E$23,3,0)=0,"---",VLOOKUP(C32,Datos_vigas!$A$19:$E$23,3,0)*D32*B32^2) -> 3620.925 | J32: 25 | K32: =L32-Z32 -> 31 | L32: 35 | M32: =IF(NOT(ISNUMBER(H32)),"---",IF(H32<=0,"---",IF(H32*100/(Datos_vigas!$B$8*J32*K32^2*Datos_vigas!$B$5)>=0.5,"REVISAR",MAX((1-SQRT(1-2*H32*100/(Datos_vigas!$B$8*J32*K32^2*Datos_vigas!$B$5)))*J32*K32*Datos_vigas!$B$5/Datos_vigas!$B$6,0.0033*J32*K32)))) -> 2.5575 | N32: 6 | O32: 8 | P32: =IF(NOT(ISNUMBER(I32)),"---",IF(I32<=0,"---",IF(I32*100/(Datos_vigas!$B$8*J32*K32^2*Datos_vigas!$B$5)>=0.5,"REVISAR",MAX((1-SQRT(1-2*I32*100/(Datos_vigas!$B$8*J32*K32^2*Datos_vigas!$B$5)))*J32*K32*Datos_vigas!$B$5/Datos_vigas!$B$6,0.0033*J32*K32)))) -> 3.2241878 | Q32: 3 | R32: 12 | S32: =F32/(J32*0.85*K32) -> 5.7465085 | T32: =G32/(J32*0.85*K32) -> 5.7465085 | U32: 6 | V32: 15 | W32: =IF(OR(M32="REVISAR",P32="REVISAR"),"SECCION INSUF.",IF(NOT(AND(M32<>"REVISAR",P32<>"REVISAR",IF(ISNUMBER(M32),N32*PI()*(O32/10)^2/4>=M32,TRUE()),IF(ISNUMBER(P32),Q32*PI()*(R32/10)^2/4>=P32,TRUE()),IF(ISNUMBER(M32),M32<=0.0163*J32*K32,TRUE()),IF(ISNUMBER(P32),P32<=0.0163*J32*K32,TRUE()))),"NO VERIFICA FLEX.",IF(NOT(F32<=Datos_vigas!$B$9*(0.53*SQRT(Datos_vigas!$B$5)*J32*K32+2*PI()*(U32/10)^2/4*Datos_vigas!$B$6*K32/V32)),"NO VERIF. CORTE","VERIFICA"))) -> VERIFICA | X32: Longitud total 7.48 m. La luz de calculo es la mayor entre pilotes, deducida de la posicion de los pilotes dibujados en el plano. | Y32: 3.15 | Z32: 4
A33: VF18b | B33: 3.05 | C33: Continua | D33: =1.2*(Datos_vigas!$B$7*J33*L33/10000+Datos_vigas!$B$16*Y33) -> 1125 | F33: =VLOOKUP(C33,Datos_vigas!$A$19:$E$23,4,0)*D33*B33 -> 1972.9688 | G33: =F33 -> 1972.9688 | H33: =VLOOKUP(C33,Datos_vigas!$A$19:$E$23,2,0)*D33*B33^2 -> 747.53727 | I33: =IF(VLOOKUP(C33,Datos_vigas!$A$19:$E$23,3,0)=0,"---",VLOOKUP(C33,Datos_vigas!$A$19:$E$23,3,0)*D33*B33^2) -> 1046.5312 | J33: 25 | K33: =L33-Z33 -> 21 | L33: 25 | M33: =IF(NOT(ISNUMBER(H33)),"---",IF(H33<=0,"---",IF(H33*100/(Datos_vigas!$B$8*J33*K33^2*Datos_vigas!$B$5)>=0.5,"REVISAR",MAX((1-SQRT(1-2*H33*100/(Datos_vigas!$B$8*J33*K33^2*Datos_vigas!$B$5)))*J33*K33*Datos_vigas!$B$5/Datos_vigas!$B$6,0.0033*J33*K33)))) -> 1.7325 | N33: 4 | O33: 8 | P33: =IF(NOT(ISNUMBER(I33)),"---",IF(I33<=0,"---",IF(I33*100/(Datos_vigas!$B$8*J33*K33^2*Datos_vigas!$B$5)>=0.5,"REVISAR",MAX((1-SQRT(1-2*I33*100/(Datos_vigas!$B$8*J33*K33^2*Datos_vigas!$B$5)))*J33*K33*Datos_vigas!$B$5/Datos_vigas!$B$6,0.0033*J33*K33)))) -> 1.7325 | Q33: 4 | R33: 8 | S33: =F33/(J33*0.85*K33) -> 4.4212185 | T33: =G33/(J33*0.85*K33) -> 4.4212185 | U33: 6 | V33: 10 | W33: =IF(OR(M33="REVISAR",P33="REVISAR"),"SECCION INSUF.",IF(NOT(AND(M33<>"REVISAR",P33<>"REVISAR",IF(ISNUMBER(M33),N33*PI()*(O33/10)^2/4>=M33,TRUE()),IF(ISNUMBER(P33),Q33*PI()*(R33/10)^2/4>=P33,TRUE()),IF(ISNUMBER(M33),M33<=0.0163*J33*K33,TRUE()),IF(ISNUMBER(P33),P33<=0.0163*J33*K33,TRUE()))),"NO VERIFICA FLEX.",IF(NOT(F33<=Datos_vigas!$B$9*(0.53*SQRT(Datos_vigas!$B$5)*J33*K33+2*PI()*(U33/10)^2/4*Datos_vigas!$B$6*K33/V33)),"NO VERIF. CORTE","VERIFICA"))) -> VERIFICA | Y33: 3.15 | Z33: 4
A34: VF18c | B34: 4.26 | C34: Continua | D34: =1.2*(Datos_vigas!$B$7*J34*L34/10000+Datos_vigas!$B$16*Y34) -> 1146.6 | F34: =VLOOKUP(C34,Datos_vigas!$A$19:$E$23,4,0)*D34*B34 -> 2808.5967 | G34: =F34 -> 2808.5967 | H34: =VLOOKUP(C34,Datos_vigas!$A$19:$E$23,2,0)*D34*B34^2 -> 1486.3182 | I34: =IF(VLOOKUP(C34,Datos_vigas!$A$19:$E$23,3,0)=0,"---",VLOOKUP(C34,Datos_vigas!$A$19:$E$23,3,0)*D34*B34^2) -> 2080.8038 | J34: 20 | K34: =L34-Z34 -> 31 | L34: 35 | M34: =IF(NOT(ISNUMBER(H34)),"---",IF(H34<=0,"---",IF(H34*100/(Datos_vigas!$B$8*J34*K34^2*Datos_vigas!$B$5)>=0.5,"REVISAR",MAX((1-SQRT(1-2*H34*100/(Datos_vigas!$B$8*J34*K34^2*Datos_vigas!$B$5)))*J34*K34*Datos_vigas!$B$5/Datos_vigas!$B$6,0.0033*J34*K34)))) -> 2.046 | N34: 2 | O34: 12 | P34: =IF(NOT(ISNUMBER(I34)),"---",IF(I34<=0,"---",IF(I34*100/(Datos_vigas!$B$8*J34*K34^2*Datos_vigas!$B$5)>=0.5,"REVISAR",MAX((1-SQRT(1-2*I34*100/(Datos_vigas!$B$8*J34*K34^2*Datos_vigas!$B$5)))*J34*K34*Datos_vigas!$B$5/Datos_vigas!$B$6,0.0033*J34*K34)))) -> 2.046 | Q34: 2 | R34: 12 | S34: =F34/(J34*0.85*K34) -> 5.3294055 | T34: =G34/(J34*0.85*K34) -> 5.3294055 | U34: 6 | V34: 15 | W34: =IF(OR(M34="REVISAR",P34="REVISAR"),"SECCION INSUF.",IF(NOT(AND(M34<>"REVISAR",P34<>"REVISAR",IF(ISNUMBER(M34),N34*PI()*(O34/10)^2/4>=M34,TRUE()),IF(ISNUMBER(P34),Q34*PI()*(R34/10)^2/4>=P34,TRUE()),IF(ISNUMBER(M34),M34<=0.0163*J34*K34,TRUE()),IF(ISNUMBER(P34),P34<=0.0163*J34*K34,TRUE()))),"NO VERIFICA FLEX.",IF(NOT(F34<=Datos_vigas!$B$9*(0.53*SQRT(Datos_vigas!$B$5)*J34*K34+2*PI()*(U34/10)^2/4*Datos_vigas!$B$6*K34/V34)),"NO VERIF. CORTE","VERIFICA"))) -> VERIFICA | X34: Longitud total 4.82 m. La luz de calculo es la mayor entre pilotes, deducida de la posicion de los pilotes dibujados en el plano. | Y34: 3.15 | Z34: 4

Sheet Pilotes y cabezales
A1: PILOTES Y CABEZALES H°A° H-21 ACERO 42/50 TODOS LOS PILOTES Ø30 h = -4,50 m
A2: POSICION | B2: COLUMNA | C2: TIPO | D2: CABEZAL (cm) | G2: CARGA | I2: PILOTES | N2: VERIFICACION | O2: OBSERVACIONES
D3: A | E3: B | F3: h | G3: mayorada (t) | H3: servicio (t) | I3: cantidad | J3: o (cm) | K3: long. (m) | L3: carga c/u (t) | M3: admisible (t)
A4: CB1 | B4: C1 (15x30) | C4: CBZ 01 | D4: 70 | E4: 70 | F4: 65 | G4: 2.49 | H4: =IF(G4="","",G4/1.4) -> 1.7785714 | I4: 1 | J4: 30 | K4: 4.5 | L4: =IF(H4="","",H4/I4) -> 1.7785714 | M4: =Datos_pilotes!$B$4 -> 22 | N4: =IF(L4="","FALTA CARGA",IF(L4<=M4,"VERIFICA","NO VERIFICA")) -> VERIFICA | O4: Cantidad de pilotes deducida de la dimension del cabezal: 70x70 cm. Carga tomada de la bajada de la planilla de columnas, que esta incompleta: el valor real es mayor.
A5: CB2 | B5: C2 (15x30) | C5: CBZ 01 | D5: 70 | E5: 70 | F5: 65 | G5: 29.46 | H5: =IF(G5="","",G5/1.4) -> 21.042857 | I5: 1 | J5: 30 | K5: 4.5 | L5: =IF(H5="","",H5/I5) -> 21.042857 | M5: =Datos_pilotes!$B$4 -> 22 | N5: =IF(L5="","FALTA CARGA",IF(L5<=M5,"VERIFICA","NO VERIFICA")) -> VERIFICA | O5: Cantidad de pilotes deducida de la dimension del cabezal: 70x70 cm. Carga tomada de la bajada de la planilla de columnas, que esta incompleta: el valor real es mayor.
A6: CB3 | B6: C5 (15x30) | C6: CBZ 01 | D6: 70 | E6: 70 | F6: 65 | G6: 15.96 | H6: =IF(G6="","",G6/1.4) -> 11.4 | I6: 1 | J6: 30 | K6: 4.5 | L6: =IF(H6="","",H6/I6) -> 11.4 | M6: =Datos_pilotes!$B$4 -> 22 | N6: =IF(L6="","FALTA CARGA",IF(L6<=M6,"VERIFICA","NO VERIFICA")) -> VERIFICA | O6: Cantidad de pilotes deducida de la dimension del cabezal: 70x70 cm. Carga tomada de la bajada de la planilla de columnas, que esta incompleta: el valor real es mayor.
A7: CB4 | B7: C3 (30x15) | C7: CBZ 01 | D7: 70 | E7: 70 | F7: 65 | G7: 10.6 | H7: =IF(G7="","",G7/1.4) -> 7.5714286 | I7: 1 | J7: 30 | K7: 4.5 | L7: =IF(H7="","",H7/I7) -> 7.5714286 | M7: =Datos_pilotes!$B$4 -> 22 | N7: =IF(L7="","FALTA CARGA",IF(L7<=M7,"VERIFICA","NO VERIFICA")) -> VERIFICA | O7: Cantidad de pilotes deducida de la dimension del cabezal: 70x70 cm. Carga tomada de la bajada de la planilla de columnas, que esta incompleta: el valor real es mayor.
A8: CB5 | B8: C4 (10x10) | C8: CBZ 01 | D8: 70 | E8: 70 | F8: 65 | G8: 10.28 | H8: =IF(G8="","",G8/1.4) -> 7.3428571 | I8: 1 | J8: 30 | K8: 4.5 | L8: =IF(H8="","",H8/I8) -> 7.3428571 | M8: =Datos_pilotes!$B$4 -> 22 | N8: =IF(L8="","FALTA CARGA",IF(L8<=M8,"VERIFICA","NO VERIFICA")) -> VERIFICA | O8: Cantidad de pilotes deducida de la dimension del cabezal: 70x70 cm. Carga tomada de la bajada de la planilla de columnas, que esta incompleta: el valor real es mayor.
A9: CB6 | B9: C6 (20x20) | C9: CBZ 03 | D9: 144 | E9: 70 | F9: 70 | G9: 32.1 | H9: =IF(G9="","",G9/1.4) -> 22.928571 | I9: 3 | J9: 30 | K9: 4.5 | L9: =IF(H9="","",H9/I9) -> 7.6428571 | M9: =Datos_pilotes!$B$4 -> 22 | N9: =IF(L9="","FALTA CARGA",IF(L9<=M9,"VERIFICA","NO VERIFICA")) -> VERIFICA | O9: Cantidad de pilotes deducida de la dimension del cabezal: 144x70 cm. Tres pilotes, no dos: la planilla de armadura declara 8 pilotes bajo cabezales de 70 cm, que son un CBZ02 y dos CBZ03. Carga tomada de la bajada de la planilla de columnas, que esta incompleta: el valor real es mayor.
A10: CB7 | B10: C7 (30x15) | C10: CBZ 02 | D10: 129 | E10: 70 | F10: 70 | G10: 37.78 | H10: =IF(G10="","",G10/1.4) -> 26.985714 | I10: 2 | J10: 30 | K10: 4.5 | L10: =IF(H10="","",H10/I10) -> 13.492857 | M10: =Datos_pilotes!$B$4 -> 22 | N10: =IF(L10="","FALTA CARGA",IF(L10<=M10,"VERIFICA","NO VERIFICA")) -> VERIFICA | O10: Cantidad de pilotes deducida de la dimension del cabezal: 129x70 cm. El computo metrico declara un solo CBZ02 y en el plano aparecen dos rotulos. Verificar cual corresponde. Carga tomada de la bajada de la planilla de columnas, que esta incompleta: el valor real es mayor.
A11: CB8 | B11: C9 (15x30) | C11: CBZ 03 | D11: 144 | E11: 70 | F11: 70 | G11: 54.93 | H11: =IF(G11="","",G11/1.4) -> 39.235714 | I11: 3 | J11: 30 | K11: 4.5 | L11: =IF(H11="","",H11/I11) -> 13.078571 | M11: =Datos_pilotes!$B$4 -> 22 | N11: =IF(L11="","FALTA CARGA",IF(L11<=M11,"VERIFICA","NO VERIFICA")) -> VERIFICA | O11: Cantidad de pilotes deducida de la dimension del cabezal: 144x70 cm. Tres pilotes, no dos: la planilla de armadura declara 8 pilotes bajo cabezales de 70 cm, que son un CBZ02 y dos CBZ03. Carga tomada de la bajada de la planilla de columnas, que esta incompleta: el valor real es mayor.
A12: CB9 | B12: C8 (15x30) | C12: CBZ 02 | D12: 129 | E12: 70 | F12: 70 | G12: 42.67 | H12: =IF(G12="","",G12/1.4) -> 30.478571 | I12: 2 | J12: 30 | K12: 4.5 | L12: =IF(H12="","",H12/I12) -> 15.239286 | M12: =Datos_pilotes!$B$4 -> 22 | N12: =IF(L12="","FALTA CARGA",IF(L12<=M12,"VERIFICA","NO VERIFICA")) -> VERIFICA | O12: Cantidad de pilotes deducida de la dimension del cabezal: 129x70 cm. El computo metrico declara un solo CBZ02 y en el plano aparecen dos rotulos. Verificar cual corresponde. Carga tomada de la bajada de la planilla de columnas, que esta incompleta: el valor real es mayor.
A14: Los 33 pilotes del plano: 13 bajo cabezales de columna (los de esta tabla) y 20 repartidos bajo las vigas de fundacion.

Sheet Tabiques
A1: TABIQUES H°A° H-21 ACERO III espesor 12 cm
A2: NIVEL | B2: POSICION | C2: CARGA (t) | D2: ALTURA (m) | E2: DIMENSIONES (cm) | G2: ARMADURA VERTICAL | J2: ARMADURA HORIZONTAL | M2: VERIFICACION | Q2: OBSERVACIONES
E3: A | F3: B | G3: cm2 | H3: o | I3: separacion | J3: cm2 | K3: o | L3: separacion | M3: area (cm2) | N3: sigma (kg/cm2) | O3: fi Pn (t) | P3: resultado
A4: PB | B4: T1 | C4: 18.74 | D4: 3.15 | E4: 365 | F4: 87 | G4: =2*(100/I4)*PI()*(H4/10)^2/4 -> 5.0265482 | H4: 8 | I4: 20 | J4: =(100/L4)*PI()*(K4/10)^2/4 -> 2.5132741 | K4: 8 | L4: 20 | M4: =IF(F4<=12,E4*F4,(E4+F4-12)*12) -> 5280 | N4: =IF(C4="","",C4*1000/M4) -> 3.5492424 | O4: =0.55*0.65*Datos_vigas!$B$5*M4*MAX(0,1-(D4*100/(32*12))^2)/1000 -> 129.65614 | P4: =IF(C4="","FALTA CARGA",IF(C4<=O4,"VERIFICA","NO VERIFICA")) -> VERIFICA | Q4: 9,00 t de la planilla de la catedra mas las reacciones de VI 01a (6,16 t) y VI 07a (3,58 t), que apoyan aqui. Se suman por la misma razon que en T6.
B5: T2 | C5: 8.5 | D5: 3.15 | E5: 420 | F5: 85 | G5: =2*(100/I5)*PI()*(H5/10)^2/4 -> 5.0265482 | H5: 8 | I5: 20 | J5: =(100/L5)*PI()*(K5/10)^2/4 -> 2.5132741 | K5: 8 | L5: 20 | M5: =IF(F5<=12,E5*F5,(E5+F5-12)*12) -> 5916 | N5: =IF(C5="","",C5*1000/M5) -> 1.4367816 | O5: =0.55*0.65*Datos_vigas!$B$5*M5*MAX(0,1-(D5*100/(32*12))^2)/1000 -> 145.27381 | P5: =IF(C5="","FALTA CARGA",IF(C5<=O5,"VERIFICA","NO VERIFICA")) -> VERIFICA | Q5: 6,00 t de la planilla de la catedra mas la reaccion de VI 01b (2,5 t), que apoya aqui y en la COL 01 de 10x10. Se suman por la misma razon que en T6.
B6: T3 | C6: 5 | D6: 3.15 | E6: 80 | F6: 12 | G6: =2*(100/I6)*PI()*(H6/10)^2/4 -> 5.0265482 | H6: 8 | I6: 20 | J6: =(100/L6)*PI()*(K6/10)^2/4 -> 2.5132741 | K6: 8 | L6: 20 | M6: =IF(F6<=12,E6*F6,(E6+F6-12)*12) -> 960 | N6: =IF(C6="","",C6*1000/M6) -> 5.2083333 | O6: =0.55*0.65*Datos_vigas!$B$5*M6*MAX(0,1-(D6*100/(32*12))^2)/1000 -> 23.573843 | P6: =IF(C6="","FALTA CARGA",IF(C6<=O6,"VERIFICA","NO VERIFICA")) -> VERIFICA | Q6: Tabique recto: B = 12 cm es el espesor.
B7: T4 | C7: 12.52 | D7: 3.15 | E7: 355 | F7: 12 | G7: =2*(100/I7)*PI()*(H7/10)^2/4 -> 5.0265482 | H7: 8 | I7: 20 | J7: =(100/L7)*PI()*(K7/10)^2/4 -> 2.5132741 | K7: 8 | L7: 20 | M7: =IF(F7<=12,E7*F7,(E7+F7-12)*12) -> 4260 | N7: =IF(C7="","",C7*1000/M7) -> 2.9389671 | O7: =0.55*0.65*Datos_vigas!$B$5*M7*MAX(0,1-(D7*100/(32*12))^2)/1000 -> 104.60893 | P7: =IF(C7="","FALTA CARGA",IF(C7<=O7,"VERIFICA","NO VERIFICA")) -> VERIFICA | Q7: Tabique recto: B = 12 cm es el espesor. 5,00 t de la planilla de la catedra mas la reaccion de VI 11c (7,52 t), que apoya en el T04b del plano y en una COL 02 de 15x30. OJO: el plano distingue T04a y T04b, de 0,73 m cada uno segun el computo, mientras que la catedra tiene un solo T4 de 3,55 m: las dos numeraciones no se corresponden una a una.
B8: T5 | C8: 11 | D8: 3.15 | E8: 400 | F8: 300 | G8: =2*(100/I8)*PI()*(H8/10)^2/4 -> 5.0265482 | H8: 8 | I8: 20 | J8: =(100/L8)*PI()*(K8/10)^2/4 -> 2.5132741 | K8: 8 | L8: 20 | M8: =IF(F8<=12,E8*F8,(E8+F8-12)*12) -> 8256 | N8: =IF(C8="","",C8*1000/M8) -> 1.3323643 | O8: =0.55*0.65*Datos_vigas!$B$5*M8*MAX(0,1-(D8*100/(32*12))^2)/1000 -> 202.73505 | P8: =IF(C8="","FALTA CARGA",IF(C8<=O8,"VERIFICA","NO VERIFICA")) -> VERIFICA | Q8: Si corresponde al T05b del plano, recibe el extremo de VI 07c, cuya reaccion da 18,1 t de servicio en mi bajada contra los 11 t de la catedra. Verificar.
B9: T6 | C9: 14.1 | D9: 3.15 | E9: 270 | F9: 90 | G9: =2*(100/I9)*PI()*(H9/10)^2/4 -> 5.0265482 | H9: 8 | I9: 20 | J9: =(100/L9)*PI()*(K9/10)^2/4 -> 2.5132741 | K9: 8 | L9: 20 | M9: =IF(F9<=12,E9*F9,(E9+F9-12)*12) -> 4176 | N9: =IF(C9="","",C9*1000/M9) -> 3.3764368 | O9: =0.55*0.65*Datos_vigas!$B$5*M9*MAX(0,1-(D9*100/(32*12))^2)/1000 -> 102.54622 | P9: =IF(C9="","FALTA CARGA",IF(C9<=O9,"VERIFICA","NO VERIFICA")) -> VERIFICA | Q9: 6,00 t de la planilla de la catedra mas las reacciones de VCH 03a (6,4 t) y VCH 05 (1,7 t), que apoyan en el perpendicularmente. No consta si los 6,00 t ya las incluian; se suman por ser la hipotesis conservadora. Con cualquiera de las dos lecturas el tabique usa entre el 6 y el 14 por ciento de su capacidad.
B10: T7 | C10: 30.62 | D10: 3.15 | E10: 98 | F10: 12 | G10: =2*(100/I10)*PI()*(H10/10)^2/4 -> 5.0265482 | H10: 8 | I10: 20 | J10: =(100/L10)*PI()*(K10/10)^2/4 -> 2.5132741 | K10: 8 | L10: 20 | M10: =IF(F10<=12,E10*F10,(E10+F10-12)*12) -> 1176 | N10: =IF(C10="","",C10*1000/M10) -> 26.037415 | O10: =0.55*0.65*Datos_vigas!$B$5*M10*MAX(0,1-(D10*100/(32*12))^2)/1000 -> 28.877958 | P10: =IF(C10="","FALTA CARGA",IF(C10<=O10,"VERIFICA","NO VERIFICA")) -> NO VERIFICA | Q10: NO VERIFICA por poco, al 106 por ciento. Recibe VI 02 (21,12 t), VI 10b (6,60 t), VI 10a (1,59 t) y VI 17 (1,31 t): 98 cm de tabique tomando 30,6 t. La capacidad sale de la formula simplificada de muro portante, cuya reduccion por esbeltez se come dos tercios: con 12 cm y 3,15 m el coeficiente vale 0,327. Un analisis mas fino del arriostramiento real daria mas capacidad. Con 104 cm de largo verificaria.
B11: T8 | C11: 13.78 | D11: 3.15 | E11: 290 | F11: 12 | G11: =2*(100/I11)*PI()*(H11/10)^2/4 -> 5.0265482 | H11: 8 | I11: 20 | J11: =(100/L11)*PI()*(K11/10)^2/4 -> 2.5132741 | K11: 8 | L11: 20 | M11: =IF(F11<=12,E11*F11,(E11+F11-12)*12) -> 3480 | N11: =IF(C11="","",C11*1000/M11) -> 3.9597701 | O11: =0.55*0.65*Datos_vigas!$B$5*M11*MAX(0,1-(D11*100/(32*12))^2)/1000 -> 85.455182 | P11: =IF(C11="","FALTA CARGA",IF(C11<=O11,"VERIFICA","NO VERIFICA")) -> VERIFICA | Q11: Carga tomada de la reaccion de VI 11a en la planilla de vigas, MAYORADA.
A12: PA | B12: T9 | C12: 6.96 | D12: 3.2 | E12: 375 | F12: 12 | G12: =2*(100/I12)*PI()*(H12/10)^2/4 -> 5.0265482 | H12: 8 | I12: 20 | J12: =(100/L12)*PI()*(K12/10)^2/4 -> 2.5132741 | K12: 8 | L12: 20 | M12: =IF(F12<=12,E12*F12,(E12+F12-12)*12) -> 4500 | N12: =IF(C12="","",C12*1000/M12) -> 1.5466667 | O12: =0.55*0.65*Datos_vigas!$B$5*M12*MAX(0,1-(D12*100/(32*12))^2)/1000 -> 103.22813 | P12: =IF(C12="","FALTA CARGA",IF(C12<=O12,"VERIFICA","NO VERIFICA")) -> VERIFICA | Q12: Recibe el extremo de VI 14. Carga mayorada.
B13: T10 | C13: 13.38 | D13: 2.6 | E13: 170 | F13: 12 | G13: =2*(100/I13)*PI()*(H13/10)^2/4 -> 5.0265482 | H13: 8 | I13: 20 | J13: =(100/L13)*PI()*(K13/10)^2/4 -> 2.5132741 | K13: 8 | L13: 20 | M13: =IF(F13<=12,E13*F13,(E13+F13-12)*12) -> 2040 | N13: =IF(C13="","",C13*1000/M13) -> 6.5588235 | O13: =0.55*0.65*Datos_vigas!$B$5*M13*MAX(0,1-(D13*100/(32*12))^2)/1000 -> 82.941257 | P13: =IF(C13="","FALTA CARGA",IF(C13<=O13,"VERIFICA","NO VERIFICA")) -> VERIFICA | Q13: Recibe el extremo de VI 12. Carga mayorada.
B14: T11 | C14: 5.07 | D14: 2.6 | E14: 28 | F14: 12 | G14: =2*(100/I14)*PI()*(H14/10)^2/4 -> 5.0265482 | H14: 8 | I14: 20 | J14: =(100/L14)*PI()*(K14/10)^2/4 -> 2.5132741 | K14: 8 | L14: 20 | M14: =IF(F14<=12,E14*F14,(E14+F14-12)*12) -> 336 | N14: =IF(C14="","",C14*1000/M14) -> 15.089286 | O14: =0.55*0.65*Datos_vigas!$B$5*M14*MAX(0,1-(D14*100/(32*12))^2)/1000 -> 13.660913 | P14: =IF(C14="","FALTA CARGA",IF(C14<=O14,"VERIFICA","NO VERIFICA")) -> VERIFICA | Q14: Recibe el extremo de VI 13b sobre solo 28 cm de largo: es el tabique con mayor tension del conjunto.
B15: T12 | C15: 5.62 | D15: 2.6 | E15: 32 | F15: 12 | G15: =2*(100/I15)*PI()*(H15/10)^2/4 -> 5.0265482 | H15: 8 | I15: 20 | J15: =(100/L15)*PI()*(K15/10)^2/4 -> 2.5132741 | K15: 8 | L15: 20 | M15: =IF(F15<=12,E15*F15,(E15+F15-12)*12) -> 384 | N15: =IF(C15="","",C15*1000/M15) -> 14.635417 | O15: =0.55*0.65*Datos_vigas!$B$5*M15*MAX(0,1-(D15*100/(32*12))^2)/1000 -> 15.612472 | P15: =IF(C15="","FALTA CARGA",IF(C15<=O15,"VERIFICA","NO VERIFICA")) -> VERIFICA | Q15: Recibe el extremo de VI 15b. VI 17 no descarga aqui sino en T07. T12 acompana a VI 17 en toda su longitud por debajo, de modo que esa viga esta mas sostenida de lo que supone el calculo: queda del lado seguro.
B16: T13 | C16: 1.22 | D16: 3.2 | E16: 132 | F16: 12 | G16: =2*(100/I16)*PI()*(H16/10)^2/4 -> 5.0265482 | H16: 8 | I16: 20 | J16: =(100/L16)*PI()*(K16/10)^2/4 -> 2.5132741 | K16: 8 | L16: 20 | M16: =IF(F16<=12,E16*F16,(E16+F16-12)*12) -> 1584 | N16: =IF(C16="","",C16*1000/M16) -> 0.77020202 | O16: =0.55*0.65*Datos_vigas!$B$5*M16*MAX(0,1-(D16*100/(32*12))^2)/1000 -> 36.3363 | P16: =IF(C16="","FALTA CARGA",IF(C16<=O16,"VERIFICA","NO VERIFICA")) -> VERIFICA | Q16: No recibe vigas: es la continuidad del tabique T06c de planta baja. La carga indicada es solo su peso propio; lo que baje de arriba se suma a T06c.
A18: T1 a T6: cargas y dimensiones tomadas de la planilla de la catedra. Probablemente sean cargas de servicio; compararlas contra fi Pn, que es resistencia ultima, queda del lado inseguro en torno a un 40 por ciento. Con utilizaciones del 10 al 20 por ciento no cambia ningun veredicto, pero conviene saberlo.
A19: T7 y T8: carga tomada de la reaccion de VI 02 y VI 11a en la planilla de vigas, que son MAYORADAS. El criterio no es el mismo que en T1 a T6.
A20: Direccion de la carga: como todas las vigas son invertidas, sobresalen 70 cm por encima del fondo de losa, mientras que los tabiques de planta alta llegan desde el piso hasta ese fondo. El tabique queda debajo y sostiene a la viga, no al reves.
A21: T9 a T13: dimensiones del computo metrico. Las cargas son las reacciones de las vigas de techo que apoyan en cada uno, aportadas por el proyectista: T9 recibe VI 14, T10 recibe VI 12, T11 recibe VI 13b y T12 recibe VI 17 mas VI 15b. T13 no recibe vigas: continua el tabique T06c de planta baja.
A22: Area: si B es menor o igual al espesor el tabique es recto y el area es A x B; si no, es un tabique en L y el area es (A + B - espesor) x espesor.
A23: fi Pn = 0,55 x 0,65 x f'c x area x [1 - (altura / 32 espesor)^2] muro portante de hormigon armado con reduccion por esbeltez.
A24: Armadura vertical en doble malla y horizontal en malla simple, ambas o8 c/20, iguales a las de la planilla de la catedra.

Sheet Balance termico
A1: FORMULARIO DE BALANCE TERMICO PARA CALEFACCION | H1: largo | I1: alto
A3: LOCAL 01 - Cocina / comedor (PB) - altura 3.00 m
A4: Nro | B4: DESCRIPCION | C4: DIMENSIONES (m) | D4: AREA (m2) | E4: FACTOR | F4: PERDIDA CALOR (Kcal/h)
A5: 1 | B5: VENTANA
B6: VA01 | C6: =IF(COUNT(H6,I6)<2,"",TEXT(H6,"0.00")&" x "&TEXT(I6,"0.00")) -> 0.75 x 3.00 | D6: =IF(COUNT(H6,I6)<2,"",ROUND(H6*I6,2)) -> 2.25 | E6: 60 | F6: =IF(D6="","",ROUND(D6*E6,1)) -> 135 | H6: 0.75 | I6: 3
B7: PF03 | C7: =IF(COUNT(H7,I7)<2,"",TEXT(H7,"0.00")&" x "&TEXT(I7,"0.00")) -> 2.88 x 3.00 | D7: =IF(COUNT(H7,I7)<2,"",ROUND(H7*I7,2)) -> 8.64 | E7: 60 | F7: =IF(D7="","",ROUND(D7*E7,1)) -> 518.4 | H7: 2.88 | I7: 3
B8: PF04 | C8: =IF(COUNT(H8,I8)<2,"",TEXT(H8,"0.00")&" x "&TEXT(I8,"0.00")) -> 2.70 x 0.60 | D8: =IF(COUNT(H8,I8)<2,"",ROUND(H8*I8,2)) -> 1.62 | E8: 60 | F8: =IF(D8="","",ROUND(D8*E8,1)) -> 97.2 | H8: 2.7 | I8: 0.6
B9: PV02 | C9: =IF(COUNT(H9,I9)<2,"",TEXT(H9,"0.00")&" x "&TEXT(I9,"0.00")) -> 2.48 x 3.00 | D9: =IF(COUNT(H9,I9)<2,"",ROUND(H9*I9,2)) -> 7.44 | E9: 60 | F9: =IF(D9="","",ROUND(D9*E9,1)) -> 446.4 | H9: 2.48 | I9: 3
A10: 2 | B10: PAREDES EXTERIORES
B11: AISLADAS (NO) | C11: =IF(COUNT(H11,I11)<2,"",TEXT(H11,"0.00")&" x "&TEXT(I11,"0.00")) -> 7.63 x 3.00 | D11: =IF(COUNT(H11,I11)<2,"",ROUND(H11*I11,2)) -> 22.89 | E11: 20 | F11: =IF(D11="","",ROUND(D11*E11,1)) -> 457.8 | H11: 7.63 | I11: 3
B12: AISLADAS (SO) | C12: =IF(COUNT(H12,I12)<2,"",TEXT(H12,"0.00")&" x "&TEXT(I12,"0.00")) -> 3.56 x 3.00 | D12: =IF(COUNT(H12,I12)<2,"",ROUND(H12*I12,2)) -> 10.68 | E12: 20 | F12: =IF(D12="","",ROUND(D12*E12,1)) -> 213.6 | H12: 3.56 | I12: 3
B13: INTERIORES (SE) | C13: =IF(COUNT(H13,I13)<2,"",TEXT(H13,"0.00")&" x "&TEXT(I13,"0.00")) -> 7.63 x 3.00 | D13: =IF(COUNT(H13,I13)<2,"",ROUND(H13*I13,2)) -> 22.89 | E13: 25 | F13: =IF(D13="","",ROUND(D13*E13,1)) -> 572.3 | H13: 7.63 | I13: 3
B14: INTERIORES (NE) | C14: =IF(COUNT(H14,I14)<2,"",TEXT(H14,"0.00")&" x "&TEXT(I14,"0.00")) -> 3.56 x 3.00 | D14: =IF(COUNT(H14,I14)<2,"",ROUND(H14*I14,2)) -> 10.68 | E14: 25 | F14: =IF(D14="","",ROUND(D14*E14,1)) -> 267 | H14: 3.56 | I14: 3
A15: 3 | B15: TECHOS O CIELORRASOS
B16: TECHO NO AISLADO | D16: =IF(COUNT(H16,I16)<2,"",ROUND(H16*I16,2)) | E16: 30 | F16: =IF(D16="","",ROUND(D16*E16,1))
B17: TECHO AISLADO | D17: =IF(COUNT(H17,I17)<2,"",ROUND(H17*I17,2)) | E17: 20 | F17: =IF(D17="","",ROUND(D17*E17,1))
B18: TECHO ENTREPISO | C18: por croquis | D18: 27.16 | E18: 15 | F18: =IF(D18="","",ROUND(D18*E18,1)) -> 407.4
A19: 4 | B19: PISO
B20: SOBRE TIERRA | C20: por croquis | D20: 27.16 | E20: 10 | F20: =IF(D20="","",ROUND(D20*E20,1)) -> 271.6
B21: SOBRE LOCAL OCUPADO | D21: =IF(COUNT(H21,I21)<2,"",ROUND(H21*I21,2)) | E21: 15 | F21: =IF(D21="","",ROUND(D21*E21,1))
A22: 5 | B22: INFILTRACION | D22: VOL. (m3)
B23: UNA PARED EXTERIOR | D23: =IF(COUNT(H23,I23)<2,"",ROUND(H23*I23,2)) | E23: 6 | F23: =IF(D23="","",ROUND(D23*E23,1))
B24: DOS PAREDES EXTERIORES | C24: 27.16 m2 x 3.00 | D24: 81.48 | E24: 9 | F24: =IF(D24="","",ROUND(D24*E24,1)) -> 733.3
B25: TRES O MAS PAREDES EXTERIORES | D25: =IF(COUNT(H25,I25)<2,"",ROUND(H25*I25,2)) | E25: 12 | F25: =IF(D25="","",ROUND(D25*E25,1))
A26: 6 | B26: SUBTOTAL | F26: =IF(F6="",0,F6)+IF(F7="",0,F7)+IF(F8="",0,F8)+IF(F9="",0,F9)+IF(F11="",0,F11)+IF(F12="",0,F12)+IF(F13="",0,F13)+IF(F14="",0,F14)+IF(F16="",0,F16)+IF(F17="",0,F17)+IF(F18="",0,F18)+IF(F20="",0,F20)+IF(F21="",0,F21)+IF(F23="",0,F23)+IF(F24="",0,F24)+IF(F25="",0,F25) -> 4120
A27: 7 | B27: PERDIDA TOTAL | C27: =TEXT(F26,"0.00")&" X "&Datos_balance!$B$4&" (FI) X "&Datos_balance!$B$5&" (FO) X "&Datos_balance!$B$6&" (FZ)" -> 4120.00 X 1.07 (FI) X 1 (FO) X 1 (FZ) | F27: =ROUND(F26*Datos_balance!$B$4*Datos_balance!$B$5*Datos_balance!$B$6,1) -> 4408.4
B28: Carga de locales sin emisor
B29: CARGA TOTAL A CUBRIR | F29: =F27+IF(F28="",0,F28) -> 4408.4
B31: Salto termico: dt = (te+ts)/2 - ti | C31: =TEXT((Datos_balance!$B$9+Datos_balance!$B$10)/2,"0")&" - "&TEXT(Datos_balance!$B$11,"0")&" = "&TEXT((Datos_balance!$B$9+Datos_balance!$B$10)/2-Datos_balance!$B$11,"0")&" C" -> 86 - 20 = 66 C
B32: Kcal/h por elemento | C32: =ROUND(Datos_balance!$B$14*Datos_balance!$B$15,2) -> 274.4
B33: Elementos necesarios | C33: =ROUNDUP(F29/(Datos_balance!$B$14*Datos_balance!$B$15),0) -> 17
B34: Ancho del radiador (cm) | C34: =ROUNDUP(F29/(Datos_balance!$B$14*Datos_balance!$B$15),0)*Datos_balance!$B$16 -> 136
B35: Radiador adoptado | C35: =Datos_balance!$B$13 -> Peisa Tropical 80-500
B37: Ubicacion en planta de 01 - Cocina / comedor
A51: LOCAL 06 - Living / comedor (PB) - altura 3.00 m
A52: Nro | B52: DESCRIPCION | C52: DIMENSIONES (m) | D52: AREA (m2) | E52: FACTOR | F52: PERDIDA CALOR (Kcal/h)
A53: 1 | B53: VENTANA
B54: PF02 | C54: =IF(COUNT(H54,I54)<2,"",TEXT(H54,"0.00")&" x "&TEXT(I54,"0.00")) -> 3.75 x 3.00 | D54: =IF(COUNT(H54,I54)<2,"",ROUND(H54*I54,2)) -> 11.25 | E54: 60 | F54: =IF(D54="","",ROUND(D54*E54,1)) -> 675 | H54: 3.75 | I54: 3
B55: PV01 | C55: =IF(COUNT(H55,I55)<2,"",TEXT(H55,"0.00")&" x "&TEXT(I55,"0.00")) -> 7.70 x 3.00 | D55: =IF(COUNT(H55,I55)<2,"",ROUND(H55*I55,2)) -> 23.1 | E55: 60 | F55: =IF(D55="","",ROUND(D55*E55,1)) -> 1386 | H55: 7.7 | I55: 3
A56: 2 | B56: PAREDES EXTERIORES
B57: AISLADAS (SE) | C57: =IF(COUNT(H57,I57)<2,"",TEXT(H57,"0.00")&" x "&TEXT(I57,"0.00")) -> 8.66 x 3.00 | D57: =IF(COUNT(H57,I57)<2,"",ROUND(H57*I57,2)) -> 25.98 | E57: 20 | F57: =IF(D57="","",ROUND(D57*E57,1)) -> 519.6 | H57: 8.66 | I57: 3
B58: AISLADAS | C58: =IF(COUNT(H58,I58)<2,"",TEXT(H58,"0.00")&" x "&TEXT(I58,"0.00")) | D58: =IF(COUNT(H58,I58)<2,"",ROUND(H58*I58,2)) | E58: 20 | F58: =IF(D58="","",ROUND(D58*E58,1))
B59: INTERIORES (NE) | C59: =IF(COUNT(H59,I59)<2,"",TEXT(H59,"0.00")&" x "&TEXT(I59,"0.00")) -> 4.06 x 3.00 | D59: =IF(COUNT(H59,I59)<2,"",ROUND(H59*I59,2)) -> 12.18 | E59: 25 | F59: =IF(D59="","",ROUND(D59*E59,1)) -> 304.5 | H59: 4.06 | I59: 3
B60: INTERIORES (NO) | C60: =IF(COUNT(H60,I60)<2,"",TEXT(H60,"0.00")&" x "&TEXT(I60,"0.00")) -> 8.66 x 3.00 | D60: =IF(COUNT(H60,I60)<2,"",ROUND(H60*I60,2)) -> 25.98 | E60: 25 | F60: =IF(D60="","",ROUND(D60*E60,1)) -> 649.5 | H60: 8.66 | I60: 3
B61: INTERIORES (SO) | C61: =IF(COUNT(H61,I61)<2,"",TEXT(H61,"0.00")&" x "&TEXT(I61,"0.00")) -> 4.06 x 3.00 | D61: =IF(COUNT(H61,I61)<2,"",ROUND(H61*I61,2)) -> 12.18 | E61: 25 | F61: =IF(D61="","",ROUND(D61*E61,1)) -> 304.5 | H61: 4.06 | I61: 3
A62: 3 | B62: TECHOS O CIELORRASOS
B63: TECHO NO AISLADO | D63: =IF(COUNT(H63,I63)<2,"",ROUND(H63*I63,2)) | E63: 30 | F63: =IF(D63="","",ROUND(D63*E63,1))
B64: TECHO AISLADO | D64: =IF(COUNT(H64,I64)<2,"",ROUND(H64*I64,2)) | E64: 20 | F64: =IF(D64="","",ROUND(D64*E64,1))
B65: TECHO ENTREPISO | C65: por croquis | D65: 35.16 | E65: 15 | F65: =IF(D65="","",ROUND(D65*E65,1)) -> 527.4
A66: 4 | B66: PISO
B67: SOBRE TIERRA | C67: por croquis | D67: 35.16 | E67: 10 | F67: =IF(D67="","",ROUND(D67*E67,1)) -> 351.6
B68: SOBRE LOCAL OCUPADO | D68: =IF(COUNT(H68,I68)<2,"",ROUND(H68*I68,2)) | E68: 15 | F68: =IF(D68="","",ROUND(D68*E68,1))
A69: 5 | B69: INFILTRACION | D69: VOL. (m3)
B70: UNA PARED EXTERIOR | C70: 35.16 m2 x 3.00 | D70: 105.48 | E70: 6 | F70: =IF(D70="","",ROUND(D70*E70,1)) -> 632.9
B71: DOS PAREDES EXTERIORES | D71: =IF(COUNT(H71,I71)<2,"",ROUND(H71*I71,2)) | E71: 9 | F71: =IF(D71="","",ROUND(D71*E71,1))
B72: TRES O MAS PAREDES EXTERIORES | D72: =IF(COUNT(H72,I72)<2,"",ROUND(H72*I72,2)) | E72: 12 | F72: =IF(D72="","",ROUND(D72*E72,1))
A73: 6 | B73: SUBTOTAL | F73: =IF(F54="",0,F54)+IF(F55="",0,F55)+IF(F57="",0,F57)+IF(F58="",0,F58)+IF(F59="",0,F59)+IF(F60="",0,F60)+IF(F61="",0,F61)+IF(F63="",0,F63)+IF(F64="",0,F64)+IF(F65="",0,F65)+IF(F67="",0,F67)+IF(F68="",0,F68)+IF(F70="",0,F70)+IF(F71="",0,F71)+IF(F72="",0,F72) -> 5351
A74: 7 | B74: PERDIDA TOTAL | C74: =TEXT(F73,"0.00")&" X "&Datos_balance!$B$4&" (FI) X "&Datos_balance!$B$5&" (FO) X "&Datos_balance!$B$6&" (FZ)" -> 5351.00 X 1.07 (FI) X 1 (FO) X 1 (FZ) | F74: =ROUND(F73*Datos_balance!$B$4*Datos_balance!$B$5*Datos_balance!$B$6,1) -> 5725.6
B75: Carga de locales sin emisor | C75: 07 - Hall / ingreso | F75: =F120 -> 2339.6
B76: CARGA TOTAL A CUBRIR | F76: =F74+IF(F75="",0,F75) -> 8065.2
B78: Salto termico: dt = (te+ts)/2 - ti | C78: =TEXT((Datos_balance!$B$9+Datos_balance!$B$10)/2,"0")&" - "&TEXT(Datos_balance!$B$11,"0")&" = "&TEXT((Datos_balance!$B$9+Datos_balance!$B$10)/2-Datos_balance!$B$11,"0")&" C" -> 86 - 20 = 66 C
B79: Kcal/h por elemento | C79: =ROUND(Datos_balance!$B$14*Datos_balance!$B$15,2) -> 274.4
B80: Elementos necesarios | C80: =ROUNDUP(F76/(Datos_balance!$B$14*Datos_balance!$B$15),0) -> 30
B81: Ancho del radiador (cm) | C81: =ROUNDUP(F76/(Datos_balance!$B$14*Datos_balance!$B$15),0)*Datos_balance!$B$16 -> 240
B82: Radiador adoptado | C82: =Datos_balance!$B$13 -> Peisa Tropical 80-500
B84: Ubicacion en planta de 06 - Living / comedor
A98: LOCAL 07 - Hall / ingreso (PB) - altura 3.00 m
A99: Nro | B99: DESCRIPCION | C99: DIMENSIONES (m) | D99: AREA (m2) | E99: FACTOR | F99: PERDIDA CALOR (Kcal/h)
A100: 1 | B100: VENTANA
B101: PF01 | C101: =IF(COUNT(H101,I101)<2,"",TEXT(H101,"0.00")&" x "&TEXT(I101,"0.00")) -> 3.55 x 3.00 | D101: =IF(COUNT(H101,I101)<2,"",ROUND(H101*I101,2)) -> 10.65 | E101: 60 | F101: =IF(D101="","",ROUND(D101*E101,1)) -> 639 | H101: 3.55 | I101: 3
B102: H01 | C102: =IF(COUNT(H102,I102)<2,"",TEXT(H102,"0.00")&" x "&TEXT(I102,"0.00")) -> 1.50 x 3.00 | D102: =IF(COUNT(H102,I102)<2,"",ROUND(H102*I102,2)) -> 4.5 | E102: 60 | F102: =IF(D102="","",ROUND(D102*E102,1)) -> 270 | H102: 1.5 | I102: 3
A103: 2 | B103: PAREDES EXTERIORES
B104: AISLADAS (SO) | C104: =IF(COUNT(H104,I104)<2,"",TEXT(H104,"0.00")&" x "&TEXT(I104,"0.00")) -> 4.00 x 3.00 | D104: =IF(COUNT(H104,I104)<2,"",ROUND(H104*I104,2)) -> 12 | E104: 20 | F104: =IF(D104="","",ROUND(D104*E104,1)) -> 240 | H104: 4 | I104: 3
B105: AISLADAS (SE) | C105: =IF(COUNT(H105,I105)<2,"",TEXT(H105,"0.00")&" x "&TEXT(I105,"0.00")) -> 2.15 x 3.00 | D105: =IF(COUNT(H105,I105)<2,"",ROUND(H105*I105,2)) -> 6.45 | E105: 20 | F105: =IF(D105="","",ROUND(D105*E105,1)) -> 129 | H105: 2.15 | I105: 3
B106: INTERIORES (NE) | C106: =IF(COUNT(H106,I106)<2,"",TEXT(H106,"0.00")&" x "&TEXT(I106,"0.00")) -> 4.00 x 3.00 | D106: =IF(COUNT(H106,I106)<2,"",ROUND(H106*I106,2)) -> 12 | E106: 25 | F106: =IF(D106="","",ROUND(D106*E106,1)) -> 300 | H106: 4 | I106: 3
B107: INTERIORES (NO) | C107: =IF(COUNT(H107,I107)<2,"",TEXT(H107,"0.00")&" x "&TEXT(I107,"0.00")) -> 2.15 x 3.00 | D107: =IF(COUNT(H107,I107)<2,"",ROUND(H107*I107,2)) -> 6.45 | E107: 25 | F107: =IF(D107="","",ROUND(D107*E107,1)) -> 161.3 | H107: 2.15 | I107: 3
A108: 3 | B108: TECHOS O CIELORRASOS
B109: TECHO NO AISLADO | D109: =IF(COUNT(H109,I109)<2,"",ROUND(H109*I109,2)) | E109: 30 | F109: =IF(D109="","",ROUND(D109*E109,1))
B110: TECHO AISLADO | D110: =IF(COUNT(H110,I110)<2,"",ROUND(H110*I110,2)) | E110: 20 | F110: =IF(D110="","",ROUND(D110*E110,1))
B111: TECHO ENTREPISO | C111: por croquis | D111: 8.6 | E111: 15 | F111: =IF(D111="","",ROUND(D111*E111,1)) -> 129
A112: 4 | B112: PISO
B113: SOBRE TIERRA | C113: por croquis | D113: 8.6 | E113: 10 | F113: =IF(D113="","",ROUND(D113*E113,1)) -> 86
B114: SOBRE LOCAL OCUPADO | D114: =IF(COUNT(H114,I114)<2,"",ROUND(H114*I114,2)) | E114: 15 | F114: =IF(D114="","",ROUND(D114*E114,1))
A115: 5 | B115: INFILTRACION | D115: VOL. (m3)
B116: UNA PARED EXTERIOR | D116: =IF(COUNT(H116,I116)<2,"",ROUND(H116*I116,2)) | E116: 6 | F116: =IF(D116="","",ROUND(D116*E116,1))
B117: DOS PAREDES EXTERIORES | C117: 8.60 m2 x 3.00 | D117: 25.8 | E117: 9 | F117: =IF(D117="","",ROUND(D117*E117,1)) -> 232.2
B118: TRES O MAS PAREDES EXTERIORES | D118: =IF(COUNT(H118,I118)<2,"",ROUND(H118*I118,2)) | E118: 12 | F118: =IF(D118="","",ROUND(D118*E118,1))
A119: 6 | B119: SUBTOTAL | F119: =IF(F101="",0,F101)+IF(F102="",0,F102)+IF(F104="",0,F104)+IF(F105="",0,F105)+IF(F106="",0,F106)+IF(F107="",0,F107)+IF(F109="",0,F109)+IF(F110="",0,F110)+IF(F111="",0,F111)+IF(F113="",0,F113)+IF(F114="",0,F114)+IF(F116="",0,F116)+IF(F117="",0,F117)+IF(F118="",0,F118) -> 2186.5
A120: 7 | B120: PERDIDA TOTAL | C120: =TEXT(F119,"0.00")&" X "&Datos_balance!$B$4&" (FI) X "&Datos_balance!$B$5&" (FO) X "&Datos_balance!$B$6&" (FZ)" -> 2186.50 X 1.07 (FI) X 1 (FO) X 1 (FZ) | F120: =ROUND(F119*Datos_balance!$B$4*Datos_balance!$B$5*Datos_balance!$B$6,1) -> 2339.6
B121: Carga de locales sin emisor
B122: CARGA TOTAL A CUBRIR | F122: =F120+IF(F121="",0,F121) -> 2339.6
B124: SIN EMISOR | C124: la cubre el radiador de 06 - Living / comedor
B126: Ubicacion en planta de 07 - Hall / ingreso
A140: LOCAL 08 - Vestidor (PB) - altura 3.00 m
A141: Nro | B141: DESCRIPCION | C141: DIMENSIONES (m) | D141: AREA (m2) | E141: FACTOR | F141: PERDIDA CALOR (Kcal/h)
A142: 1 | B142: VENTANA
B143: (sin aberturas) | C143: =IF(COUNT(H143,I143)<2,"",TEXT(H143,"0.00")&" x "&TEXT(I143,"0.00")) | D143: =IF(COUNT(H143,I143)<2,"",ROUND(H143*I143,2)) | E143: 60 | F143: =IF(D143="","",ROUND(D143*E143,1))
A144: 2 | B144: PAREDES EXTERIORES
B145: AISLADAS (SO) | C145: =IF(COUNT(H145,I145)<2,"",TEXT(H145,"0.00")&" x "&TEXT(I145,"0.00")) -> 1.70 x 3.00 | D145: =IF(COUNT(H145,I145)<2,"",ROUND(H145*I145,2)) -> 5.1 | E145: 20 | F145: =IF(D145="","",ROUND(D145*E145,1)) -> 102 | H145: 1.7 | I145: 3
B146: AISLADAS | C146: =IF(COUNT(H146,I146)<2,"",TEXT(H146,"0.00")&" x "&TEXT(I146,"0.00")) | D146: =IF(COUNT(H146,I146)<2,"",ROUND(H146*I146,2)) | E146: 20 | F146: =IF(D146="","",ROUND(D146*E146,1))
...

Sheet Datos_vigas
A1: DATOS DE PARTIDA - HIPOTESIS DE CALCULO
A2: Celdas verdes: editables. La planilla recalcula sola.
A4: MATERIALES | B4: valor | C4: unidad
A5: Hormigon H-21 f'c | B5: 210 | C5: kg/cm2
A6: Acero 42/50 fy | B6: 4200 | C6: kg/cm2
A7: Peso especifico H.A. | B7: 2400 | C7: kg/m3
A8: phi flexion | B8: 0.9 | C8: -
A9: phi corte | B9: 0.75 | C9: -
A10: Coef. mayoracion permanente | B10: 1.2 | C10: -
A11: Coef. mayoracion sobrecarga | B11: 1.6 | C11: -
A13: PAQUETES DE CARGA | B13: g (kg/m2) | C13: q (kg/m2) | D13: h muro (m) | E13: B trib. (m) | F13: composicion
A14: PA | B14: 550 | C14: 200 | D14: 2.6 | E14: 2 | F14: Losa 12 cm 300 + contrapiso 130 + carpeta 42 + piso 50 + cielorraso 20
A15: TECHO | B15: 560 | C15: 100 | D15: 1 | E15: 2 | F15: Losa 12 cm 300 + contrapiso pendiente 140 + carpeta 42 + aislacion 50 + cielorraso 20
A16: Mamposteria sobre viga | B16: 250 | C16: kg/m2 | F16: Ladrillo hueco 18 cm + revoque en ambas caras
A18: COEFICIENTES SEGUN ESQUEMA | B18: M tramo | C18: M apoyo | D18: Reaccion | E18: L/d min
A19: Simplemente apoyada | B19: 0.125 | C19: 0 | D19: 0.5 | E19: 16
A20: Continua | B20: 0.07143 | C20: 0.1 | D20: 0.575 | E20: 21
A21: Empotrada-apoyada | B21: 0.07031 | C21: 0.125 | D21: 0.625 | E21: 18.5
A22: Biempotrada | B22: 0.04167 | C22: 0.08333 | D22: 0.5 | E22: 21
A23: Voladizo | B23: 0 | C23: 0.5 | D23: 1 | E23: 8
A25: p = 1,2 g + 1,6 q | M = coef x p x L2 | R = coef x p x L

Sheet Datos_losas
A1: DATOS DE PARTIDA - LOSAS
A2: Celdas verdes: editables. La planilla recalcula sola.
A4: MATERIALES Y METODO | B4: valor | C4: unidad
A5: Hormigon H-21 f'c | B5: 210 | C5: kg/cm2
A6: Acero 42/50 fy | B6: 4200 | C6: kg/cm2
A7: Tension admisible del acero | B7: 2400 | C7: kg/cm2
A8: Brazo elastico z / h | B8: 0.9 | C8: -
A9: Peso especifico H.A. | B9: 2400 | C9: kg/m3
A10: Recubrimiento | B10: 1.5 | C10: cm
A11: Separacion maxima | B11: 20 | C11: cm
A12: Armadura de reparticion | B12: 0.2 | C12: de la principal
A13: Reparticion minima | B13: 0.3 | C13: cm2/m
A15: CARGAS POR NIVEL | B15: terminaciones (kg/m2) | C15: q (kg/m2) | D15: composicion
A16: S/PB | B16: 242 | C16: 200 | D16: Contrapiso 130 + carpeta 42 + piso 50 + cielorraso 20. q vivienda 200
A17: S/PA | B17: 252 | C17: 100 | D17: Contrapiso pendiente 140 + carpeta 42 + aislacion 50 + cielorraso 20. q azotea 100
A18: El peso propio se suma aparte: 2400 x d / 100
A20: GRADO DE EMPOTRAMIENTO | B20: coef. M | C20: coef. R | D20: esquema
A21: 1/8 | B21: 0.125 | C21: 0.5 | D21: Simplemente apoyada
A22: 1/10 | B22: 0.1 | C22: 0.55 | D22: Continua
A23: 1/12 | B23: 0.0833 | C23: 0.5 | D23: Biempotrada
A24: 1/14 | B24: 0.0714 | C24: 0.575 | D24: Continua
A25: 1/2 | B25: 0.5 | C25: 1 | D25: Voladizo
A27: p = peso propio + terminaciones + q (cargas de servicio)
A28: M = coef x p x L2 R = coef x p x L As = M x 100 / (2400 x 0,9 x h) rep. = As / 5

Sheet Datos_columnas
A1: DATOS DE PARTIDA - COLUMNAS
A3: MATERIALES Y CRITERIOS | B3: valor | C3: unidad
A4: Hormigon H-21 f'c | B4: 210 | C4: kg/cm2
A5: Acero 42/50 fy | B5: 4200 | C5: kg/cm2
A6: Peso especifico H.A. | B6: 2400 | C6: kg/m3
A7: phi compresion (estribos) | B7: 0.65 | C7: -
A8: Cuantia minima | B8: 0.008 | C8: de la seccion
A9: Altura PB | B9: 3.15 | C9: m
A10: Altura PA | B10: 3.22 | C10: m
A12: As = cuantia minima x area phi Pn = 0,65 x 0,80 x [0,85 f'c (Ag - As) + fy As]
A13: Separacion de estribos = min(12 x diam. longitudinal ; 48 x diam. estribo ; lado menor)

Sheet Datos_pilotes
A1: DATOS DE PARTIDA - PILOTES
A3: PARAMETRO | B3: valor | C3: unidad | D3: origen
A4: Carga admisible por pilote | B4: 22 | C4: t | D4: ADOPTADA del propio diseno, NO verificada. Ver nota abajo. Cambiar aca cuando aparezca el estudio de suelos.
A5: Tension admisible del terreno | B5: 2 | C5: kg/cm2 | D5: Dato real, tomado del encabezado del calculo de bases.
A6: Diametro del pilote | B6: 30 | C6: cm | D6: Nota del plano: todos los pilotes son O30.
A7: Profundidad | B7: -4.5 | C7: m | D7: Nota del plano: h = -4,50 m desde la cota +-0,00 de vereda.
A8: Coef. de mayoracion adoptado | B8: 1.4 | C8: - | D8: Para pasar de carga mayorada a carga de servicio.
A9: ARMADURA DEL PILOTE (planilla del Ing. Caggiano, 23-03-22) | C9: 5 barras del 12 longitudinales, mas espiral o6 c/15 de 20 cm de diametro, 27 vueltas, longitud teorica 16,95 m. SIN BULBO.
A10: TIPOS DE PILOTE (nota general del plano: CANTIDAD 33 PILOTES)
A11: tipo | B11: cantidad | C11: cota fundacion | D11: nivel llenado | E11: long. hormigon
A12: Pilote tipo "A" | B12: 8 | C12: -4.5 | D12: -0.4 | E12: 4.6 | F12: bajo cabezales de 70 cm (CBZ02 y CBZ03)
A13: Pilote tipo "B" | B13: 5 | C13: -4.5 | D13: -0.35 | E13: 4.5 | F13: bajo cabezales de 65 cm (CBZ01)
A14: Pilote tipo "C" | B14: 16 | C14: -4.5 | D14: -0.05 | E14: 4.35 | F14: bajo VF de 25x35 y 20x35
A15: Pilote tipo "D" | B15: 4 | C15: -4.5 | D15: -0.1 | E15: 4.4 | F15: bajo VF de 25x40
A17: Los cuatro tipos se funden a -4,50 m; se diferencian en el nivel de llenado de hormigon, o sea en la longitud real del fuste.
A18: El computo metrico declara 32 pilotes: le falta uno. La nota del plano dice 33, que es la cantidad que se detecta en el dibujo.
A20: COMO SE ESTIMO LA CARGA ADMISIBLE
A21: Pilote O30: area de punta 0,0707 m2. Punta 0,0707 x 20 t/m2 = 1,4 t.
A22: Area lateral segun el tipo: 3,86 m2 el A, 3,91 el B, 4,19 el C y 4,15 el D.
A23: Con una adherencia de 2,5 t/m2 la capacidad va de 11,1 t el tipo A a 11,9 t el C:
A24: la diferencia entre tipos es menor al 8 por ciento, por eso se usa un unico valor
A25: para todos en lugar de uno por tipo.
A27: DE DONDE SALEN LOS 22 t QUE SE ADOPTAN, Y QUE VALOR TIENEN:
A28: El calculista puso UN solo pilote bajo la columna mas cargada, que baja 21,04 t
A29: de servicio. Si dimensiono asi, es porque para el ese pilote admite al menos eso.
A30: Se adopta 22 t, el redondeo por encima de esa solicitacion.
... A51: trabajan sobre todo por friccion: son dos cosas distintas.

Sheet Datos_higro
A1: DATOS DE PARTIDA - PLANILLA 3 HIGROTERMICA
A3: PARAMETRO | B3: valor | C3: unidad | D3: origen
A4: Transmitancia maxima admitida | B4: 2.9 | C4: W/m2K | D4: Es el valor que usa la planilla de la catedra en todas las filas.
A5: K maximo si los vanos superan el 60% de la fachada | B5: 1.8 | C5: W/m2K | D5: Decreto 1647/2021, Anexo Etapa 3. NO esta aplicado: la planilla usa 2,90 fijo como el ejemplo. Si la fachada es mayormente vidriada, cambiar el valor de arriba por 1,80.
A8: TIPOS DE VIDRIO
A9: descripcion | B9: K orientativo
A10: DVH 6+9+3+3 (el de obra, aluminio linea A30) | B10: 2.8
A11: Simple incoloro 3 mm | B11: 5.8
A12: Simple incoloro 6 mm | B12: 5.7
A13: DVH Incoloro ext; incoloro interior (3+12+3 mm) | B13: 2.8
A14: DVH Incoloro ext; incoloro interior (4+12+4 mm) | B14: 2.75
A15: DVH con lamina de baja emisividad (3+12+3 mm) | B15: 1.8
A16: DVH con camara de argon (4+16+4 mm) | B16: 1.6
A17: Vidrio laminado 3+3 mm | B17: 5.6
A19: TIPOS DE PROTECCION
A20: descripcion | B20: FES orientativo
A21: Sin Proteccion | B21: 0.88
A22: Cortina blackout INTERIOR (no computa) | B22: 0.88
A23: Parasol horizontal fijo 1:2 | B23: 0.35
A24: Parasol horizontal fijo 1:1 | B24: 0.5
A25: Alero | B25: 0.6
A26: Cortina de enrollar exterior | B26: 0.25
A27: Persiana de madera | B27: 0.3
A28: Toldo | B28: 0.2
A29: SUPERFICIE VIDRIADA POR LOCAL (de la planilla de iluminacion y ventilacion)
A30: local | B30: ilum. (m2) | C30: vent. (m2)
A31: 01 - Cocina / comedor | B31: 16.95 | C31: 8.48
A32: 03 - Lavadero | B32: 10.5 | C32: 1.6
A33: 06 - Living / comedor | B33: 34.05 | C33: 15
A34: 07 - Hall / ingreso | B34: 10.5 | C34: 1.6
A35: 09 - Dormitorio suite | B35: 6 | C35: 3
A36: 13 - Dormitorio 1 | B36: 8.75 | C36: 4.38
A37: 14 - Estar / Playroom | B37: 5 | C37: 5
A38: 15 - Dormitorio 2 | B38: 3.75 | C38: 1.88
A39: 17 - Bano | B39: 1.875 | C39: 0.94
A40: TOTAL | B40: 97.38
A42: La suma da 97.38 m2 de superficie vidriada. El total de vanos de los cuatro planos de la Planilla 3 deberia dar ese orden: sirve de control.
A44: FACTOR DE EXPOSICION SOLAR MAXIMO ADMITIDO (Ordenanza 8757/11)
A45: orientacion | B45: FES max | C45: cuadrante | D45: observacion
A46: Norte | B46: 0.45 | C46: 341 a 20 grados | D46: Cuadrante Norte (NNE-NNO).
A47: Este | B47: 0.3 | C47: 21 a 160 grados | D47: Modificado a 0,39 por decreto de 2021. Verificar vigencia.
A48: Oeste | B48: 0.3 | C48: 201 a 340 grados | D48: Modificado a 0,39 por decreto de 2021. Verificar vigencia.
A49: Sur | B49: 0.9 | C49: 161 a 200 grados | D49: Cuadrante Sur (SSE-SSO).
A50: Noreste | B50: 0.3 | C50: cae en cuadrante Este | D50: 45 grados: entra en el cuadrante Este (21 a 160).
A51: Sudeste | B51: 0.3 | C51: cae en cuadrante Este | D51: 135 grados: entra en el cuadrante Este (21 a 160).
A52: Sudoeste | B52: 0.3 | C52: cae en cuadrante Oeste | D52: 225 grados: entra en el cuadrante Oeste (201 a 340).
A53: Noroeste | B53: 0.3 | C53: cae en cuadrante Oeste | D53: 315 grados: entra en el cuadrante Oeste (201 a 340).
A54: Horizontal | B54: 0.25 | C54: lucernarios | D54: Planos inclinados con angulo menor a 60 grados.
A56: La casa esta girada 45 grados respecto del norte, asi que NINGUNA de sus cuatro fachadas
A57: cae en el cuadrante Norte ni en el Sur: las cuatro entran en el cuadrante Este/Oeste, que es
A58: el mas exigente (0,30, o 0,39 segun la modificacion de 2021). Conviene confirmarlo en la
A59: Secretaria de Planeamiento antes de presentar: hay versiones distintas dando vueltas.
